2_Excercise/fullAdder.v
module fullAdder(a, b, cIn, sum, cOut);

//Define Inputs
input [3:0] a, b;
input cIn;

//Define Outputs
output reg [3:0] sum; //We need this to be a reg since it is begin changed within an @always block
output reg cOut; 

//Define wires or midway points
reg [4:0] tempOutput; //We need this to be a reg since it is begin changed within an @always block


always @(*) begin //The always @ (x) is for setting up a conditional, the * indicates that this points towards all inputs and outputs, think "when x changes, this block will activate"
    //Here we want to describe what we need to happen for the full adder to work 
    tempOutput = a + b;
    tempOutput = tempOutput + cIn; 

    sum = tempOutput[3:0];
    cOut = tempOutput[4];
end

endmodule

2_Excercise/fourFullAdder.v

`include "fullAdder.v"
module fourFullAdder(a, b, cIn, cOutFinal, sumFinal);

    //Initalize all the inputs
    input [15:0] a, b;
    input cIn;


    //Intialize all the wires since we are moving from one module to another
    wire [3:0] cOut; //These must be wire since they are the output of a fullAdder operation
    wire [15:0] sum;


    //Initailze all outputs
    output reg [3:0] cOutFinal;
    output reg [15:0] sumFinal;

    //Now we need to make sure that all the modules for the full adders are correctly made
    fullAdder zeroToThree (
        .a(a[3:0]),
        .b(b[3:0]),
        .cIn(cIn),
        .cOut(cOut[0]),
        .sum(sum[3:0])
    );

    fullAdder fourToSeven (
        .a(a[7:4]),
        .b(b[7:4]),
        .cIn(cOut[0]),
        .cOut(cOut[1]),
        .sum(sum[7:4])
    );

    fullAdder eightToEleven (
        .a(a[11:8]),
        .b(b[11:8]),
        .cIn(cOut[1]),
        .cOut(cOut[2]),
        .sum(sum[11:8])
    );


    fullAdder twelveToFifteen (
        .a(a[15:12]),
        .b(b[15:12]),
        .cIn(cOut[2]),
        .cOut(cOut[3]),
        .sum(sum[15:12])
    );

    //Whenever a change is detected, lets update our final updates
    always @(*) begin
        cOutFinal =  cOut;
        sumFinal = sum; 
    end


endmodule

2_Excercise/tb_fourFullAdder.v
`timescale 1ns/1ns
`include "fourFullAdder.v"
module tb_fourFullAdder(); 

    //Initalize the registers
    reg [15:0] a; 
    reg [15:0] b;
    reg cIn; 

    //Initalize the wires (outputs)
    wire [3:0] cOutFinal; 
    wire [15:0] sumFinal;

    //Intialize a fourFullAdderObject
    fourFullAdder fa(
        .a(a), 
        .b(b),
        .cIn(cIn),
        .cOutFinal(cOutFinal),
        .sumFinal(sumFinal)
    );
    
    //Define the clock 
    reg Clk; 

    //Get clock going
    always begin 
        Clk = 0;
        #1;
        Clk = 1; 
        #1;
    end

    integer i, j;
   // Test cases
    initial begin
        $dumpvars(0, tb_fourFullAdder); // To capture waveform data

        //Set the a input value
        a = 1;

        for (i = 0; i <= 15; i = i + 1) begin
            b = {i, 8'b00000000};

            cIn = 0;
            //Run the test case
            @(posedge Clk);

            //Check if it is equivalent or not
            if (a + {i, 8'b00000000} != sumFinal) begin
                $display("You Failed!: a=%d, b=%d, Value Expected=%d, Got=%d", a, {i, 8'b00000000}, a + i, sumFinal);
            end
        end
        
        // Forcing an error

        a = 16'b0000000000000000;
        b = 16'b0000000000000000; //We want blocking assingment so it is sequential logic
        cIn = 0;
        @(posedge Clk);

        //Forced error
        if (10 != sumFinal) begin
                    $display("You Failed!: a=%d, b=%d, Value Expected=%d, Got=%d", i, j, i + j, sumFinal);
        end
        /*
        // Test case 2: Add maximum values without carry-in
        a = 16'b1111111111111111;
        b = 16'b1111111111111111;
        cIn = 0;
        @(posedge Clk);

        // Test case 3: Add maximum values with carry-in
        a = 16'b1111111111111111;
        b = 16'b1111111111111111;
        cIn = 1;
        @(posedge Clk);

        // Test case 4: Add random values
        a = 16'b1010101010101010;
        b = 16'b0101010101010101;
        cIn = 1;
        @(posedge Clk);

        // Test case 5: Add alternating bits
        a = 16'b0000111100001111;
        b = 16'b1111000011110000;
        cIn = 0;
        
        a = 16'b1100101110101001;
        b = 16'b1000011101100101;
        cIn = 0;
        @(posedge Clk);
        */

        

        // Finish simulation
        $finish;
    end


endmodule

2_Excercise/dump.vcd
$date
	Mon Jan 27 10:32:35 2025
$end
$version
	Icarus Verilog
$end
$timescale
	1ns
$end
$scope module tb_fourFullAdder $end
$var wire 16 ! sumFinal [15:0] $end
$var wire 4 " cOutFinal [3:0] $end
$var reg 1 # Clk $end
$var reg 16 $ a [15:0] $end
$var reg 16 % b [15:0] $end
$var reg 1 & cIn $end
$var integer 32 ' i [31:0] $end
$var integer 32 ( j [31:0] $end
$scope module fa $end
$var wire 16 ) a [15:0] $end
$var wire 16 * b [15:0] $end
$var wire 1 & cIn $end
$var wire 16 + sum [15:0] $end
$var wire 4 , cOut [3:0] $end
$var reg 4 - cOutFinal [3:0] $end
$var reg 16 . sumFinal [15:0] $end
$scope module eightToEleven $end
$var wire 4 / a [3:0] $end
$var wire 4 0 b [3:0] $end
$var wire 1 1 cIn $end
$var reg 1 2 cOut $end
$var reg 4 3 sum [3:0] $end
$var reg 5 4 tempOutput [4:0] $end
$upscope $end
$scope module fourToSeven $end
$var wire 4 5 a [3:0] $end
$var wire 4 6 b [3:0] $end
$var wire 1 7 cIn $end
$var reg 1 8 cOut $end
$var reg 4 9 sum [3:0] $end
$var reg 5 : tempOutput [4:0] $end
$upscope $end
$scope module twelveToFifteen $end
$var wire 4 ; a [3:0] $end
$var wire 4 < b [3:0] $end
$var wire 1 = cIn $end
$var reg 1 > cOut $end
$var reg 4 ? sum [3:0] $end
$var reg 5 @ tempOutput [4:0] $end
$upscope $end
$scope module zeroToThree $end
$var wire 4 A a [3:0] $end
$var wire 4 B b [3:0] $end
$var wire 1 & cIn $end
$var reg 1 C cOut $end
$var reg 4 D sum [3:0] $end
$var reg 5 E tempOutput [4:0] $end
$upscope $end
$upscope $end
$upscope $end
$enddefinitions $end
$comment Show the parameter values. $end
$dumpall
$end
#0
$dumpvars
b1 E
b1 D
0C
b0 B
b1 A
b0 @
b0 ?
0>
0=
b0 <
b0 ;
b0 :
b0 9
08
07
b0 6
b0 5
b0 4
b0 3
02
01
b0 0
b0 /
b1 .
b0 -
b0 ,
b1 +
b0 *
b1 )
bx (
b0 '
0&
b0 %
b1 $
0#
b0 "
b1 !
$end
#1
b100000001 !
b100000001 .
b100000001 +
b1 3
b1 4
b1 0
b100000000 %
b100000000 *
b1 '
1#
#2
0#
#3
b1000000001 !
b1000000001 .
b1000000001 +
b10 3
b10 4
b10 0
b1000000000 %
b1000000000 *
b10 '
1#
#4
0#
#5
b1100000001 !
b1100000001 .
b1100000001 +
b11 3
b11 4
b11 0
b1100000000 %
b1100000000 *
b11 '
1#
#6
0#
#7
b10000000001 !
b10000000001 .
b10000000001 +
b100 3
b100 4
b100 0
b10000000000 %
b10000000000 *
b100 '
1#
#8
0#
#9
b10100000001 !
b10100000001 .
b10100000001 +
b101 3
b101 4
b101 0
b10100000000 %
b10100000000 *
b101 '
1#
#10
0#
#11
b11000000001 !
b11000000001 .
b11000000001 +
b110 3
b110 4
b110 0
b11000000000 %
b11000000000 *
b110 '
1#
#12
0#
#13
b11100000001 !
b11100000001 .
b11100000001 +
b111 3
b111 4
b111 0
b11100000000 %
b11100000000 *
b111 '
1#
#14
0#
#15
b100000000001 !
b100000000001 .
b100000000001 +
b1000 3
b1000 4
b1000 0
b100000000000 %
b100000000000 *
b1000 '
1#
#16
0#
#17
b100100000001 !
b100100000001 .
b100100000001 +
b1001 3
b1001 4
b1001 0
b100100000000 %
b100100000000 *
b1001 '
1#
#18
0#
#19
b101000000001 !
b101000000001 .
b101000000001 +
b1010 3
b1010 4
b1010 0
b101000000000 %
b101000000000 *
b1010 '
1#
#20
0#
#21
b101100000001 !
b101100000001 .
b101100000001 +
b1011 3
b1011 4
b1011 0
b101100000000 %
b101100000000 *
b1011 '
1#
#22
0#
#23
b110000000001 !
b110000000001 .
b110000000001 +
b1100 3
b1100 4
b1100 0
b110000000000 %
b110000000000 *
b1100 '
1#
#24
0#
#25
b110100000001 !
b110100000001 .
b110100000001 +
b1101 3
b1101 4
b1101 0
b110100000000 %
b110100000000 *
b1101 '
1#
#26
0#
#27
b111000000001 !
b111000000001 .
b111000000001 +
b1110 3
b1110 4
b1110 0
b111000000000 %
b111000000000 *
b1110 '
1#
#28
0#
#29
b111100000001 !
b111100000001 .
b111100000001 +
b1111 3
b1111 4
b1111 0
b111100000000 %
b111100000000 *
b1111 '
1#
#30
0#
#31
b0 !
b0 .
b0 3
b0 4
b0 +
b0 D
b0 E
b0 0
b0 A
b0 %
b0 *
b0 $
b0 )
b10000 '
1#
