2_Excercise/fullAdder.v
module fullAdder(a, b, cIn, sum, cOut);

//Define Inputs
input [3:0] a, b;
input cIn;

//Define Outputs
output reg [3:0] sum; //We need this to be a reg since it is begin changed within an @always block
output reg cOut; 

//Define wires or midway points
reg [4:0] tempOutput; //We need this to be a reg since it is begin changed within an @always block


always @(*) begin //The always @ (x) is for setting up a conditional, the * indicates that this points towards all inputs and outputs, think "when x changes, this block will activate"
    //Here we want to describe what we need to happen for the full adder to work 
    tempOutput = a + b;
    tempOutput = tempOutput + cIn; 

    sum = tempOutput[3:0];
    cOut = tempOutput[4];
end

endmodule

2_Excercise/fourFullAdder.v

`include "fullAdder.v"
module fourFullAdder(a, b, cIn, cOutFinal, sumFinal);

    //Initalize all the inputs
    input [15:0] a, b;
    input cIn;


    //Intialize all the wires since we are moving from one module to another
    wire [3:0] cOut; //These must be wire since they are the output of a fullAdder operation
    wire [15:0] sum;


    //Initailze all outputs
    output reg [3:0] cOutFinal;
    output reg [15:0] sumFinal;

    //Now we need to make sure that all the modules for the full adders are correctly made
    fullAdder zeroToThree (
        .a(a[3:0]),
        .b(b[3:0]),
        .cIn(cIn),
        .cOut(cOut[0]),
        .sum(sum[3:0])
    );

    fullAdder fourToSeven (
        .a(a[7:4]),
        .b(b[7:4]),
        .cIn(cOut[0]),
        .cOut(cOut[1]),
        .sum(sum[7:4])
    );

    fullAdder eightToEleven (
        .a(a[11:8]),
        .b(b[11:8]),
        .cIn(cOut[1]),
        .cOut(cOut[2]),
        .sum(sum[11:8])
    );


    fullAdder twelveToFifteen (
        .a(a[15:12]),
        .b(b[15:12]),
        .cIn(cOut[2]),
        .cOut(cOut[3]),
        .sum(sum[15:12])
    );

    //Whenever a change is detected, lets update our final updates
    always @(*) begin
        cOutFinal =  cOut;
        sumFinal = sum; 
    end


endmodule

2_Excercise/tb_fourFullAdder.v
`timescale 1ns/1ns
`include "fourFullAdder.v"
module tb_fourFullAdder(); 

    //Initalize the registers
    reg [15:0] a; 
    reg [15:0] b;
    reg cIn; 

    //Initalize the wires (outputs)
    wire [3:0] cOutFinal; 
    wire [15:0] sumFinal;

    //Wire for Self Checking
    reg rightWrong; 

    //Intialize a fourFullAdderObject
    fourFullAdder fa(
        .a(a), 
        .b(b),
        .cIn(cIn),
        .cOutFinal(cOutFinal),
        .sumFinal(sumFinal)
    );
    
    //Define the clock 
    reg Clk; 

    //Get clock going
    always begin 
        Clk = 0;
        #1;
        Clk = 1; 
        #1;
    end

    integer i, j;
   // Test cases
    initial begin
        $dumpvars(0, tb_fourFullAdder); // To capture waveform data

        //Set the a input value
        a = 1;
        for (j = 0; j < 100; j++) begin
            a = j;
            for (i = 0; i <= 15; i = i + 1) begin
                b = {i, 8'b00000000};

                cIn = 0;
                //Run the test case
                @(posedge Clk);

                //Check if it is equivalent or not
                if (a + {i, 8'b00000000} != sumFinal) begin
                    $display("You Failed!: a=%d, b=%d, Value Expected=%d, Got=%d", a, {i, 8'b00000000}, a + i, sumFinal);
                    rightWrong = 0; 
                end

                else begin
                    rightWrong = 1;
                end

                a++; 
            end
        end
        
        // Forcing an error

        a = 16'b0000000000000000;
        b = 16'b0000000000000000; //We want blocking assingment so it is sequential logic
        cIn = 0;
        @(posedge Clk);

        //Forced error
        if (10 != sumFinal) begin
                    $display("You Failed!: a=%d, b=%d, Value Expected=%d, Got=%d", a, b, 10, sumFinal);
                    rightWrong = 0; 
        end
        /*
        // Test case 2: Add maximum values without carry-in
        a = 16'b1111111111111111;
        b = 16'b1111111111111111;
        cIn = 0;
        @(posedge Clk);

        // Test case 3: Add maximum values with carry-in
        a = 16'b1111111111111111;
        b = 16'b1111111111111111;
        cIn = 1;
        @(posedge Clk);

        // Test case 4: Add random values
        a = 16'b1010101010101010;
        b = 16'b0101010101010101;
        cIn = 1;
        @(posedge Clk);

        // Test case 5: Add alternating bits
        a = 16'b0000111100001111;
        b = 16'b1111000011110000;
        cIn = 0;
        
        a = 16'b1100101110101001;
        b = 16'b1000011101100101;
        cIn = 0;
        @(posedge Clk);
        */

        

        // Finish simulation
        $finish;
    end


endmodule

2_Excercise/dump.vcd
$date
	Mon Jan 27 11:40:35 2025
$end
$version
	Icarus Verilog
$end
$timescale
	1ns
$end
$scope module tb_fourFullAdder $end
$var wire 16 ! sumFinal [15:0] $end
$var wire 4 " cOutFinal [3:0] $end
$var reg 1 # Clk $end
$var reg 16 $ a [15:0] $end
$var reg 16 % b [15:0] $end
$var reg 1 & cIn $end
$var reg 1 ' rightWrong $end
$var integer 32 ( i [31:0] $end
$var integer 32 ) j [31:0] $end
$scope module fa $end
$var wire 16 * a [15:0] $end
$var wire 16 + b [15:0] $end
$var wire 1 & cIn $end
$var wire 16 , sum [15:0] $end
$var wire 4 - cOut [3:0] $end
$var reg 4 . cOutFinal [3:0] $end
$var reg 16 / sumFinal [15:0] $end
$scope module eightToEleven $end
$var wire 4 0 a [3:0] $end
$var wire 4 1 b [3:0] $end
$var wire 1 2 cIn $end
$var reg 1 3 cOut $end
$var reg 4 4 sum [3:0] $end
$var reg 5 5 tempOutput [4:0] $end
$upscope $end
$scope module fourToSeven $end
$var wire 4 6 a [3:0] $end
$var wire 4 7 b [3:0] $end
$var wire 1 8 cIn $end
$var reg 1 9 cOut $end
$var reg 4 : sum [3:0] $end
$var reg 5 ; tempOutput [4:0] $end
$upscope $end
$scope module twelveToFifteen $end
$var wire 4 < a [3:0] $end
$var wire 4 = b [3:0] $end
$var wire 1 > cIn $end
$var reg 1 ? cOut $end
$var reg 4 @ sum [3:0] $end
$var reg 5 A tempOutput [4:0] $end
$upscope $end
$scope module zeroToThree $end
$var wire 4 B a [3:0] $end
$var wire 4 C b [3:0] $end
$var wire 1 & cIn $end
$var reg 1 D cOut $end
$var reg 4 E sum [3:0] $end
$var reg 5 F tempOutput [4:0] $end
$upscope $end
$upscope $end
$upscope $end
$enddefinitions $end
$comment Show the parameter values. $end
$dumpall
$end
#0
$dumpvars
b0 F
b0 E
0D
b0 C
b0 B
b0 A
b0 @
0?
0>
b0 =
b0 <
b0 ;
b0 :
09
08
b0 7
b0 6
b0 5
b0 4
03
02
b0 1
b0 0
b0 /
b0 .
b0 -
b0 ,
b0 +
b0 *
b0 )
b0 (
x'
0&
b0 %
b0 $
0#
b0 "
b0 !
$end
#1
b100000001 !
b100000001 /
b1 4
b1 5
b100000001 ,
b1 E
b1 F
b1 1
b1 B
b100000000 %
b100000000 +
b1 (
b1 $
b1 *
1'
1#
#2
0#
#3
b1000000010 !
b1000000010 /
b10 4
b10 5
b1000000010 ,
b10 E
b10 F
b10 1
b10 B
b1000000000 %
b1000000000 +
b10 (
b10 $
b10 *
1#
#4
0#
#5
b1100000011 !
b1100000011 /
b11 4
b11 5
b1100000011 ,
b11 E
b11 F
b11 1
b11 B
b1100000000 %
b1100000000 +
b11 (
b11 $
b11 *
1#
#6
0#
#7
b10000000100 !
b10000000100 /
b100 4
b100 5
b10000000100 ,
b100 E
b100 F
b100 1
b100 B
b10000000000 %
b10000000000 +
b100 (
b100 $
b100 *
1#
#8
0#
#9
b10100000101 !
b10100000101 /
b101 4
b101 5
b10100000101 ,
b101 E
b101 F
b101 1
b101 B
b10100000000 %
b10100000000 +
b101 (
b101 $
b101 *
1#
#10
0#
#11
b11000000110 !
b11000000110 /
b110 4
b110 5
b11000000110 ,
b110 E
b110 F
b110 1
b110 B
b11000000000 %
b11000000000 +
b110 (
b110 $
b110 *
1#
#12
0#
#13
b11100000111 !
b11100000111 /
b111 4
b111 5
b11100000111 ,
b111 E
b111 F
b111 1
b111 B
b11100000000 %
b11100000000 +
b111 (
b111 $
b111 *
1#
#14
0#
#15
b100000001000 !
b100000001000 /
b1000 4
b1000 5
b100000001000 ,
b1000 E
b1000 F
b1000 1
b1000 B
b100000000000 %
b100000000000 +
b1000 (
b1000 $
b1000 *
1#
#16
0#
#17
b100100001001 !
b100100001001 /
b1001 4
b1001 5
b100100001001 ,
b1001 E
b1001 F
b1001 1
b1001 B
b100100000000 %
b100100000000 +
b1001 (
b1001 $
b1001 *
1#
#18
0#
#19
b101000001010 !
b101000001010 /
b1010 4
b1010 5
b101000001010 ,
b1010 E
b1010 F
b1010 1
b1010 B
b101000000000 %
b101000000000 +
b1010 (
b1010 $
b1010 *
1#
#20
0#
#21
b101100001011 !
b101100001011 /
b1011 4
b1011 5
b101100001011 ,
b1011 E
b1011 F
b1011 1
b1011 B
b101100000000 %
b101100000000 +
b1011 (
b1011 $
b1011 *
1#
#22
0#
#23
b110000001100 !
b110000001100 /
b1100 4
b1100 5
b110000001100 ,
b1100 E
b1100 F
b1100 1
b1100 B
b110000000000 %
b110000000000 +
b1100 (
b1100 $
b1100 *
1#
#24
0#
#25
b110100001101 !
b110100001101 /
b1101 4
b1101 5
b110100001101 ,
b1101 E
b1101 F
b1101 1
b1101 B
b110100000000 %
b110100000000 +
b1101 (
b1101 $
b1101 *
1#
#26
0#
#27
b111000001110 !
b111000001110 /
b1110 4
b1110 5
b111000001110 ,
b1110 E
b1110 F
b1110 1
b1110 B
b111000000000 %
b111000000000 +
b1110 (
b1110 $
b1110 *
1#
#28
0#
#29
b111100001111 !
b111100001111 /
b1111 4
b1111 5
b111100001111 ,
b1111 E
b1111 F
b1111 1
b1111 B
b111100000000 %
b111100000000 +
b1111 (
b1111 $
b1111 *
1#
#30
0#
#31
b1 !
b1 /
b0 4
b0 5
b1 ,
b1 E
b1 F
b0 1
b1 B
b0 %
b0 +
b1 )
b0 (
b1 $
b1 *
1#
#32
0#
#33
b100000010 !
b100000010 /
b1 4
b1 5
b100000010 ,
b10 E
b10 F
b1 1
b10 B
b100000000 %
b100000000 +
b1 (
b10 $
b10 *
1#
#34
0#
#35
b1000000011 !
b1000000011 /
b10 4
b10 5
b1000000011 ,
b11 E
b11 F
b10 1
b11 B
b1000000000 %
b1000000000 +
b10 (
b11 $
b11 *
1#
#36
0#
#37
b1100000100 !
b1100000100 /
b11 4
b11 5
b1100000100 ,
b100 E
b100 F
b11 1
b100 B
b1100000000 %
b1100000000 +
b11 (
b100 $
b100 *
1#
#38
0#
#39
b10000000101 !
b10000000101 /
b100 4
b100 5
b10000000101 ,
b101 E
b101 F
b100 1
b101 B
b10000000000 %
b10000000000 +
b100 (
b101 $
b101 *
1#
#40
0#
#41
b10100000110 !
b10100000110 /
b101 4
b101 5
b10100000110 ,
b110 E
b110 F
b101 1
b110 B
b10100000000 %
b10100000000 +
b101 (
b110 $
b110 *
1#
#42
0#
#43
b11000000111 !
b11000000111 /
b110 4
b110 5
b11000000111 ,
b111 E
b111 F
b110 1
b111 B
b11000000000 %
b11000000000 +
b110 (
b111 $
b111 *
1#
#44
0#
#45
b11100001000 !
b11100001000 /
b111 4
b111 5
b11100001000 ,
b1000 E
b1000 F
b111 1
b1000 B
b11100000000 %
b11100000000 +
b111 (
b1000 $
b1000 *
1#
#46
0#
#47
b100000001001 !
b100000001001 /
b1000 4
b1000 5
b100000001001 ,
b1001 E
b1001 F
b1000 1
b1001 B
b100000000000 %
b100000000000 +
b1000 (
b1001 $
b1001 *
1#
#48
0#
#49
b100100001010 !
b100100001010 /
b1001 4
b1001 5
b100100001010 ,
b1010 E
b1010 F
b1001 1
b1010 B
b100100000000 %
b100100000000 +
b1001 (
b1010 $
b1010 *
1#
#50
0#
#51
b101000001011 !
b101000001011 /
b1010 4
b1010 5
b101000001011 ,
b1011 E
b1011 F
b1010 1
b1011 B
b101000000000 %
b101000000000 +
b1010 (
b1011 $
b1011 *
1#
#52
0#
#53
b101100001100 !
b101100001100 /
b1011 4
b1011 5
b101100001100 ,
b1100 E
b1100 F
b1011 1
b1100 B
b101100000000 %
b101100000000 +
b1011 (
b1100 $
b1100 *
1#
#54
0#
#55
b110000001101 !
b110000001101 /
b1100 4
b1100 5
b110000001101 ,
b1101 E
b1101 F
b1100 1
b1101 B
b110000000000 %
b110000000000 +
b1100 (
b1101 $
b1101 *
1#
#56
0#
#57
b110100001110 !
b110100001110 /
b1101 4
b1101 5
b110100001110 ,
b1110 E
b1110 F
b1101 1
b1110 B
b110100000000 %
b110100000000 +
b1101 (
b1110 $
b1110 *
1#
#58
0#
#59
b111000001111 !
b111000001111 /
b1110 4
b1110 5
b111000001111 ,
b1111 E
b1111 F
b1110 1
b1111 B
b111000000000 %
b111000000000 +
b1110 (
b1111 $
b1111 *
1#
#60
0#
#61
b111100010000 !
b111100010000 /
b1111 4
b1111 5
b0 E
b0 F
b111100010000 ,
b1 :
b1 ;
b1111 1
b0 B
b1 6
b111100000000 %
b111100000000 +
b1111 (
b10000 $
b10000 *
1#
#62
0#
#63
b10 !
b10 /
b0 4
b0 5
b0 :
b0 ;
b10 ,
b10 E
b10 F
b0 1
b0 6
b10 B
b0 %
b0 +
b10 )
b0 (
b10 $
b10 *
1#
#64
0#
#65
b100000011 !
b100000011 /
b1 4
b1 5
b100000011 ,
b11 E
b11 F
b1 1
b11 B
b100000000 %
b100000000 +
b1 (
b11 $
b11 *
1#
#66
0#
#67
b1000000100 !
b1000000100 /
b10 4
b10 5
b1000000100 ,
b100 E
b100 F
b10 1
b100 B
b1000000000 %
b1000000000 +
b10 (
b100 $
b100 *
1#
#68
0#
#69
b1100000101 !
b1100000101 /
b11 4
b11 5
b1100000101 ,
b101 E
b101 F
b11 1
b101 B
b1100000000 %
b1100000000 +
b11 (
b101 $
b101 *
1#
#70
0#
#71
b10000000110 !
b10000000110 /
b100 4
b100 5
b10000000110 ,
b110 E
b110 F
b100 1
b110 B
b10000000000 %
b10000000000 +
b100 (
b110 $
b110 *
1#
#72
0#
#73
b10100000111 !
b10100000111 /
b101 4
b101 5
b10100000111 ,
b111 E
b111 F
b101 1
b111 B
b10100000000 %
b10100000000 +
b101 (
b111 $
b111 *
1#
#74
0#
#75
b11000001000 !
b11000001000 /
b110 4
b110 5
b11000001000 ,
b1000 E
b1000 F
b110 1
b1000 B
b11000000000 %
b11000000000 +
b110 (
b1000 $
b1000 *
1#
#76
0#
#77
b11100001001 !
b11100001001 /
b111 4
b111 5
b11100001001 ,
b1001 E
b1001 F
b111 1
b1001 B
b11100000000 %
b11100000000 +
b111 (
b1001 $
b1001 *
1#
#78
0#
#79
b100000001010 !
b100000001010 /
b1000 4
b1000 5
b100000001010 ,
b1010 E
b1010 F
b1000 1
b1010 B
b100000000000 %
b100000000000 +
b1000 (
b1010 $
b1010 *
1#
#80
0#
#81
b100100001011 !
b100100001011 /
b1001 4
b1001 5
b100100001011 ,
b1011 E
b1011 F
b1001 1
b1011 B
b100100000000 %
b100100000000 +
b1001 (
b1011 $
b1011 *
1#
#82
0#
#83
b101000001100 !
b101000001100 /
b1010 4
b1010 5
b101000001100 ,
b1100 E
b1100 F
b1010 1
b1100 B
b101000000000 %
b101000000000 +
b1010 (
b1100 $
b1100 *
1#
#84
0#
#85
b101100001101 !
b101100001101 /
b1011 4
b1011 5
b101100001101 ,
b1101 E
b1101 F
b1011 1
b1101 B
b101100000000 %
b101100000000 +
b1011 (
b1101 $
b1101 *
1#
#86
0#
#87
b110000001110 !
b110000001110 /
b1100 4
b1100 5
b110000001110 ,
b1110 E
b1110 F
b1100 1
b1110 B
b110000000000 %
b110000000000 +
b1100 (
b1110 $
b1110 *
1#
#88
0#
#89
b110100001111 !
b110100001111 /
b1101 4
b1101 5
b110100001111 ,
b1111 E
b1111 F
b1101 1
b1111 B
b110100000000 %
b110100000000 +
b1101 (
b1111 $
b1111 *
1#
#90
0#
#91
b111000010000 !
b111000010000 /
b1110 4
b1110 5
b0 E
b0 F
b111000010000 ,
b1 :
b1 ;
b1110 1
b0 B
b1 6
b111000000000 %
b111000000000 +
b1110 (
b10000 $
b10000 *
1#
#92
0#
#93
b111100010001 !
b111100010001 /
b1111 4
b1111 5
b111100010001 ,
b1 E
b1 F
b1111 1
b1 B
b111100000000 %
b111100000000 +
b1111 (
b10001 $
b10001 *
1#
#94
0#
#95
b11 !
b11 /
b0 4
b0 5
b0 :
b0 ;
b11 ,
b11 E
b11 F
b0 1
b0 6
b11 B
b0 %
b0 +
b11 )
b0 (
b11 $
b11 *
1#
#96
0#
#97
b100000100 !
b100000100 /
b1 4
b1 5
b100000100 ,
b100 E
b100 F
b1 1
b100 B
b100000000 %
b100000000 +
b1 (
b100 $
b100 *
1#
#98
0#
#99
b1000000101 !
b1000000101 /
b10 4
b10 5
b1000000101 ,
b101 E
b101 F
b10 1
b101 B
b1000000000 %
b1000000000 +
b10 (
b101 $
b101 *
1#
#100
0#
#101
b1100000110 !
b1100000110 /
b11 4
b11 5
b1100000110 ,
b110 E
b110 F
b11 1
b110 B
b1100000000 %
b1100000000 +
b11 (
b110 $
b110 *
1#
#102
0#
#103
b10000000111 !
b10000000111 /
b100 4
b100 5
b10000000111 ,
b111 E
b111 F
b100 1
b111 B
b10000000000 %
b10000000000 +
b100 (
b111 $
b111 *
1#
#104
0#
#105
b10100001000 !
b10100001000 /
b101 4
b101 5
b10100001000 ,
b1000 E
b1000 F
b101 1
b1000 B
b10100000000 %
b10100000000 +
b101 (
b1000 $
b1000 *
1#
#106
0#
#107
b11000001001 !
b11000001001 /
b110 4
b110 5
b11000001001 ,
b1001 E
b1001 F
b110 1
b1001 B
b11000000000 %
b11000000000 +
b110 (
b1001 $
b1001 *
1#
#108
0#
#109
b11100001010 !
b11100001010 /
b111 4
b111 5
b11100001010 ,
b1010 E
b1010 F
b111 1
b1010 B
b11100000000 %
b11100000000 +
b111 (
b1010 $
b1010 *
1#
#110
0#
#111
b100000001011 !
b100000001011 /
b1000 4
b1000 5
b100000001011 ,
b1011 E
b1011 F
b1000 1
b1011 B
b100000000000 %
b100000000000 +
b1000 (
b1011 $
b1011 *
1#
#112
0#
#113
b100100001100 !
b100100001100 /
b1001 4
b1001 5
b100100001100 ,
b1100 E
b1100 F
b1001 1
b1100 B
b100100000000 %
b100100000000 +
b1001 (
b1100 $
b1100 *
1#
#114
0#
#115
b101000001101 !
b101000001101 /
b1010 4
b1010 5
b101000001101 ,
b1101 E
b1101 F
b1010 1
b1101 B
b101000000000 %
b101000000000 +
b1010 (
b1101 $
b1101 *
1#
#116
0#
#117
b101100001110 !
b101100001110 /
b1011 4
b1011 5
b101100001110 ,
b1110 E
b1110 F
b1011 1
b1110 B
b101100000000 %
b101100000000 +
b1011 (
b1110 $
b1110 *
1#
#118
0#
#119
b110000001111 !
b110000001111 /
b1100 4
b1100 5
b110000001111 ,
b1111 E
b1111 F
b1100 1
b1111 B
b110000000000 %
b110000000000 +
b1100 (
b1111 $
b1111 *
1#
#120
0#
#121
b110100010000 !
b110100010000 /
b1101 4
b1101 5
b0 E
b0 F
b110100010000 ,
b1 :
b1 ;
b1101 1
b0 B
b1 6
b110100000000 %
b110100000000 +
b1101 (
b10000 $
b10000 *
1#
#122
0#
#123
b111000010001 !
b111000010001 /
b1110 4
b1110 5
b111000010001 ,
b1 E
b1 F
b1110 1
b1 B
b111000000000 %
b111000000000 +
b1110 (
b10001 $
b10001 *
1#
#124
0#
#125
b111100010010 !
b111100010010 /
b1111 4
b1111 5
b111100010010 ,
b10 E
b10 F
b1111 1
b10 B
b111100000000 %
b111100000000 +
b1111 (
b10010 $
b10010 *
1#
#126
0#
#127
b100 !
b100 /
b0 4
b0 5
b0 :
b0 ;
b100 ,
b100 E
b100 F
b0 1
b0 6
b100 B
b0 %
b0 +
b100 )
b0 (
b100 $
b100 *
1#
#128
0#
#129
b100000101 !
b100000101 /
b1 4
b1 5
b100000101 ,
b101 E
b101 F
b1 1
b101 B
b100000000 %
b100000000 +
b1 (
b101 $
b101 *
1#
#130
0#
#131
b1000000110 !
b1000000110 /
b10 4
b10 5
b1000000110 ,
b110 E
b110 F
b10 1
b110 B
b1000000000 %
b1000000000 +
b10 (
b110 $
b110 *
1#
#132
0#
#133
b1100000111 !
b1100000111 /
b11 4
b11 5
b1100000111 ,
b111 E
b111 F
b11 1
b111 B
b1100000000 %
b1100000000 +
b11 (
b111 $
b111 *
1#
#134
0#
#135
b10000001000 !
b10000001000 /
b100 4
b100 5
b10000001000 ,
b1000 E
b1000 F
b100 1
b1000 B
b10000000000 %
b10000000000 +
b100 (
b1000 $
b1000 *
1#
#136
0#
#137
b10100001001 !
b10100001001 /
b101 4
b101 5
b10100001001 ,
b1001 E
b1001 F
b101 1
b1001 B
b10100000000 %
b10100000000 +
b101 (
b1001 $
b1001 *
1#
#138
0#
#139
b11000001010 !
b11000001010 /
b110 4
b110 5
b11000001010 ,
b1010 E
b1010 F
b110 1
b1010 B
b11000000000 %
b11000000000 +
b110 (
b1010 $
b1010 *
1#
#140
0#
#141
b11100001011 !
b11100001011 /
b111 4
b111 5
b11100001011 ,
b1011 E
b1011 F
b111 1
b1011 B
b11100000000 %
b11100000000 +
b111 (
b1011 $
b1011 *
1#
#142
0#
#143
b100000001100 !
b100000001100 /
b1000 4
b1000 5
b100000001100 ,
b1100 E
b1100 F
b1000 1
b1100 B
b100000000000 %
b100000000000 +
b1000 (
b1100 $
b1100 *
1#
#144
0#
#145
b100100001101 !
b100100001101 /
b1001 4
b1001 5
b100100001101 ,
b1101 E
b1101 F
b1001 1
b1101 B
b100100000000 %
b100100000000 +
b1001 (
b1101 $
b1101 *
1#
#146
0#
#147
b101000001110 !
b101000001110 /
b1010 4
b1010 5
b101000001110 ,
b1110 E
b1110 F
b1010 1
b1110 B
b101000000000 %
b101000000000 +
b1010 (
b1110 $
b1110 *
1#
#148
0#
#149
b101100001111 !
b101100001111 /
b1011 4
b1011 5
b101100001111 ,
b1111 E
b1111 F
b1011 1
b1111 B
b101100000000 %
b101100000000 +
b1011 (
b1111 $
b1111 *
1#
#150
0#
#151
b110000010000 !
b110000010000 /
b1100 4
b1100 5
b0 E
b0 F
b110000010000 ,
b1 :
b1 ;
b1100 1
b0 B
b1 6
b110000000000 %
b110000000000 +
b1100 (
b10000 $
b10000 *
1#
#152
0#
#153
b110100010001 !
b110100010001 /
b1101 4
b1101 5
b110100010001 ,
b1 E
b1 F
b1101 1
b1 B
b110100000000 %
b110100000000 +
b1101 (
b10001 $
b10001 *
1#
#154
0#
#155
b111000010010 !
b111000010010 /
b1110 4
b1110 5
b111000010010 ,
b10 E
b10 F
b1110 1
b10 B
b111000000000 %
b111000000000 +
b1110 (
b10010 $
b10010 *
1#
#156
0#
#157
b111100010011 !
b111100010011 /
b1111 4
b1111 5
b111100010011 ,
b11 E
b11 F
b1111 1
b11 B
b111100000000 %
b111100000000 +
b1111 (
b10011 $
b10011 *
1#
#158
0#
#159
b101 !
b101 /
b0 4
b0 5
b0 :
b0 ;
b101 ,
b101 E
b101 F
b0 1
b0 6
b101 B
b0 %
b0 +
b101 )
b0 (
b101 $
b101 *
1#
#160
0#
#161
b100000110 !
b100000110 /
b1 4
b1 5
b100000110 ,
b110 E
b110 F
b1 1
b110 B
b100000000 %
b100000000 +
b1 (
b110 $
b110 *
1#
#162
0#
#163
b1000000111 !
b1000000111 /
b10 4
b10 5
b1000000111 ,
b111 E
b111 F
b10 1
b111 B
b1000000000 %
b1000000000 +
b10 (
b111 $
b111 *
1#
#164
0#
#165
b1100001000 !
b1100001000 /
b11 4
b11 5
b1100001000 ,
b1000 E
b1000 F
b11 1
b1000 B
b1100000000 %
b1100000000 +
b11 (
b1000 $
b1000 *
1#
#166
0#
#167
b10000001001 !
b10000001001 /
b100 4
b100 5
b10000001001 ,
b1001 E
b1001 F
b100 1
b1001 B
b10000000000 %
b10000000000 +
b100 (
b1001 $
b1001 *
1#
#168
0#
#169
b10100001010 !
b10100001010 /
b101 4
b101 5
b10100001010 ,
b1010 E
b1010 F
b101 1
b1010 B
b10100000000 %
b10100000000 +
b101 (
b1010 $
b1010 *
1#
#170
0#
#171
b11000001011 !
b11000001011 /
b110 4
b110 5
b11000001011 ,
b1011 E
b1011 F
b110 1
b1011 B
b11000000000 %
b11000000000 +
b110 (
b1011 $
b1011 *
1#
#172
0#
#173
b11100001100 !
b11100001100 /
b111 4
b111 5
b11100001100 ,
b1100 E
b1100 F
b111 1
b1100 B
b11100000000 %
b11100000000 +
b111 (
b1100 $
b1100 *
1#
#174
0#
#175
b100000001101 !
b100000001101 /
b1000 4
b1000 5
b100000001101 ,
b1101 E
b1101 F
b1000 1
b1101 B
b100000000000 %
b100000000000 +
b1000 (
b1101 $
b1101 *
1#
#176
0#
#177
b100100001110 !
b100100001110 /
b1001 4
b1001 5
b100100001110 ,
b1110 E
b1110 F
b1001 1
b1110 B
b100100000000 %
b100100000000 +
b1001 (
b1110 $
b1110 *
1#
#178
0#
#179
b101000001111 !
b101000001111 /
b1010 4
b1010 5
b101000001111 ,
b1111 E
b1111 F
b1010 1
b1111 B
b101000000000 %
b101000000000 +
b1010 (
b1111 $
b1111 *
1#
#180
0#
#181
b101100010000 !
b101100010000 /
b1011 4
b1011 5
b0 E
b0 F
b101100010000 ,
b1 :
b1 ;
b1011 1
b0 B
b1 6
b101100000000 %
b101100000000 +
b1011 (
b10000 $
b10000 *
1#
#182
0#
#183
b110000010001 !
b110000010001 /
b1100 4
b1100 5
b110000010001 ,
b1 E
b1 F
b1100 1
b1 B
b110000000000 %
b110000000000 +
b1100 (
b10001 $
b10001 *
1#
#184
0#
#185
b110100010010 !
b110100010010 /
b1101 4
b1101 5
b110100010010 ,
b10 E
b10 F
b1101 1
b10 B
b110100000000 %
b110100000000 +
b1101 (
b10010 $
b10010 *
1#
#186
0#
#187
b111000010011 !
b111000010011 /
b1110 4
b1110 5
b111000010011 ,
b11 E
b11 F
b1110 1
b11 B
b111000000000 %
b111000000000 +
b1110 (
b10011 $
b10011 *
1#
#188
0#
#189
b111100010100 !
b111100010100 /
b1111 4
b1111 5
b111100010100 ,
b100 E
b100 F
b1111 1
b100 B
b111100000000 %
b111100000000 +
b1111 (
b10100 $
b10100 *
1#
#190
0#
#191
b110 !
b110 /
b0 4
b0 5
b0 :
b0 ;
b110 ,
b110 E
b110 F
b0 1
b0 6
b110 B
b0 %
b0 +
b110 )
b0 (
b110 $
b110 *
1#
#192
0#
#193
b100000111 !
b100000111 /
b1 4
b1 5
b100000111 ,
b111 E
b111 F
b1 1
b111 B
b100000000 %
b100000000 +
b1 (
b111 $
b111 *
1#
#194
0#
#195
b1000001000 !
b1000001000 /
b10 4
b10 5
b1000001000 ,
b1000 E
b1000 F
b10 1
b1000 B
b1000000000 %
b1000000000 +
b10 (
b1000 $
b1000 *
1#
#196
0#
#197
b1100001001 !
b1100001001 /
b11 4
b11 5
b1100001001 ,
b1001 E
b1001 F
b11 1
b1001 B
b1100000000 %
b1100000000 +
b11 (
b1001 $
b1001 *
1#
#198
0#
#199
b10000001010 !
b10000001010 /
b100 4
b100 5
b10000001010 ,
b1010 E
b1010 F
b100 1
b1010 B
b10000000000 %
b10000000000 +
b100 (
b1010 $
b1010 *
1#
#200
0#
#201
b10100001011 !
b10100001011 /
b101 4
b101 5
b10100001011 ,
b1011 E
b1011 F
b101 1
b1011 B
b10100000000 %
b10100000000 +
b101 (
b1011 $
b1011 *
1#
#202
0#
#203
b11000001100 !
b11000001100 /
b110 4
b110 5
b11000001100 ,
b1100 E
b1100 F
b110 1
b1100 B
b11000000000 %
b11000000000 +
b110 (
b1100 $
b1100 *
1#
#204
0#
#205
b11100001101 !
b11100001101 /
b111 4
b111 5
b11100001101 ,
b1101 E
b1101 F
b111 1
b1101 B
b11100000000 %
b11100000000 +
b111 (
b1101 $
b1101 *
1#
#206
0#
#207
b100000001110 !
b100000001110 /
b1000 4
b1000 5
b100000001110 ,
b1110 E
b1110 F
b1000 1
b1110 B
b100000000000 %
b100000000000 +
b1000 (
b1110 $
b1110 *
1#
#208
0#
#209
b100100001111 !
b100100001111 /
b1001 4
b1001 5
b100100001111 ,
b1111 E
b1111 F
b1001 1
b1111 B
b100100000000 %
b100100000000 +
b1001 (
b1111 $
b1111 *
1#
#210
0#
#211
b101000010000 !
b101000010000 /
b1010 4
b1010 5
b0 E
b0 F
b101000010000 ,
b1 :
b1 ;
b1010 1
b0 B
b1 6
b101000000000 %
b101000000000 +
b1010 (
b10000 $
b10000 *
1#
#212
0#
#213
b101100010001 !
b101100010001 /
b1011 4
b1011 5
b101100010001 ,
b1 E
b1 F
b1011 1
b1 B
b101100000000 %
b101100000000 +
b1011 (
b10001 $
b10001 *
1#
#214
0#
#215
b110000010010 !
b110000010010 /
b1100 4
b1100 5
b110000010010 ,
b10 E
b10 F
b1100 1
b10 B
b110000000000 %
b110000000000 +
b1100 (
b10010 $
b10010 *
1#
#216
0#
#217
b110100010011 !
b110100010011 /
b1101 4
b1101 5
b110100010011 ,
b11 E
b11 F
b1101 1
b11 B
b110100000000 %
b110100000000 +
b1101 (
b10011 $
b10011 *
1#
#218
0#
#219
b111000010100 !
b111000010100 /
b1110 4
b1110 5
b111000010100 ,
b100 E
b100 F
b1110 1
b100 B
b111000000000 %
b111000000000 +
b1110 (
b10100 $
b10100 *
1#
#220
0#
#221
b111100010101 !
b111100010101 /
b1111 4
b1111 5
b111100010101 ,
b101 E
b101 F
b1111 1
b101 B
b111100000000 %
b111100000000 +
b1111 (
b10101 $
b10101 *
1#
#222
0#
#223
b111 !
b111 /
b0 4
b0 5
b0 :
b0 ;
b111 ,
b111 E
b111 F
b0 1
b0 6
b111 B
b0 %
b0 +
b111 )
b0 (
b111 $
b111 *
1#
#224
0#
#225
b100001000 !
b100001000 /
b1 4
b1 5
b100001000 ,
b1000 E
b1000 F
b1 1
b1000 B
b100000000 %
b100000000 +
b1 (
b1000 $
b1000 *
1#
#226
0#
#227
b1000001001 !
b1000001001 /
b10 4
b10 5
b1000001001 ,
b1001 E
b1001 F
b10 1
b1001 B
b1000000000 %
b1000000000 +
b10 (
b1001 $
b1001 *
1#
#228
0#
