final_Project/read_fifo.v
module read_fifo(signalReady, dataIn, readBegin, clk, dataOut, rxDone);
    input signalReady; 
    input [7:0] dataIn;
    input readBegin;  
    input clk; 

    output reg [31:0] dataOut; 
    output reg rxDone; 

    //Function for LUT
    function [3:0] ascii_to_hex;
        input [7:0] ascii_char;
        begin
            case (ascii_char)
                8'h30: ascii_to_hex = 4'h0;  // '0'
                8'h31: ascii_to_hex = 4'h1;  // '1'
                8'h32: ascii_to_hex = 4'h2;  // '2'
                8'h33: ascii_to_hex = 4'h3;  // '3'
                8'h34: ascii_to_hex = 4'h4;  // '4'
                8'h35: ascii_to_hex = 4'h5;  // '5'
                8'h36: ascii_to_hex = 4'h6;  // '6'
                8'h37: ascii_to_hex = 4'h7;  // '7'
                8'h38: ascii_to_hex = 4'h8;  // '8'
                8'h39: ascii_to_hex = 4'h9;  // '9'
                8'h41: ascii_to_hex = 4'hA;  // 'A'
                8'h42: ascii_to_hex = 4'hB;  // 'B'
                8'h43: ascii_to_hex = 4'hC;  // 'C'
                8'h44: ascii_to_hex = 4'hD;  // 'D'
                8'h45: ascii_to_hex = 4'hE;  // 'E'
                8'h46: ascii_to_hex = 4'hF;  // 'F'
                8'h61: ascii_to_hex = 4'hA;  // 'a'
                8'h62: ascii_to_hex = 4'hB;  // 'b'
                8'h63: ascii_to_hex = 4'hC;  // 'c'
                8'h64: ascii_to_hex = 4'hD;  // 'd'
                8'h65: ascii_to_hex = 4'hE;  // 'e'
                8'h66: ascii_to_hex = 4'hF;  // 'f'
                default: ascii_to_hex = 4'h0;
            endcase
        end
    endfunction


    //Make registers here: 
    reg [7:0] fifoRegister [0:31];
    reg [7:0] byteRegister [0:8];

    reg [5:0] counter; 
    reg [5:0] byteCounter;

    reg [5:0] passoverCounter;
    reg [5:0] insertCounter;   

    reg [3:0] topNibble; 
    reg [3:0] bottomNibble; 
    reg [7:0] fullByte; 
    
    reg [7:0] rpmParam1; 
    reg [7:0] rpmParam2; 

    reg [7:0] coolantParam; 

    reg nibbleFormed; 
    reg coolantFound; 
    reg rpmFound; 
    //Make the states

    //The idea for the states is that we should enter an idle state when we don't need to be reciving any data
    //The next state is the load state where we essentially take in the byte of memory and put it in the fifo
    //The last state is the passover state where we will give all the data to the main code to decode and well worry about that later
    //We also might need a wait state to wait for signals to go low 

    parameter sIdle = 0, sLoad = 1, sPassover = 2, sWait = 3, sCalc = 4;  

    reg [2:0] state, stateNext; 


    always @(posedge clk) begin 
        //Default
        state = stateNext; 
        
        //Case statements
        case(state) 
            sIdle: begin 
                //For this we need to watch the signalReady input
                if (readBegin) begin 
                    //This means that we are ready to accept data and we need to move into the next state; 
                    counter = 0; 
                    stateNext = sLoad; 
                end else begin 
                    stateNext = sIdle; 
                    rxDone = 0; 
                end
            end

            sLoad: begin
                if (signalReady) begin 
                    //Now what we need to do is look for the dataOut
                    if (dataIn == 8'h3E) begin 
                        //This means that we can take the data from fifoRegister and start decoding it
                        fifoRegister[counter] = dataIn; 
                        counter++; 
                        stateNext = sPassover; 

                        coolantFound = 0; 
                        rpmFound = 0; 
                        passoverCounter = 0;
                        insertCounter = 0;  
                        byteCounter = 0; 

                    end else begin
                        stateNext = sWait; 
                        //Now what we need to do is load in the data and send the fsm to a wait state
                        //Load the new data in 
                        fifoRegister[counter] = dataIn; 
                        counter = counter + 1; 
                    end
                end else begin 
                    stateNext = sLoad; 
                end
            end

            sWait: begin 
                if (signalReady) begin 
                    stateNext = sWait; 
                end else begin 
                    stateNext = sLoad; 
                end
            end

            sPassover: begin 
                //Now in the passover phase what we need to do is use a lookup table to find what things we need to send over
                if (passoverCounter < counter) begin
                    stateNext = sPassover; 
                    
                    //Now we need to build up our nibbles
                    if (fifoRegister[passoverCounter] != 8'h20 && fifoRegister[passoverCounter] != 8'h0D && fifoRegister[passoverCounter] != 8'h3E) begin 
                        $display("fifoReg:", fifoRegister[passoverCounter], " passoverCounter", passoverCounter);
                        if (insertCounter % 2 == 0) begin 
                            //This means that it is even so it will go in firstNibble
                            topNibble = ascii_to_hex(fifoRegister[passoverCounter]);
                            
                            insertCounter = insertCounter + 1; 
                            passoverCounter = passoverCounter + 1; 
                        end else if (insertCounter % 2 == 1) begin 
                            //This means that it is odd so it should fill out the second nibble and analyze
                            bottomNibble = ascii_to_hex(fifoRegister[passoverCounter]);

                            insertCounter = insertCounter + 1; 
                            passoverCounter = passoverCounter + 1; 

                            //Now lets build our byte
                            fullByte = {topNibble, bottomNibble}; 
                            
                            byteRegister[byteCounter] = fullByte; 
                            byteCounter++; 
                        end
                    end else begin 
                        passoverCounter = passoverCounter + 1; 
                    end 

                end else begin 
                    stateNext = sCalc; 
                end
            
            end

            sCalc: begin 
                //Here we need to make sure that we have all the right numbers
                
                if (byteRegister[0] == 8'h41) begin 
                     
                    if (byteRegister[1] == 8'h0C) begin 
                        dataOut = ((256 * byteRegister[2] * byteRegister[3]) >> 2);
                        rxDone = 1; 
                    end else if (byteRegister[1] == 8'h05) begin
                        dataOut = byteRegister[2] - 40; 
                        dataOut[31] = 1; 

                        rxDone = 1; 
                    end
                end

                rxDone = 1; 
                stateNext = sIdle; 
            end

            default: begin 
                stateNext = sIdle; 
            end
        endcase

    end

   

endmodule

final_Project/testBenches/tb_read_fifo.v
`timescale 1ns / 1ps
`include "../read_fifo.v"
module read_fifo_tb;

    // Inputs
    reg clk;
    reg signalReady;
    reg [7:0] dataIn;
    reg readBegin;

    // Outputs
    wire [31:0] dataOut;
    wire rxDone;

    // Instantiate the Unit Under Test (UUT)
    read_fifo uut (
        .clk(clk),
        .signalReady(signalReady),
        .dataIn(dataIn),
        .readBegin(readBegin),
        .dataOut(dataOut),
        .rxDone(rxDone)
    );

    // Clock generation
    always #5 clk = ~clk; // 100MHz clock (10ns period)

    // Task to send a byte with signalReady pulse
    task send_byte;
        input [7:0] byte;
        begin
            dataIn = byte;
            signalReady = 1;
            #10;
            signalReady = 0;
            #10;
        end
    endtask

    initial begin
        $dumpvars(0, read_fifo_tb);
        // Initialize Inputs
        clk = 0;
        signalReady = 0;
        dataIn = 8'h00;
        readBegin = 0;

        // Wait for global reset
        #20;

        // Begin reading
        readBegin = 1;
        #10;
        readBegin = 0;

        // Send ELM327 response: "41 05 5A >"
        send_byte("4"); // '4'
        send_byte("1"); // '1'
        send_byte(8'h20); // SPACE
        send_byte("0");
        send_byte("5");
        send_byte(8'h20);
        send_byte("5");
        send_byte("A");
        send_byte(8'h20);
        send_byte(8'h3E); // '>'
        send_byte(8'h0D); // '


        // Wait to process
        #200;

        $display("rxDone = %b, dataOut = %h", rxDone, dataOut);
        $finish;
    end

endmodule

final_Project/testBenches/dump.vcd
$date
	Tue Apr 15 21:49:57 2025
$end
$version
	Icarus Verilog
$end
$timescale
	1ps
$end
$scope module read_fifo_tb $end
$var wire 1 ! rxDone $end
$var wire 32 " dataOut [31:0] $end
$var reg 1 # clk $end
$var reg 8 $ dataIn [7:0] $end
$var reg 1 % readBegin $end
$var reg 1 & signalReady $end
$scope module uut $end
$var wire 1 # clk $end
$var wire 8 ' dataIn [7:0] $end
$var wire 1 % readBegin $end
$var wire 1 & signalReady $end
$var parameter 32 ( sCalc $end
$var parameter 32 ) sIdle $end
$var parameter 32 * sLoad $end
$var parameter 32 + sPassover $end
$var parameter 32 , sWait $end
$var reg 4 - bottomNibble [3:0] $end
$var reg 6 . byteCounter [5:0] $end
$var reg 1 / coolantFound $end
$var reg 6 0 counter [5:0] $end
$var reg 32 1 dataOut [31:0] $end
$var reg 8 2 fullByte [7:0] $end
$var reg 6 3 insertCounter [5:0] $end
$var reg 6 4 passoverCounter [5:0] $end
$var reg 1 5 rpmFound $end
$var reg 1 ! rxDone $end
$var reg 3 6 state [2:0] $end
$var reg 3 7 stateNext [2:0] $end
$var reg 4 8 topNibble [3:0] $end
$scope function ascii_to_hex $end
$var reg 8 9 ascii_char [7:0] $end
$upscope $end
$upscope $end
$scope task send_byte $end
$var reg 8 : byte [7:0] $end
$upscope $end
$upscope $end
$enddefinitions $end
$comment Show the parameter values. $end
$dumpall
b11 ,
b10 +
b1 *
b0 )
b100 (
$end
#0
$dumpvars
bx :
bx 9
bx 8
bx 7
bx 6
x5
bx 4
bx 3
bx 2
bx 1
bx 0
x/
bx .
bx -
b0 '
0&
0%
b0 $
0#
bx "
x!
$end
#5000
b0 7
1#
#10000
0#
#15000
0!
b0 6
1#
#20000
0#
1%
#25000
b1 7
b0 0
1#
#30000
0#
1&
b110100 $
b110100 '
b110100 :
0%
#35000
b1 0
b11 7
b1 6
1#
#40000
0#
0&
#45000
b1 7
b11 6
1#
#50000
0#
1&
b110001 $
b110001 '
b110001 :
#55000
b10 0
b11 7
b1 6
1#
#60000
0#
0&
#65000
b1 7
b11 6
1#
#70000
0#
1&
b100000 $
b100000 '
b100000 :
#75000
b11 0
b11 7
b1 6
1#
#80000
0#
0&
#85000
b1 7
b11 6
1#
#90000
0#
1&
b110000 $
b110000 '
b110000 :
#95000
b100 0
b11 7
b1 6
1#
#100000
0#
0&
#105000
b1 7
b11 6
1#
#110000
0#
1&
b110101 $
b110101 '
b110101 :
#115000
b101 0
b11 7
b1 6
1#
#120000
0#
0&
#125000
b1 7
b11 6
1#
#130000
0#
1&
b100000 $
b100000 '
b100000 :
#135000
b110 0
b11 7
b1 6
1#
#140000
0#
0&
#145000
b1 7
b11 6
1#
#150000
0#
1&
b110101 $
b110101 '
b110101 :
#155000
b111 0
b11 7
b1 6
1#
#160000
0#
0&
#165000
b1 7
b11 6
1#
#170000
0#
1&
b1000001 $
b1000001 '
b1000001 :
#175000
b1000 0
b11 7
b1 6
1#
#180000
0#
0&
#185000
b1 7
b11 6
1#
#190000
0#
1&
b100000 $
b100000 '
b100000 :
#195000
b1001 0
b11 7
b1 6
1#
#200000
0#
0&
#205000
b1 7
b11 6
1#
#210000
0#
1&
b111110 $
b111110 '
b111110 :
#215000
b0 .
b0 3
b0 4
05
0/
b10 7
b1010 0
b1 6
1#
#220000
0#
0&
#225000
b1 4
b1 3
b100 8
b110100 9
b10 6
1#
#230000
0#
1&
b1101 $
b1101 '
b1101 :
#235000
b1 .
b1000001 2
b10 4
b10 3
b1 -
b110001 9
1#
#240000
0#
0&
#245000
b11 4
1#
#250000
0#
#255000
b100 4
b11 3
b0 8
b110000 9
1#
#260000
0#
#265000
b10 .
b101 2
b101 4
b100 3
b101 -
b110101 9
1#
#270000
0#
#275000
b110 4
1#
#280000
0#
#285000
b111 4
b101 3
b101 8
1#
#290000
0#
#295000
b11 .
b1011010 2
b1000 4
b110 3
b1010 -
b1000001 9
1#
#300000
0#
#305000
b1001 4
1#
#310000
0#
#315000
b1010 4
1#
#320000
0#
#325000
b100 7
1#
#330000
0#
#335000
b0 7
1!
b10000000000000000000000000110010 "
b10000000000000000000000000110010 1
b100 6
1#
#340000
0#
#345000
0!
b0 6
1#
