final_Project/transmit_uart.v
module transmit_uart(dataIn, rst, clk, bitStream, txDone);

    //Declare inputs here 
    input [7:0] dataIn; 
    input rst; 
    input clk; //This will be the baudRateGen so 153.6k bps 

    //Delcare outputs here
    output reg bitStream; 
    output reg txDone; 


    //Delcare other variables here
    reg [4:0] counter; 
    reg [3:0] datCounter; 
    reg [9:0] inputStream; 

    

    /*
        In terms of machine movment I think there should be 4 states
        - The first state is the idle state, that keeps bitstream high until rst is low
        - The next state should be the state that runs the transmit process, it will send out the start bit 
            and the data bits as well as the stop bit, hopefully this works
    */

    //Declare states
    parameter sIdle = 0, sTransmit = 1; 

    reg state, stateNext; 

    //Moving states
    always @(posedge clk) begin
        state <= stateNext; 
    end

    //Case statements
    always @(posedge clk) begin
        case (state)

            sIdle: begin
                //Here we just need to keep bitstream high until rst goes low
                if (rst == 0) begin
                    stateNext = sTransmit; 
                    //Set up rest of the outputs
                    txDone = 0; 
                    datCounter = 0; 
                    counter = 0; 

                    //Setup input stream 
                    inputStream[9] = 0;
                    inputStream[8:1] = dataIn;
                    inputStream[0] = 1; 
                    
                end else begin
                    stateNext = sIdle; 
                    bitStream = 1; 
                end
            end

            sTransmit: begin 
                if (datCounter < 10) begin 
                    //This means we need to keep going back to here
                    if (counter < 7) begin 
                        bitStream = inputStream[datCounter]; 
                        counter = counter + 1; 
                    end else begin 
                        datCounter = datCounter + 1; 
                        counter = 0; 
                    end 
                    stateNext = sTransmit; 
                end else begin 
                    //This means that we are done with tranmission so we can let the FIFO know we are done
                    txDone = 1; 
                    stateNext = sIdle; 
                end

                

            end

            default: begin 
                stateNext = sIdle; 
            end

        endcase

    end

    

endmodule

final_Project/baudRate.v


module baudRate(clk, outBaud, rst);

    //Define inputs here: 
    input clk; 
    input rst; 

    //Defind outputs here: 
    output reg outBaud;

    reg [9:0] counter; 

    //Define the states here: 
    parameter sIdle = 0, sCount = 1; 

    reg stateNext, state; 

    //We know that our internal clock is 100MHz and baudRate is 9600 so we won't try and make this module universal so we can do all math in hosue
    //Let's Take 16 baud symbols as one bit - 9600 * 16 = 153,000
    //Now lets take how many clock cycles we need to count before turing on and off our clock
    // 100M/153.6k = 651 cycles


    always @(posedge clk) begin 
        state <= stateNext; 
    end
    //Letsd do the programming
    always @(posedge clk) begin
        if (rst) begin
            counter = 0; 
            stateNext = sIdle; 
        end

        case (state)

            sIdle: begin 
                //This will be the reset state
                if (rst) begin
                    stateNext = sIdle; 
                    outBaud = 0; 
                end else begin
                    stateNext = sCount;
                    outBaud = 0; 
                    counter = 0;  
                end
            end

            sCount: begin
                //Here lets calcuate our couter
                if (rst) begin
                    counter = 0; 
                    stateNext = sIdle; 
                end else begin
                    counter = counter + 1; 
                    stateNext = sCount; 
                end

                if (counter == 651) begin
                    outBaud = ~outBaud;
                    counter = 0; 
                end
            end

            default: 
                stateNext = sIdle; 


        endcase

    end

endmodule

final_Project/testBenches/tb_uart_transmitter.v
`timescale 1ns/1ns
`include "../transmit_uart.v"
`include "../baudRate.v"
module tb_uart_transmitter();
    //Inputs for baudRate
    reg clk;
    reg clkRst; 

    //Outputs for baudRate
    wire outBaud; 

    //Init baudRate controller
    baudRate baudRate(
        .clk(clk), 
        .outBaud(outBaud), 
        .rst(clkRst)
    );

    //Lets declare inputs for transmitter
    reg [7:0] dataIn; 
    reg rst; 

    //Declare outputs for transmitter
    wire bitStream; 
    wire txDone; 

    //Init module
    transmit_uart transmitter(
        .dataIn(dataIn), 
        .rst(rst), 
        .clk(outBaud), 
        .bitStream(bitStream), 
        .txDone(txDone)
    );

    //Make ref 9600 clk
    reg pwm; 

    //Move clocks
    always #52083 pwm = ~pwm;

    always #5 clk = ~clk;

    //Set up intial conditions: 
    initial begin
        $dumpvars(0, tb_uart_transmitter);  
        clk = 1; 

        dataIn = 8'b10001001;

        clkRst = 1; // Assert reset
        rst = 1; 
        #10;       // Hold reset for 10ns

        clkRst = 0; // Deassert reset
        rst = 0; 

        #1000000; // Run for a while
        $finish;
    end


    

    
endmodule

final_Project/testBenches/dump.vcd
$date
	Wed Mar 26 12:27:54 2025
$end
$version
	Icarus Verilog
$end
$timescale
	1ns
$end
$scope module tb_uart_transmitter $end
$var wire 1 ! txDone $end
$var wire 1 " outBaud $end
$var wire 1 # bitStream $end
$var reg 1 $ clk $end
$var reg 1 % clkRst $end
$var reg 8 & dataIn [7:0] $end
$var reg 1 ' pwm $end
$var reg 1 ( rst $end
$scope module baudRate $end
$var wire 1 $ clk $end
$var wire 1 % rst $end
$var parameter 32 ) sCount $end
$var parameter 32 * sIdle $end
$var reg 10 + counter [9:0] $end
$var reg 1 " outBaud $end
$var reg 1 , state $end
$var reg 1 - stateNext $end
$upscope $end
$scope module transmitter $end
$var wire 1 " clk $end
$var wire 8 . dataIn [7:0] $end
$var wire 1 ( rst $end
$var parameter 32 / sIdle $end
$var parameter 32 0 sTransmit $end
$var reg 1 # bitStream $end
$var reg 5 1 counter [4:0] $end
$var reg 4 2 datCounter [3:0] $end
$var reg 10 3 inputStream [9:0] $end
$var reg 1 4 state $end
$var reg 1 5 stateNext $end
$var reg 1 ! txDone $end
$upscope $end
$upscope $end
$enddefinitions $end
$comment Show the parameter values. $end
$dumpall
b1 0
b0 /
b0 *
b1 )
$end
#0
$dumpvars
x5
x4
bx 3
bx 2
bx 1
b10001001 .
0-
0,
b0 +
1(
x'
b10001001 &
1%
1$
x#
x"
x!
$end
#5
0$
#10
0"
1-
1$
0(
0%
#15
0$
#20
1,
1$
#25
0$
#30
b1 +
1$
#35
0$
#40
b10 +
1$
#45
0$
#50
b11 +
1$
#55
0$
#60
b100 +
1$
#65
0$
#70
b101 +
1$
#75
0$
#80
b110 +
1$
#85
0$
#90
b111 +
1$
#95
0$
#100
b1000 +
1$
#105
0$
#110
b1001 +
1$
#115
0$
#120
b1010 +
1$
#125
0$
#130
b1011 +
1$
#135
0$
#140
b1100 +
1$
#145
0$
#150
b1101 +
1$
#155
0$
#160
b1110 +
1$
#165
0$
#170
b1111 +
1$
#175
0$
#180
b10000 +
1$
#185
0$
#190
b10001 +
1$
#195
0$
#200
b10010 +
1$
#205
0$
#210
b10011 +
1$
#215
0$
#220
b10100 +
1$
#225
0$
#230
b10101 +
1$
#235
0$
#240
b10110 +
1$
#245
0$
#250
b10111 +
1$
#255
0$
#260
b11000 +
1$
#265
0$
#270
b11001 +
1$
#275
0$
#280
b11010 +
1$
#285
0$
#290
b11011 +
1$
#295
0$
#300
b11100 +
1$
#305
0$
#310
b11101 +
1$
#315
0$
#320
b11110 +
1$
#325
0$
#330
b11111 +
1$
#335
0$
#340
b100000 +
1$
#345
0$
#350
b100001 +
1$
#355
0$
#360
b100010 +
1$
#365
0$
#370
b100011 +
1$
#375
0$
#380
b100100 +
1$
#385
0$
#390
b100101 +
1$
#395
0$
#400
b100110 +
1$
#405
0$
#410
b100111 +
1$
#415
0$
#420
b101000 +
1$
#425
0$
#430
b101001 +
1$
#435
0$
#440
b101010 +
1$
#445
0$
#450
b101011 +
1$
#455
0$
#460
b101100 +
1$
#465
0$
#470
b101101 +
1$
#475
0$
#480
b101110 +
1$
#485
0$
#490
b101111 +
1$
#495
0$
#500
b110000 +
1$
#505
0$
#510
b110001 +
1$
#515
0$
#520
b110010 +
1$
#525
0$
#530
b110011 +
1$
#535
0$
#540
b110100 +
1$
#545
0$
#550
b110101 +
1$
#555
0$
#560
b110110 +
1$
#565
0$
#570
b110111 +
1$
#575
0$
#580
b111000 +
1$
#585
0$
#590
b111001 +
1$
#595
0$
#600
b111010 +
1$
#605
0$
#610
b111011 +
1$
#615
0$
#620
b111100 +
1$
#625
0$
#630
b111101 +
1$
#635
0$
#640
b111110 +
1$
#645
0$
#650
b111111 +
1$
#655
0$
#660
b1000000 +
1$
#665
0$
#670
b1000001 +
1$
#675
0$
#680
b1000010 +
1$
#685
0$
#690
b1000011 +
1$
#695
0$
#700
b1000100 +
1$
#705
0$
#710
b1000101 +
1$
#715
0$
#720
b1000110 +
1$
#725
0$
#730
b1000111 +
1$
#735
0$
#740
b1001000 +
1$
#745
0$
#750
b1001001 +
1$
#755
0$
#760
b1001010 +
1$
#765
0$
#770
b1001011 +
1$
#775
0$
#780
b1001100 +
1$
#785
0$
#790
b1001101 +
1$
#795
0$
#800
b1001110 +
1$
#805
0$
#810
b1001111 +
1$
#815
0$
#820
b1010000 +
1$
#825
0$
#830
b1010001 +
1$
#835
0$
#840
b1010010 +
1$
#845
0$
#850
b1010011 +
1$
#855
0$
#860
b1010100 +
1$
#865
0$
#870
b1010101 +
1$
#875
0$
#880
b1010110 +
1$
#885
0$
#890
b1010111 +
1$
#895
0$
#900
b1011000 +
1$
#905
0$
#910
b1011001 +
1$
#915
0$
#920
b1011010 +
1$
#925
0$
#930
b1011011 +
1$
#935
0$
#940
b1011100 +
1$
#945
0$
#950
b1011101 +
1$
#955
0$
#960
b1011110 +
1$
#965
0$
#970
b1011111 +
1$
#975
0$
#980
b1100000 +
1$
#985
0$
#990
b1100001 +
1$
#995
0$
#1000
b1100010 +
1$
#1005
0$
#1010
b1100011 +
1$
#1015
0$
#1020
b1100100 +
1$
#1025
0$
#1030
b1100101 +
1$
#1035
0$
#1040
b1100110 +
1$
#1045
0$
#1050
b1100111 +
1$
#1055
0$
#1060
b1101000 +
1$
#1065
0$
#1070
b1101001 +
1$
#1075
0$
#1080
b1101010 +
1$
#1085
0$
#1090
b1101011 +
1$
#1095
0$
#1100
b1101100 +
1$
#1105
0$
#1110
b1101101 +
1$
#1115
0$
#1120
b1101110 +
1$
#1125
0$
#1130
b1101111 +
1$
#1135
0$
#1140
b1110000 +
1$
#1145
0$
#1150
b1110001 +
1$
#1155
0$
#1160
b1110010 +
1$
#1165
0$
#1170
b1110011 +
1$
#1175
0$
#1180
b1110100 +
1$
#1185
0$
#1190
b1110101 +
1$
#1195
0$
#1200
b1110110 +
1$
#1205
0$
#1210
b1110111 +
1$
#1215
0$
#1220
b1111000 +
1$
#1225
0$
#1230
b1111001 +
1$
#1235
0$
#1240
b1111010 +
1$
#1245
0$
#1250
b1111011 +
1$
#1255
0$
#1260
b1111100 +
1$
#1265
0$
#1270
b1111101 +
1$
#1275
0$
#1280
b1111110 +
1$
#1285
0$
#1290
b1111111 +
1$
#1295
0$
#1300
b10000000 +
1$
#1305
0$
#1310
b10000001 +
1$
#1315
0$
#1320
b10000010 +
1$
#1325
0$
#1330
b10000011 +
1$
#1335
0$
#1340
b10000100 +
1$
#1345
0$
#1350
b10000101 +
1$
#1355
0$
#1360
b10000110 +
1$
#1365
0$
#1370
b10000111 +
1$
#1375
0$
#1380
b10001000 +
1$
#1385
0$
#1390
b10001001 +
1$
#1395
0$
#1400
b10001010 +
1$
#1405
0$
#1410
b10001011 +
1$
#1415
0$
#1420
b10001100 +
1$
#1425
0$
#1430
b10001101 +
1$
#1435
0$
#1440
b10001110 +
1$
#1445
0$
#1450
b10001111 +
1$
#1455
0$
#1460
b10010000 +
1$
#1465
0$
#1470
b10010001 +
1$
#1475
0$
#1480
b10010010 +
1$
#1485
0$
#1490
b10010011 +
1$
#1495
0$
#1500
b10010100 +
1$
#1505
0$
#1510
b10010101 +
1$
#1515
0$
#1520
b10010110 +
1$
#1525
0$
#1530
b10010111 +
1$
#1535
0$
#1540
b10011000 +
1$
#1545
0$
#1550
b10011001 +
1$
#1555
0$
#1560
b10011010 +
1$
#1565
0$
#1570
b10011011 +
1$
#1575
0$
#1580
b10011100 +
1$
#1585
0$
#1590
b10011101 +
1$
#1595
0$
#1600
b10011110 +
1$
#1605
0$
#1610
b10011111 +
1$
#1615
0$
#1620
b10100000 +
1$
#1625
0$
#1630
b10100001 +
1$
#1635
0$
#1640
b10100010 +
1$
#1645
0$
#1650
b10100011 +
1$
#1655
0$
#1660
b10100100 +
1$
#1665
0$
#1670
b10100101 +
1$
#1675
0$
#1680
b10100110 +
1$
#1685
0$
#1690
b10100111 +
1$
#1695
0$
#1700
b10101000 +
1$
#1705
0$
#1710
b10101001 +
1$
#1715
0$
#1720
b10101010 +
1$
#1725
0$
#1730
b10101011 +
1$
#1735
0$
#1740
b10101100 +
1$
#1745
0$
#1750
b10101101 +
1$
#1755
0$
#1760
b10101110 +
1$
#1765
0$
#1770
b10101111 +
1$
#1775
0$
#1780
b10110000 +
1$
#1785
0$
#1790
b10110001 +
1$
#1795
0$
#1800
b10110010 +
1$
#1805
0$
#1810
b10110011 +
1$
#1815
0$
#1820
b10110100 +
1$
#1825
0$
#1830
b10110101 +
1$
#1835
0$
#1840
b10110110 +
1$
#1845
0$
#1850
b10110111 +
1$
#1855
0$
#1860
b10111000 +
1$
#1865
0$
#1870
b10111001 +
1$
#1875
0$
#1880
b10111010 +
1$
#1885
0$
#1890
b10111011 +
1$
#1895
0$
#1900
b10111100 +
1$
#1905
0$
#1910
b10111101 +
1$
#1915
0$
#1920
b10111110 +
1$
#1925
0$
#1930
b10111111 +
1$
#1935
0$
#1940
b11000000 +
1$
#1945
0$
#1950
b11000001 +
1$
#1955
0$
#1960
b11000010 +
1$
#1965
0$
#1970
b11000011 +
1$
#1975
0$
#1980
b11000100 +
1$
#1985
0$
#1990
b11000101 +
1$
#1995
0$
#2000
b11000110 +
1$
#2005
0$
#2010
b11000111 +
1$
#2015
0$
#2020
b11001000 +
1$
#2025
0$
#2030
b11001001 +
1$
#2035
0$
#2040
b11001010 +
1$
#2045
0$
#2050
b11001011 +
1$
#2055
0$
#2060
b11001100 +
1$
#2065
0$
#2070
b11001101 +
1$
#2075
0$
#2080
b11001110 +
1$
#2085
0$
#2090
b11001111 +
1$
#2095
0$
#2100
b11010000 +
1$
#2105
0$
#2110
b11010001 +
1$
#2115
0$
#2120
b11010010 +
1$
#2125
0$
#2130
b11010011 +
1$
#2135
0$
#2140
b11010100 +
1$
#2145
0$
#2150
b11010101 +
1$
#2155
0$
#2160
b11010110 +
1$
#2165
0$
#2170
b11010111 +
1$
#2175
0$
#2180
b11011000 +
1$
#2185
0$
#2190
b11011001 +
1$
#2195
0$
#2200
b11011010 +
1$
#2205
0$
#2210
b11011011 +
1$
#2215
0$
#2220
b11011100 +
1$
#2225
0$
#2230
b11011101 +
1$
#2235
0$
#2240
b11011110 +
1$
#2245
0$
#2250
b11011111 +
1$
#2255
0$
#2260
b11100000 +
1$
#2265
0$
#2270
b11100001 +
1$
#2275
0$
#2280
b11100010 +
1$
#2285
0$
#2290
b11100011 +
1$
#2295
0$
#2300
b11100100 +
1$
#2305
0$
#2310
b11100101 +
1$
#2315
0$
#2320
b11100110 +
1$
#2325
0$
#2330
b11100111 +
1$
#2335
0$
#2340
b11101000 +
1$
#2345
0$
#2350
b11101001 +
1$
#2355
0$
#2360
b11101010 +
1$
#2365
0$
#2370
b11101011 +
1$
#2375
0$
#2380
b11101100 +
1$
#2385
0$
#2390
b11101101 +
1$
#2395
0$
#2400
b11101110 +
1$
#2405
0$
#2410
b11101111 +
1$
#2415
0$
#2420
b11110000 +
1$
#2425
0$
#2430
b11110001 +
1$
#2435
0$
#2440
b11110010 +
1$
#2445
0$
#2450
b11110011 +
1$
#2455
0$
#2460
b11110100 +
1$
#2465
0$
#2470
b11110101 +
1$
#2475
0$
#2480
b11110110 +
1$
#2485
0$
#2490
b11110111 +
1$
#2495
0$
#2500
b11111000 +
1$
#2505
0$
#2510
b11111001 +
1$
#2515
0$
#2520
b11111010 +
1$
#2525
0$
#2530
b11111011 +
1$
#2535
0$
#2540
b11111100 +
1$
#2545
0$
#2550
b11111101 +
1$
#2555
0$
#2560
b11111110 +
1$
#2565
0$
#2570
b11111111 +
1$
#2575
0$
#2580
b100000000 +
1$
#2585
0$
#2590
b100000001 +
1$
#2595
0$
#2600
b100000010 +
1$
#2605
0$
#2610
b100000011 +
1$
#2615
0$
#2620
b100000100 +
1$
#2625
0$
#2630
b100000101 +
1$
#2635
0$
#2640
b100000110 +
1$
#2645
0$
#2650
b100000111 +
1$
#2655
0$
#2660
b100001000 +
1$
#2665
0$
#2670
b100001001 +
1$
#2675
0$
#2680
b100001010 +
1$
#2685
0$
#2690
b100001011 +
1$
#2695
0$
#2700
b100001100 +
1$
#2705
0$
#2710
b100001101 +
1$
#2715
0$
#2720
b100001110 +
1$
#2725
0$
#2730
b100001111 +
1$
#2735
0$
#2740
b100010000 +
1$
#2745
0$
#2750
b100010001 +
1$
#2755
0$
#2760
b100010010 +
1$
#2765
0$
#2770
b100010011 +
1$
#2775
0$
#2780
b100010100 +
1$
#2785
0$
#2790
b100010101 +
1$
#2795
0$
#2800
b100010110 +
1$
#2805
0$
#2810
b100010111 +
1$
#2815
0$
#2820
b100011000 +
1$
#2825
0$
#2830
b100011001 +
1$
#2835
0$
#2840
b100011010 +
1$
#2845
0$
#2850
b100011011 +
1$
#2855
0$
#2860
b100011100 +
1$
#2865
0$
#2870
b100011101 +
1$
#2875
0$
#2880
b100011110 +
1$
#2885
0$
#2890
b100011111 +
1$
#2895
0$
#2900
b100100000 +
1$
#2905
0$
#2910
b100100001 +
1$
#2915
0$
#2920
b100100010 +
1$
#2925
0$
#2930
b100100011 +
1$
#2935
0$
#2940
b100100100 +
1$
#2945
0$
#2950
b100100101 +
1$
#2955
0$
#2960
b100100110 +
1$
#2965
0$
#2970
b100100111 +
1$
#2975
0$
#2980
b100101000 +
1$
#2985
0$
#2990
b100101001 +
1$
#2995
0$
#3000
b100101010 +
1$
#3005
0$
#3010
b100101011 +
1$
#3015
0$
#3020
b100101100 +
1$
#3025
0$
#3030
b100101101 +
1$
#3035
0$
#3040
b100101110 +
1$
#3045
0$
#3050
b100101111 +
1$
#3055
0$
#3060
b100110000 +
1$
#3065
0$
#3070
b100110001 +
1$
#3075
0$
#3080
b100110010 +
1$
#3085
0$
#3090
b100110011 +
1$
#3095
0$
#3100
b100110100 +
1$
#3105
0$
#3110
b100110101 +
1$
#3115
0$
#3120
b100110110 +
1$
#3125
0$
#3130
b100110111 +
1$
#3135
0$
#3140
b100111000 +
1$
#3145
0$
#3150
b100111001 +
1$
#3155
0$
#3160
b100111010 +
1$
#3165
0$
#3170
b100111011 +
1$
#3175
0$
#3180
b100111100 +
1$
#3185
0$
#3190
b100111101 +
1$
#3195
0$
#3200
b100111110 +
1$
#3205
0$
#3210
b100111111 +
1$
#3215
0$
#3220
b101000000 +
1$
#3225
0$
#3230
b101000001 +
1$
#3235
0$
#3240
b101000010 +
1$
#3245
0$
#3250
b101000011 +
1$
#3255
0$
#3260
b101000100 +
1$
#3265
0$
#3270
b101000101 +
1$
#3275
0$
#3280
b101000110 +
1$
#3285
0$
#3290
b101000111 +
1$
#3295
0$
#3300
b101001000 +
1$
#3305
0$
#3310
b101001001 +
1$
#3315
0$
#3320
b101001010 +
1$
#3325
0$
#3330
b101001011 +
1$
#3335
0$
#3340
b101001100 +
1$
#3345
0$
#3350
b101001101 +
1$
#3355
0$
#3360
b101001110 +
1$
#3365
0$
#3370
b101001111 +
1$
#3375
0$
#3380
b101010000 +
1$
#3385
0$
#3390
b101010001 +
1$
#3395
0$
#3400
b101010010 +
1$
#3405
0$
#3410
b101010011 +
1$
#3415
0$
#3420
b101010100 +
1$
#3425
0$
#3430
b101010101 +
1$
#3435
0$
#3440
b101010110 +
1$
#3445
0$
#3450
b101010111 +
1$
#3455
0$
#3460
b101011000 +
1$
#3465
0$
#3470
b101011001 +
1$
#3475
0$
#3480
b101011010 +
1$
#3485
0$
#3490
b101011011 +
1$
#3495
0$
#3500
b101011100 +
1$
#3505
0$
#3510
b101011101 +
1$
#3515
0$
#3520
b101011110 +
1$
#3525
0$
#3530
b101011111 +
1$
#3535
0$
#3540
b101100000 +
1$
#3545
0$
#3550
b101100001 +
1$
#3555
0$
#3560
b101100010 +
1$
#3565
0$
#3570
b101100011 +
1$
#3575
0$
#3580
b101100100 +
1$
#3585
0$
#3590
b101100101 +
1$
#3595
0$
#3600
b101100110 +
1$
#3605
0$
#3610
b101100111 +
1$
#3615
0$
#3620
b101101000 +
1$
#3625
0$
#3630
b101101001 +
1$
#3635
0$
#3640
b101101010 +
1$
#3645
0$
#3650
b101101011 +
1$
#3655
0$
#3660
b101101100 +
1$
#3665
0$
#3670
b101101101 +
1$
#3675
0$
#3680
b101101110 +
1$
#3685
0$
#3690
b101101111 +
1$
#3695
0$
#3700
b101110000 +
1$
#3705
0$
#3710
b101110001 +
1$
#3715
0$
#3720
b101110010 +
1$
#3725
0$
#3730
b101110011 +
1$
#3735
0$
#3740
b101110100 +
1$
#3745
0$
#3750
b101110101 +
1$
#3755
0$
#3760
b101110110 +
1$
#3765
0$
#3770
b101110111 +
1$
#3775
0$
#3780
b101111000 +
1$
#3785
0$
#3790
b101111001 +
1$
#3795
0$
#3800
b101111010 +
1$
#3805
0$
#3810
b101111011 +
1$
#3815
0$
#3820
b101111100 +
1$
#3825
0$
#3830
b101111101 +
1$
#3835
0$
#3840
b101111110 +
1$
#3845
0$
#3850
b101111111 +
1$
#3855
0$
#3860
b110000000 +
1$
#3865
0$
#3870
b110000001 +
1$
#3875
0$
#3880
b110000010 +
1$
#3885
0$
#3890
b110000011 +
1$
#3895
0$
#3900
b110000100 +
1$
#3905
0$
#3910
b110000101 +
1$
#3915
0$
#3920
b110000110 +
1$
#3925
0$
#3930
b110000111 +
1$
#3935
0$
#3940
b110001000 +
1$
#3945
0$
#3950
b110001001 +
1$
#3955
0$
#3960
b110001010 +
1$
#3965
0$
#3970
b110001011 +
1$
#3975
0$
#3980
b110001100 +
1$
#3985
0$
#3990
b110001101 +
1$
#3995
0$
#4000
b110001110 +
1$
#4005
0$
#4010
b110001111 +
1$
#4015
0$
#4020
b110010000 +
1$
#4025
0$
#4030
b110010001 +
1$
#4035
0$
#4040
b110010010 +
1$
#4045
0$
#4050
b110010011 +
1$
#4055
0$
#4060
b110010100 +
1$
#4065
0$
#4070
b110010101 +
1$
#4075
0$
#4080
b110010110 +
1$
#4085
0$
#4090
b110010111 +
1$
#4095
0$
#4100
b110011000 +
1$
#4105
0$
#4110
b110011001 +
1$
#4115
0$
#4120
b110011010 +
1$
#4125
0$
#4130
b110011011 +
1$
#4135
0$
#4140
b110011100 +
1$
#4145
0$
#4150
b110011101 +
1$
#4155
0$
#4160
b110011110 +
1$
#4165
0$
#4170
b110011111 +
1$
#4175
0$
#4180
b110100000 +
1$
#4185
0$
#4190
b110100001 +
1$
#4195
0$
#4200
b110100010 +
1$
#4205
0$
#4210
b110100011 +
1$
#4215
0$
#4220
b110100100 +
1$
#4225
0$
#4230
b110100101 +
1$
#4235
0$
#4240
b110100110 +
1$
#4245
0$
#4250
b110100111 +
1$
#4255
0$
#4260
b110101000 +
1$
#4265
0$
#4270
b110101001 +
1$
#4275
0$
#4280
b110101010 +
1$
#4285
0$
#4290
b110101011 +
1$
#4295
0$
#4300
b110101100 +
1$
#4305
0$
#4310
b110101101 +
1$
#4315
0$
#4320
b110101110 +
1$
#4325
0$
#4330
b110101111 +
1$
#4335
0$
#4340
b110110000 +
1$
#4345
0$
#4350
b110110001 +
1$
#4355
0$
#4360
b110110010 +
1$
#4365
0$
#4370
b110110011 +
1$
#4375
0$
#4380
b110110100 +
1$
#4385
0$
#4390
b110110101 +
1$
#4395
0$
#4400
b110110110 +
1$
#4405
0$
#4410
b110110111 +
1$
#4415
0$
#4420
b110111000 +
1$
#4425
0$
#4430
b110111001 +
1$
#4435
0$
#4440
b110111010 +
1$
#4445
0$
#4450
b110111011 +
1$
#4455
0$
#4460
b110111100 +
1$
#4465
0$
#4470
b110111101 +
1$
#4475
0$
#4480
b110111110 +
1$
#4485
0$
#4490
b110111111 +
1$
#4495
0$
#4500
b111000000 +
1$
#4505
0$
#4510
b111000001 +
1$
#4515
0$
#4520
b111000010 +
1$
#4525
0$
#4530
b111000011 +
1$
#4535
0$
#4540
b111000100 +
1$
#4545
0$
#4550
b111000101 +
1$
#4555
0$
#4560
b111000110 +
1$
#4565
0$
#4570
b111000111 +
1$
#4575
0$
#4580
b111001000 +
1$
#4585
0$
#4590
b111001001 +
1$
#4595
0$
#4600
b111001010 +
1$
#4605
0$
#4610
b111001011 +
1$
#4615
0$
#4620
b111001100 +
1$
#4625
0$
#4630
b111001101 +
1$
#4635
0$
#4640
b111001110 +
1$
#4645
0$
#4650
b111001111 +
1$
#4655
0$
#4660
b111010000 +
1$
#4665
0$
#4670
b111010001 +
1$
#4675
0$
#4680
b111010010 +
1$
#4685
0$
#4690
b111010011 +
1$
#4695
0$
#4700
b111010100 +
1$
#4705
0$
#4710
b111010101 +
1$
#4715
0$
#4720
b111010110 +
1$
#4725
0$
#4730
b111010111 +
1$
#4735
0$
#4740
b111011000 +
1$
#4745
0$
#4750
b111011001 +
1$
#4755
0$
#4760
b111011010 +
1$
#4765
0$
#4770
b111011011 +
1$
#4775
0$
#4780
b111011100 +
1$
#4785
0$
#4790
b111011101 +
1$
#4795
0$
#4800
b111011110 +
1$
#4805
0$
#4810
b111011111 +
1$
#4815
0$
#4820
b111100000 +
1$
#4825
0$
#4830
b111100001 +
1$
#4835
0$
#4840
b111100010 +
1$
#4845
0$
#4850
b111100011 +
1$
#4855
0$
#4860
b111100100 +
1$
#4865
0$
#4870
b111100101 +
1$
#4875
0$
#4880
b111100110 +
1$
#4885
0$
#4890
b111100111 +
1$
#4895
0$
#4900
b111101000 +
1$
#4905
0$
#4910
b111101001 +
1$
#4915
0$
#4920
b111101010 +
1$
#4925
0$
#4930
b111101011 +
1$
#4935
0$
#4940
b111101100 +
1$
#4945
0$
#4950
b111101101 +
1$
#4955
0$
#4960
b111101110 +
1$
#4965
0$
#4970
b111101111 +
1$
#4975
0$
#4980
b111110000 +
1$
#4985
0$
#4990
b111110001 +
1$
#4995
0$
#5000
b111110010 +
1$
#5005
0$
#5010
b111110011 +
1$
#5015
0$
#5020
b111110100 +
1$
#5025
0$
#5030
b111110101 +
1$
#5035
0$
#5040
b111110110 +
1$
#5045
0$
#5050
b111110111 +
1$
#5055
0$
#5060
b111111000 +
1$
#5065
0$
#5070
b111111001 +
1$
#5075
0$
#5080
b111111010 +
1$
#5085
0$
#5090
b111111011 +
1$
#5095
0$
#5100
b111111100 +
1$
#5105
0$
#5110
b111111101 +
1$
#5115
0$
#5120
b111111110 +
1$
#5125
0$
#5130
b111111111 +
1$
#5135
0$
#5140
b1000000000 +
1$
#5145
0$
#5150
b1000000001 +
1$
#5155
0$
#5160
b1000000010 +
1$
#5165
0$
#5170
b1000000011 +
1$
#5175
0$
#5180
b1000000100 +
1$
#5185
0$
#5190
b1000000101 +
1$
#5195
0$
#5200
b1000000110 +
1$
#5205
0$
#5210
b1000000111 +
1$
#5215
0$
#5220
b1000001000 +
1$
#5225
0$
#5230
b1000001001 +
1$
#5235
0$
#5240
b1000001010 +
1$
#5245
0$
#5250
b1000001011 +
1$
#5255
0$
#5260
b1000001100 +
1$
#5265
0$
#5270
b1000001101 +
1$
#5275
0$
#5280
b1000001110 +
1$
#5285
0$
#5290
b1000001111 +
1$
#5295
0$
#5300
b1000010000 +
1$
#5305
0$
#5310
b1000010001 +
1$
#5315
0$
#5320
b1000010010 +
1$
#5325
0$
#5330
b1000010011 +
1$
#5335
0$
#5340
b1000010100 +
1$
#5345
0$
#5350
b1000010101 +
1$
#5355
0$
#5360
b1000010110 +
1$
#5365
0$
#5370
b1000010111 +
1$
#5375
0$
#5380
b1000011000 +
1$
#5385
0$
#5390
b1000011001 +
1$
#5395
0$
#5400
b1000011010 +
1$
#5405
0$
#5410
b1000011011 +
1$
#5415
0$
#5420
b1000011100 +
1$
#5425
0$
#5430
b1000011101 +
1$
#5435
0$
#5440
b1000011110 +
1$
#5445
0$
#5450
b1000011111 +
1$
#5455
0$
#5460
b1000100000 +
1$
#5465
0$
#5470
b1000100001 +
1$
#5475
0$
#5480
b1000100010 +
1$
#5485
0$
#5490
b1000100011 +
1$
#5495
0$
#5500
b1000100100 +
1$
#5505
0$
#5510
b1000100101 +
1$
#5515
0$
#5520
b1000100110 +
1$
#5525
0$
#5530
b1000100111 +
1$
#5535
0$
#5540
b1000101000 +
1$
#5545
0$
#5550
b1000101001 +
1$
#5555
0$
#5560
b1000101010 +
1$
#5565
0$
#5570
b1000101011 +
1$
#5575
0$
#5580
b1000101100 +
1$
#5585
0$
#5590
b1000101101 +
1$
#5595
0$
#5600
b1000101110 +
1$
#5605
0$
#5610
b1000101111 +
1$
#5615
0$
#5620
b1000110000 +
1$
#5625
0$
#5630
b1000110001 +
1$
#5635
0$
#5640
b1000110010 +
1$
#5645
0$
#5650
b1000110011 +
1$
#5655
0$
#5660
b1000110100 +
1$
#5665
0$
#5670
b1000110101 +
1$
#5675
0$
#5680
b1000110110 +
1$
#5685
0$
#5690
b1000110111 +
1$
#5695
0$
#5700
b1000111000 +
1$
#5705
0$
#5710
b1000111001 +
1$
#5715
0$
#5720
b1000111010 +
1$
#5725
0$
#5730
b1000111011 +
1$
#5735
0$
#5740
b1000111100 +
1$
#5745
0$
#5750
b1000111101 +
1$
#5755
0$
#5760
b1000111110 +
1$
#5765
0$
#5770
b1000111111 +
1$
#5775
0$
#5780
b1001000000 +
1$
#5785
0$
#5790
b1001000001 +
1$
#5795
0$
#5800
b1001000010 +
1$
#5805
0$
#5810
b1001000011 +
1$
#5815
0$
#5820
b1001000100 +
1$
#5825
0$
#5830
b1001000101 +
1$
#5835
0$
#5840
b1001000110 +
1$
#5845
0$
#5850
b1001000111 +
1$
#5855
0$
#5860
b1001001000 +
1$
#5865
0$
#5870
b1001001001 +
1$
#5875
0$
#5880
b1001001010 +
1$
#5885
0$
#5890
b1001001011 +
1$
#5895
0$
#5900
b1001001100 +
1$
#5905
0$
#5910
b1001001101 +
1$
#5915
0$
#5920
b1001001110 +
1$
#5925
0$
