4_Exercise/pwm.v

module pwm (clk, rst, period, dutyCycle, modeBurst, typeBurst, pwmOut, outRST);

    //Define the inputs here - remeber inputs don't need reg key word but outputs do
    input clk; 
    input rst;
    input [15:0] period;
    input [7:0] dutyCycle;
    input typeBurst; 
    input modeBurst;

    //define outputs here
    output reg pwmOut; 
    output reg outRST; 

    //define states here
    parameter sIdle = 0, sInit = 1, sOn = 2, sOff = 3, sOnBurst = 4, sOffBurst = 5;

    //States
    reg [2:0] state, stateNext; 

    //Extranous variables
    reg [32:0] onTime;
    reg [32:0] offTime; 

    //burst variables
    reg [32:0] burst_onTime, burst_offTime;  
    reg [32:0] burstDiv; 
    reg [32:0] burstCounter; 
    reg [32:0] tickTime;
    initial begin 
        $display(1000000000/period);
        if (typeBurst == 1) begin 
            burstDiv = 32; 
            burstCounter = 16; 
        end else begin 
            burstDiv = 16; 
            burstCounter = 8; 
        end
    end
    
         
    

    /* Moore Machines consist of 3 always blocks 
        - The first is to drive the states
        - The second is to drive the logic
        - The thrid is to drive the outputs
    */

    //always block to drive the states
    always @(posedge clk) begin
        state <= stateNext; 
    end


    //always block to drive the logic
    always @(posedge clk, rst) begin 
        if (rst == 1) begin 
            state = sIdle; 
        end else begin 
            state = stateNext; 
        end
        case (state)

            sIdle: begin 
                //Drive outputs: 
                outRST = rst; 
                pwmOut = 0; 

                //sIdle needs to only go to sInit, when rst = 0, else stay on sIdle
                if (rst == 0) begin 
                    stateNext = sInit;
                end else begin 
                    stateNext = sIdle; 
                end
            end

            sInit: begin 
                //Drive outputs: 
                outRST = rst; 
                pwmOut = 0; 

                //sInit should always move to sOn unless rst goes back on
                if (rst == 1) begin
                    //go back to sIdle
                    stateNext = sIdle; 
                end else begin 

                    if (modeBurst) begin 
                        stateNext = sOnBurst; 
                    end else begin 
                        stateNext = sOn; 
                    end; 

                    tickTime = 1000000000/period;
                    tickTime = 1000000000/tickTime;
                    //Lets also calcuate on and off times so we don't have to worry about that 
                    onTime = (tickTime * dutyCycle)/100; 
                    offTime = (tickTime*(100 - dutyCycle))/100; 

                    burst_onTime = onTime/burstDiv; 
                    burst_offTime = onTime/burstDiv; 
                    
                end
            end

            sOn: begin
                //Drive output
                pwmOut = 1;
                outRST = rst; 

                /* There are 3 options for movement within this stage
                    - sOn has not finished its duty cycle so it goes back to sOn
                    - sOn has finsihed its duty cycle so it moves to sOff
                    - rst is turned on and the system needs to go back to the idle state
                */

                if (rst == 1) begin 
                    //set idle back on 
                    stateNext = sIdle; 
                end else if (onTime != 0) begin 
                    onTime--; 
                    stateNext = sOn;   
                end else begin 
                    stateNext = sOff; 
                    onTime = (tickTime * dutyCycle)/100; 
                end
            end

            sOff: begin
                //Drive output
                pwmOut = 0;
                outRST = rst; 

                /* There are 3 options for movement within this stage
                    - sOff has not finished its duty cycle so it goes back to sOf
                    - sOff has finsihed its duty cycle so it moves to sOn or sOnBurst
                    - rst is turned on and the system needs to go back to the idle state
                */
                if (rst == 1) begin 
                    //set idle back on 
                    stateNext = sIdle; 
                end else if (offTime != 0) begin 
                    offTime--; 
                    stateNext = sOff; 
                end else begin 
                    if (modeBurst) begin 
                        stateNext = sOnBurst; 
                    end else begin
                        stateNext = sOn; 
                    end  
                    offTime = (tickTime * (100 - dutyCycle))/100; 
                end
            end

            sOnBurst: begin
                //Drive output
                pwmOut = 0;
                outRST = rst; 

                if (rst == 1) begin 
                    stateNext = sIdle;
                end else if (burstCounter > 0) begin //we need to decide wheater we need to go to sOff or sBurstOff or stay on burstOn
                    //Now we look at either sburston or sburstoff
                    if (burst_onTime > 0) begin 
                        burst_onTime--; 
                        stateNext = sOnBurst; 
                    end else begin 
                        //This means that it is time to go to burstOff 
                        burstCounter--; 
                        burst_onTime = ((tickTime * dutyCycle)/100)/burstDiv;
                        stateNext = sOffBurst;
                    end
                end else begin //this means that the burst counter is at 0
                    //Drive the state to sOff
                    stateNext = sOff; 

                    //Drive output
                    if (typeBurst == 1) begin 
                        burstCounter = 16; 
                    end else begin 
                        burstCounter = 8; 
                    end
                end
            end

            sOffBurst: begin
                //Drive output
                pwmOut = 1;


                /* There are 2 cases in which this state can move to
                    - It can go to offBurst while count is less than 8 or 16 depending on burst type
                    - or it can go to idle if reset is activated
                */

                if (rst == 1) begin 
                    stateNext = sIdle; 
                end else if (burst_offTime > 0) begin 
                    burst_offTime--;
                    stateNext = sOffBurst; 
                end else begin //This is when burstOff time is done
                    burst_offTime = ((tickTime * dutyCycle)/100)/burstDiv;
                    stateNext = sOnBurst;
                end
            end

            default: //NEVER FORGET THE DEFAULT CASE STATEMENT!!!
                stateNext = sInit; 
            


        endcase

    end



endmodule

4_Exercise/tb_pwm.v
`timescale 1ns/1ps
`include "pwm.v"

module tb_pwm;
    // Declare inputs as reg and outputs as wire
    reg clk;
    reg rst;
    reg [15:0] period;
    reg [7:0] dutyCycle;
    reg modeBurst;
    reg typeBurst;
    wire pwmOut;
    wire outRST;

    // Instantiate the PWM module
    pwm signal (
        .clk(clk),
        .rst(rst),
        .period(period),
        .dutyCycle(dutyCycle),
        .modeBurst(modeBurst),
        .typeBurst(typeBurst),
        .pwmOut(pwmOut),
        .outRST(outRST)
    );

    // This should generate a clock signal at 1 GHz
    always begin
        clk = 1;
        #0.5;
        clk = 0;
        #0.5;
    end

    // Test procedure
    initial begin
        $dumpvars(0, tb_pwm);

        typeBurst = 0; 
        modeBurst = 0; 
        // Set initial values
        rst = 0;
        //Transfer Function: MHz / 1G
        period = 1000;  // Set period
        dutyCycle = 50;    // Set duty cycle


        #5000;

        $finish;
    end

endmodule

4_Exercise/dump.vcd
$date
	Thu Feb 06 19:01:07 2025
$end
$version
	Icarus Verilog
$end
$timescale
	1ps
$end
$scope module tb_pwm $end
$var wire 1 ! pwmOut $end
$var wire 1 " outRST $end
$var reg 1 # clk $end
$var reg 8 $ dutyCycle [7:0] $end
$var reg 1 % modeBurst $end
$var reg 16 & period [15:0] $end
$var reg 1 ' rst $end
$var reg 1 ( typeBurst $end
$scope module signal $end
$var wire 1 # clk $end
$var wire 8 ) dutyCycle [7:0] $end
$var wire 1 % modeBurst $end
$var wire 16 * period [15:0] $end
$var wire 1 ' rst $end
$var wire 1 ( typeBurst $end
$var parameter 32 + sIdle $end
$var parameter 32 , sInit $end
$var parameter 32 - sOff $end
$var parameter 32 . sOffBurst $end
$var parameter 32 / sOn $end
$var parameter 32 0 sOnBurst $end
$var reg 33 1 burstCounter [32:0] $end
$var reg 33 2 burstDiv [32:0] $end
$var reg 33 3 burst_offTime [32:0] $end
$var reg 33 4 burst_onTime [32:0] $end
$var reg 33 5 offTime [32:0] $end
$var reg 33 6 onTime [32:0] $end
$var reg 1 " outRST $end
$var reg 1 ! pwmOut $end
$var reg 3 7 state [2:0] $end
$var reg 3 8 stateNext [2:0] $end
$var reg 33 9 tickTime [32:0] $end
$upscope $end
$upscope $end
$enddefinitions $end
$comment Show the parameter values. $end
$dumpall
b100 0
b10 /
b101 .
b11 -
b1 ,
b0 +
$end
#0
$dumpvars
bx 9
b1 8
bx 7
bx 6
bx 5
bx 4
bx 3
b10000 2
b1000 1
b1111101000 *
b110010 )
0(
0'
b1111101000 &
0%
b110010 $
1#
x"
x!
$end
#500
0#
#1000
b11111 3
b11111 4
b111110100 5
b111110100 6
b1111101000 9
b10 8
0!
0"
b1 7
1#
#1500
0#
#2000
b111110011 6
1!
b10 7
1#
#2500
0#
#3000
b111110010 6
1#
#3500
0#
#4000
b111110001 6
1#
#4500
0#
#5000
b111110000 6
1#
#5500
0#
#6000
b111101111 6
1#
#6500
0#
#7000
b111101110 6
1#
#7500
0#
#8000
b111101101 6
1#
#8500
0#
#9000
b111101100 6
1#
#9500
0#
#10000
b111101011 6
1#
#10500
0#
#11000
b111101010 6
1#
#11500
0#
#12000
b111101001 6
1#
#12500
0#
#13000
b111101000 6
1#
#13500
0#
#14000
b111100111 6
1#
#14500
0#
#15000
b111100110 6
1#
#15500
0#
#16000
b111100101 6
1#
#16500
0#
#17000
b111100100 6
1#
#17500
0#
#18000
b111100011 6
1#
#18500
0#
#19000
b111100010 6
1#
#19500
0#
#20000
b111100001 6
1#
#20500
0#
#21000
b111100000 6
1#
#21500
0#
#22000
b111011111 6
1#
#22500
0#
#23000
b111011110 6
1#
#23500
0#
#24000
b111011101 6
1#
#24500
0#
#25000
b111011100 6
1#
#25500
0#
#26000
b111011011 6
1#
#26500
0#
#27000
b111011010 6
1#
#27500
0#
#28000
b111011001 6
1#
#28500
0#
#29000
b111011000 6
1#
#29500
0#
#30000
b111010111 6
1#
#30500
0#
#31000
b111010110 6
1#
#31500
0#
#32000
b111010101 6
1#
#32500
0#
#33000
b111010100 6
1#
#33500
0#
#34000
b111010011 6
1#
#34500
0#
#35000
b111010010 6
1#
#35500
0#
#36000
b111010001 6
1#
#36500
0#
#37000
b111010000 6
1#
#37500
0#
#38000
b111001111 6
1#
#38500
0#
#39000
b111001110 6
1#
#39500
0#
#40000
b111001101 6
1#
#40500
0#
#41000
b111001100 6
1#
#41500
0#
#42000
b111001011 6
1#
#42500
0#
#43000
b111001010 6
1#
#43500
0#
#44000
b111001001 6
1#
#44500
0#
#45000
b111001000 6
1#
#45500
0#
#46000
b111000111 6
1#
#46500
0#
#47000
b111000110 6
1#
#47500
0#
#48000
b111000101 6
1#
#48500
0#
#49000
b111000100 6
1#
#49500
0#
#50000
b111000011 6
1#
#50500
0#
#51000
b111000010 6
1#
#51500
0#
#52000
b111000001 6
1#
#52500
0#
#53000
b111000000 6
1#
#53500
0#
#54000
b110111111 6
1#
#54500
0#
#55000
b110111110 6
1#
#55500
0#
#56000
b110111101 6
1#
#56500
0#
#57000
b110111100 6
1#
#57500
0#
#58000
b110111011 6
1#
#58500
0#
#59000
b110111010 6
1#
#59500
0#
#60000
b110111001 6
1#
#60500
0#
#61000
b110111000 6
1#
#61500
0#
#62000
b110110111 6
1#
#62500
0#
#63000
b110110110 6
1#
#63500
0#
#64000
b110110101 6
1#
#64500
0#
#65000
b110110100 6
1#
#65500
0#
#66000
b110110011 6
1#
#66500
0#
#67000
b110110010 6
1#
#67500
0#
#68000
b110110001 6
1#
#68500
0#
#69000
b110110000 6
1#
#69500
0#
#70000
b110101111 6
1#
#70500
0#
#71000
b110101110 6
1#
#71500
0#
#72000
b110101101 6
1#
#72500
0#
#73000
b110101100 6
1#
#73500
0#
#74000
b110101011 6
1#
#74500
0#
#75000
b110101010 6
1#
#75500
0#
#76000
b110101001 6
1#
#76500
0#
#77000
b110101000 6
1#
#77500
0#
#78000
b110100111 6
1#
#78500
0#
#79000
b110100110 6
1#
#79500
0#
#80000
b110100101 6
1#
#80500
0#
#81000
b110100100 6
1#
#81500
0#
#82000
b110100011 6
1#
#82500
0#
#83000
b110100010 6
1#
#83500
0#
#84000
b110100001 6
1#
#84500
0#
#85000
b110100000 6
1#
#85500
0#
#86000
b110011111 6
1#
#86500
0#
#87000
b110011110 6
1#
#87500
0#
#88000
b110011101 6
1#
#88500
0#
#89000
b110011100 6
1#
#89500
0#
#90000
b110011011 6
1#
#90500
0#
#91000
b110011010 6
1#
#91500
0#
#92000
b110011001 6
1#
#92500
0#
#93000
b110011000 6
1#
#93500
0#
#94000
b110010111 6
1#
#94500
0#
#95000
b110010110 6
1#
#95500
0#
#96000
b110010101 6
1#
#96500
0#
#97000
b110010100 6
1#
#97500
0#
#98000
b110010011 6
1#
#98500
0#
#99000
b110010010 6
1#
#99500
0#
#100000
b110010001 6
1#
#100500
0#
#101000
b110010000 6
1#
#101500
0#
#102000
b110001111 6
1#
#102500
0#
#103000
b110001110 6
1#
#103500
0#
#104000
b110001101 6
1#
#104500
0#
#105000
b110001100 6
1#
#105500
0#
#106000
b110001011 6
1#
#106500
0#
#107000
b110001010 6
1#
#107500
0#
#108000
b110001001 6
1#
#108500
0#
#109000
b110001000 6
1#
#109500
0#
#110000
b110000111 6
1#
#110500
0#
#111000
b110000110 6
1#
#111500
0#
#112000
b110000101 6
1#
#112500
0#
#113000
b110000100 6
1#
#113500
0#
#114000
b110000011 6
1#
#114500
0#
#115000
b110000010 6
1#
#115500
0#
#116000
b110000001 6
1#
#116500
0#
#117000
b110000000 6
1#
#117500
0#
#118000
b101111111 6
1#
#118500
0#
#119000
b101111110 6
1#
#119500
0#
#120000
b101111101 6
1#
#120500
0#
#121000
b101111100 6
1#
#121500
0#
#122000
b101111011 6
1#
#122500
0#
#123000
b101111010 6
1#
#123500
0#
#124000
b101111001 6
1#
#124500
0#
#125000
b101111000 6
1#
#125500
0#
#126000
b101110111 6
1#
#126500
0#
#127000
b101110110 6
1#
#127500
0#
#128000
b101110101 6
1#
#128500
0#
#129000
b101110100 6
1#
#129500
0#
#130000
b101110011 6
1#
#130500
0#
#131000
b101110010 6
1#
#131500
0#
#132000
b101110001 6
1#
#132500
0#
#133000
b101110000 6
1#
#133500
0#
#134000
b101101111 6
1#
#134500
0#
#135000
b101101110 6
1#
#135500
0#
#136000
b101101101 6
1#
#136500
0#
#137000
b101101100 6
1#
#137500
0#
#138000
b101101011 6
1#
#138500
0#
#139000
b101101010 6
1#
#139500
0#
#140000
b101101001 6
1#
#140500
0#
#141000
b101101000 6
1#
#141500
0#
#142000
b101100111 6
1#
#142500
0#
#143000
b101100110 6
1#
#143500
0#
#144000
b101100101 6
1#
#144500
0#
#145000
b101100100 6
1#
#145500
0#
#146000
b101100011 6
1#
#146500
0#
#147000
b101100010 6
1#
#147500
0#
#148000
b101100001 6
1#
#148500
0#
#149000
b101100000 6
1#
#149500
0#
#150000
b101011111 6
1#
#150500
0#
#151000
b101011110 6
1#
#151500
0#
#152000
b101011101 6
1#
#152500
0#
#153000
b101011100 6
1#
#153500
0#
#154000
b101011011 6
1#
#154500
0#
#155000
b101011010 6
1#
#155500
0#
#156000
b101011001 6
1#
#156500
0#
#157000
b101011000 6
1#
#157500
0#
#158000
b101010111 6
1#
#158500
0#
#159000
b101010110 6
1#
#159500
0#
#160000
b101010101 6
1#
#160500
0#
#161000
b101010100 6
1#
#161500
0#
#162000
b101010011 6
1#
#162500
0#
#163000
b101010010 6
1#
#163500
0#
#164000
b101010001 6
1#
#164500
0#
#165000
b101010000 6
1#
#165500
0#
#166000
b101001111 6
1#
#166500
0#
#167000
b101001110 6
1#
#167500
0#
#168000
b101001101 6
1#
#168500
0#
#169000
b101001100 6
1#
#169500
0#
#170000
b101001011 6
1#
#170500
0#
#171000
b101001010 6
1#
#171500
0#
#172000
b101001001 6
1#
#172500
0#
#173000
b101001000 6
1#
#173500
0#
#174000
b101000111 6
1#
#174500
0#
#175000
b101000110 6
1#
#175500
0#
#176000
b101000101 6
1#
#176500
0#
#177000
b101000100 6
1#
#177500
0#
#178000
b101000011 6
1#
#178500
0#
#179000
b101000010 6
1#
#179500
0#
#180000
b101000001 6
1#
#180500
0#
#181000
b101000000 6
1#
#181500
0#
#182000
b100111111 6
1#
#182500
0#
#183000
b100111110 6
1#
#183500
0#
#184000
b100111101 6
1#
#184500
0#
#185000
b100111100 6
1#
#185500
0#
#186000
b100111011 6
1#
#186500
0#
#187000
b100111010 6
1#
#187500
0#
#188000
b100111001 6
1#
#188500
0#
#189000
b100111000 6
1#
#189500
0#
#190000
b100110111 6
1#
#190500
0#
#191000
b100110110 6
1#
#191500
0#
#192000
b100110101 6
1#
#192500
0#
#193000
b100110100 6
1#
#193500
0#
#194000
b100110011 6
1#
#194500
0#
#195000
b100110010 6
1#
#195500
0#
#196000
b100110001 6
1#
#196500
0#
#197000
b100110000 6
1#
#197500
0#
#198000
b100101111 6
1#
#198500
0#
#199000
b100101110 6
1#
#199500
0#
#200000
b100101101 6
1#
#200500
0#
#201000
b100101100 6
1#
#201500
0#
#202000
b100101011 6
1#
#202500
0#
#203000
b100101010 6
1#
#203500
0#
#204000
b100101001 6
1#
#204500
0#
#205000
b100101000 6
1#
#205500
0#
#206000
b100100111 6
1#
#206500
0#
#207000
b100100110 6
1#
#207500
0#
#208000
b100100101 6
1#
#208500
0#
#209000
b100100100 6
1#
#209500
0#
#210000
b100100011 6
1#
#210500
0#
#211000
b100100010 6
1#
#211500
0#
#212000
b100100001 6
1#
#212500
0#
#213000
b100100000 6
1#
#213500
0#
#214000
b100011111 6
1#
#214500
0#
#215000
b100011110 6
1#
#215500
0#
#216000
b100011101 6
1#
#216500
0#
#217000
b100011100 6
1#
#217500
0#
#218000
b100011011 6
1#
#218500
0#
#219000
b100011010 6
1#
#219500
0#
#220000
b100011001 6
1#
#220500
0#
#221000
b100011000 6
1#
#221500
0#
#222000
b100010111 6
1#
#222500
0#
#223000
b100010110 6
1#
#223500
0#
#224000
b100010101 6
1#
#224500
0#
#225000
b100010100 6
1#
#225500
0#
#226000
b100010011 6
1#
#226500
0#
#227000
b100010010 6
1#
#227500
0#
#228000
b100010001 6
1#
#228500
0#
#229000
b100010000 6
1#
#229500
0#
#230000
b100001111 6
1#
#230500
0#
#231000
b100001110 6
1#
#231500
0#
#232000
b100001101 6
1#
#232500
0#
#233000
b100001100 6
1#
#233500
0#
#234000
b100001011 6
1#
#234500
0#
#235000
b100001010 6
1#
#235500
0#
#236000
b100001001 6
1#
#236500
0#
#237000
b100001000 6
1#
#237500
0#
#238000
b100000111 6
1#
#238500
0#
#239000
b100000110 6
1#
#239500
0#
#240000
b100000101 6
1#
#240500
0#
#241000
b100000100 6
1#
#241500
0#
#242000
b100000011 6
1#
#242500
0#
#243000
b100000010 6
1#
#243500
0#
#244000
b100000001 6
1#
#244500
0#
#245000
b100000000 6
1#
#245500
0#
#246000
b11111111 6
1#
#246500
0#
#247000
b11111110 6
1#
#247500
0#
#248000
b11111101 6
1#
#248500
0#
#249000
b11111100 6
1#
#249500
0#
#250000
b11111011 6
1#
#250500
0#
#251000
b11111010 6
1#
#251500
0#
#252000
b11111001 6
1#
#252500
0#
#253000
b11111000 6
1#
#253500
0#
#254000
b11110111 6
1#
#254500
0#
#255000
b11110110 6
1#
#255500
0#
#256000
b11110101 6
1#
#256500
0#
#257000
b11110100 6
1#
#257500
0#
#258000
b11110011 6
1#
#258500
0#
#259000
b11110010 6
1#
#259500
0#
#260000
b11110001 6
1#
#260500
0#
#261000
b11110000 6
1#
#261500
0#
#262000
b11101111 6
1#
#262500
0#
#263000
b11101110 6
1#
#263500
0#
#264000
b11101101 6
1#
#264500
0#
#265000
b11101100 6
1#
#265500
0#
#266000
b11101011 6
1#
#266500
0#
#267000
b11101010 6
1#
#267500
0#
#268000
b11101001 6
1#
#268500
0#
#269000
b11101000 6
1#
#269500
0#
#270000
b11100111 6
1#
#270500
0#
#271000
b11100110 6
1#
#271500
0#
#272000
b11100101 6
1#
#272500
0#
#273000
b11100100 6
1#
#273500
0#
#274000
b11100011 6
1#
#274500
0#
#275000
b11100010 6
1#
#275500
0#
#276000
b11100001 6
1#
#276500
0#
#277000
b11100000 6
1#
#277500
0#
#278000
b11011111 6
1#
#278500
0#
#279000
b11011110 6
1#
#279500
0#
#280000
b11011101 6
1#
#280500
0#
#281000
b11011100 6
1#
#281500
0#
#282000
b11011011 6
1#
#282500
0#
#283000
b11011010 6
1#
#283500
0#
#284000
b11011001 6
1#
#284500
0#
#285000
b11011000 6
1#
#285500
0#
#286000
b11010111 6
1#
#286500
0#
#287000
b11010110 6
1#
#287500
0#
#288000
b11010101 6
1#
#288500
0#
#289000
b11010100 6
1#
#289500
0#
#290000
b11010011 6
1#
#290500
0#
#291000
b11010010 6
1#
#291500
0#
#292000
b11010001 6
1#
#292500
0#
#293000
b11010000 6
1#
#293500
0#
#294000
b11001111 6
1#
#294500
0#
#295000
b11001110 6
1#
#295500
0#
#296000
b11001101 6
1#
#296500
0#
#297000
b11001100 6
1#
#297500
0#
#298000
b11001011 6
1#
#298500
0#
#299000
b11001010 6
1#
#299500
0#
#300000
b11001001 6
1#
#300500
0#
#301000
b11001000 6
1#
#301500
0#
#302000
b11000111 6
1#
#302500
0#
#303000
b11000110 6
1#
#303500
0#
#304000
b11000101 6
1#
#304500
0#
#305000
b11000100 6
1#
#305500
0#
#306000
b11000011 6
1#
#306500
0#
#307000
b11000010 6
1#
#307500
0#
#308000
b11000001 6
1#
#308500
0#
#309000
b11000000 6
1#
#309500
0#
#310000
b10111111 6
1#
#310500
0#
#311000
b10111110 6
1#
#311500
0#
#312000
b10111101 6
1#
#312500
0#
#313000
b10111100 6
1#
#313500
0#
#314000
b10111011 6
1#
#314500
0#
#315000
b10111010 6
1#
#315500
0#
#316000
b10111001 6
1#
#316500
0#
#317000
b10111000 6
1#
#317500
0#
#318000
b10110111 6
1#
#318500
0#
#319000
b10110110 6
1#
#319500
0#
#320000
b10110101 6
1#
#320500
0#
#321000
b10110100 6
1#
#321500
0#
#322000
b10110011 6
1#
#322500
0#
#323000
b10110010 6
1#
#323500
0#
#324000
b10110001 6
1#
#324500
0#
#325000
b10110000 6
1#
#325500
0#
#326000
b10101111 6
1#
#326500
0#
#327000
b10101110 6
1#
#327500
0#
#328000
b10101101 6
1#
#328500
0#
#329000
b10101100 6
1#
#329500
0#
#330000
b10101011 6
1#
#330500
0#
#331000
b10101010 6
1#
#331500
0#
#332000
b10101001 6
1#
#332500
0#
#333000
b10101000 6
1#
#333500
0#
#334000
b10100111 6
1#
#334500
0#
#335000
b10100110 6
1#
#335500
0#
#336000
b10100101 6
1#
#336500
0#
#337000
b10100100 6
1#
#337500
0#
#338000
b10100011 6
1#
#338500
0#
#339000
b10100010 6
1#
#339500
0#
#340000
b10100001 6
1#
#340500
0#
#341000
b10100000 6
1#
#341500
0#
#342000
b10011111 6
1#
#342500
0#
#343000
b10011110 6
1#
#343500
0#
#344000
b10011101 6
1#
#344500
0#
#345000
b10011100 6
1#
#345500
0#
#346000
b10011011 6
1#
#346500
0#
#347000
b10011010 6
1#
#347500
0#
#348000
b10011001 6
1#
#348500
0#
#349000
b10011000 6
1#
#349500
0#
#350000
b10010111 6
1#
#350500
0#
#351000
b10010110 6
1#
#351500
0#
#352000
b10010101 6
1#
#352500
0#
#353000
b10010100 6
1#
#353500
0#
#354000
b10010011 6
1#
#354500
0#
#355000
b10010010 6
1#
#355500
0#
#356000
b10010001 6
1#
#356500
0#
#357000
b10010000 6
1#
#357500
0#
#358000
b10001111 6
1#
#358500
0#
#359000
b10001110 6
1#
#359500
0#
#360000
b10001101 6
1#
#360500
0#
#361000
b10001100 6
1#
#361500
0#
#362000
b10001011 6
1#
#362500
0#
#363000
b10001010 6
1#
#363500
0#
#364000
b10001001 6
1#
#364500
0#
#365000
b10001000 6
1#
#365500
0#
#366000
b10000111 6
1#
#366500
0#
#367000
b10000110 6
1#
#367500
0#
#368000
b10000101 6
1#
#368500
0#
#369000
b10000100 6
1#
#369500
0#
#370000
b10000011 6
1#
#370500
0#
#371000
b10000010 6
1#
#371500
0#
#372000
b10000001 6
1#
#372500
0#
#373000
b10000000 6
1#
#373500
0#
#374000
b1111111 6
1#
#374500
0#
#375000
b1111110 6
1#
#375500
0#
#376000
b1111101 6
1#
#376500
0#
#377000
b1111100 6
1#
#377500
0#
#378000
b1111011 6
1#
#378500
0#
#379000
b1111010 6
1#
#379500
0#
#380000
b1111001 6
1#
#380500
0#
#381000
b1111000 6
1#
#381500
0#
#382000
b1110111 6
1#
#382500
0#
#383000
b1110110 6
1#
#383500
0#
#384000
b1110101 6
1#
#384500
0#
#385000
b1110100 6
1#
#385500
0#
#386000
b1110011 6
1#
#386500
0#
#387000
b1110010 6
1#
#387500
0#
#388000
b1110001 6
1#
#388500
0#
#389000
b1110000 6
1#
#389500
0#
#390000
b1101111 6
1#
#390500
0#
#391000
b1101110 6
1#
#391500
0#
#392000
b1101101 6
1#
#392500
0#
#393000
b1101100 6
1#
#393500
0#
#394000
b1101011 6
1#
#394500
0#
#395000
b1101010 6
1#
#395500
0#
#396000
b1101001 6
1#
#396500
0#
#397000
b1101000 6
1#
#397500
0#
#398000
b1100111 6
1#
#398500
0#
#399000
b1100110 6
1#
#399500
0#
#400000
b1100101 6
1#
#400500
0#
#401000
b1100100 6
1#
#401500
0#
#402000
b1100011 6
1#
#402500
0#
#403000
b1100010 6
1#
#403500
0#
#404000
b1100001 6
1#
#404500
0#
#405000
b1100000 6
1#
#405500
0#
#406000
b1011111 6
1#
#406500
0#
#407000
b1011110 6
1#
#407500
0#
#408000
b1011101 6
1#
#408500
0#
#409000
b1011100 6
1#
#409500
0#
#410000
b1011011 6
1#
#410500
0#
#411000
b1011010 6
1#
#411500
0#
#412000
b1011001 6
1#
#412500
0#
#413000
b1011000 6
1#
#413500
0#
#414000
b1010111 6
1#
#414500
0#
#415000
b1010110 6
1#
#415500
0#
#416000
b1010101 6
1#
#416500
0#
#417000
b1010100 6
1#
#417500
0#
#418000
b1010011 6
1#
#418500
0#
#419000
b1010010 6
1#
#419500
0#
#420000
b1010001 6
1#
#420500
0#
#421000
b1010000 6
1#
#421500
0#
#422000
b1001111 6
1#
#422500
0#
#423000
b1001110 6
1#
#423500
0#
#424000
b1001101 6
1#
#424500
0#
#425000
b1001100 6
1#
#425500
0#
#426000
b1001011 6
1#
#426500
0#
#427000
b1001010 6
1#
#427500
0#
#428000
b1001001 6
1#
#428500
0#
#429000
b1001000 6
1#
#429500
0#
#430000
b1000111 6
1#
#430500
0#
#431000
b1000110 6
1#
#431500
0#
#432000
b1000101 6
1#
#432500
0#
#433000
b1000100 6
1#
#433500
0#
#434000
b1000011 6
1#
#434500
0#
#435000
b1000010 6
1#
#435500
0#
#436000
b1000001 6
1#
#436500
0#
#437000
b1000000 6
1#
#437500
0#
#438000
b111111 6
1#
#438500
0#
#439000
b111110 6
1#
#439500
0#
#440000
b111101 6
1#
#440500
0#
#441000
b111100 6
1#
#441500
0#
#442000
b111011 6
1#
#442500
0#
#443000
b111010 6
1#
#443500
0#
#444000
b111001 6
1#
#444500
0#
#445000
b111000 6
1#
#445500
0#
#446000
b110111 6
1#
#446500
0#
#447000
b110110 6
1#
#447500
0#
#448000
b110101 6
1#
#448500
0#
#449000
b110100 6
1#
#449500
0#
#450000
b110011 6
1#
#450500
0#
#451000
b110010 6
1#
#451500
0#
#452000
b110001 6
1#
#452500
0#
#453000
b110000 6
1#
#453500
0#
#454000
b101111 6
1#
#454500
0#
#455000
b101110 6
1#
#455500
0#
#456000
b101101 6
1#
#456500
0#
#457000
b101100 6
1#
#457500
0#
#458000
b101011 6
1#
#458500
0#
#459000
b101010 6
1#
#459500
0#
#460000
b101001 6
1#
#460500
0#
#461000
b101000 6
1#
#461500
0#
#462000
b100111 6
1#
#462500
0#
#463000
b100110 6
1#
#463500
0#
#464000
b100101 6
1#
#464500
0#
#465000
b100100 6
1#
#465500
0#
#466000
b100011 6
1#
#466500
0#
#467000
b100010 6
1#
#467500
0#
#468000
b100001 6
1#
#468500
0#
#469000
b100000 6
1#
#469500
0#
#470000
b11111 6
1#
#470500
0#
#471000
b11110 6
1#
#471500
0#
#472000
b11101 6
1#
#472500
0#
#473000
b11100 6
1#
#473500
0#
#474000
b11011 6
1#
#474500
0#
#475000
b11010 6
1#
#475500
0#
#476000
b11001 6
1#
#476500
0#
#477000
b11000 6
1#
#477500
0#
#478000
b10111 6
1#
#478500
0#
#479000
b10110 6
1#
#479500
0#
#480000
b10101 6
1#
#480500
0#
#481000
b10100 6
1#
#481500
0#
#482000
b10011 6
1#
#482500
0#
#483000
b10010 6
1#
#483500
0#
#484000
b10001 6
1#
#484500
0#
#485000
b10000 6
1#
#485500
0#
#486000
b1111 6
1#
#486500
0#
#487000
b1110 6
1#
#487500
0#
#488000
b1101 6
1#
#488500
0#
#489000
b1100 6
1#
#489500
0#
#490000
b1011 6
1#
#490500
0#
#491000
b1010 6
1#
#491500
0#
#492000
b1001 6
1#
#492500
0#
#493000
b1000 6
1#
#493500
0#
#494000
b111 6
1#
#494500
0#
#495000
b110 6
1#
#495500
0#
#496000
b101 6
1#
#496500
0#
#497000
b100 6
1#
#497500
0#
#498000
b11 6
1#
#498500
0#
#499000
b10 6
1#
#499500
0#
#500000
b1 6
1#
#500500
0#
#501000
b0 6
1#
#501500
0#
#502000
b111110100 6
b11 8
1#
#502500
0#
#503000
b111110011 5
0!
b11 7
1#
#503500
0#
#504000
b111110010 5
1#
#504500
0#
#505000
b111110001 5
1#
#505500
0#
#506000
b111110000 5
1#
#506500
0#
#507000
b111101111 5
1#
#507500
0#
#508000
b111101110 5
1#
#508500
0#
#509000
b111101101 5
1#
#509500
0#
#510000
b111101100 5
1#
#510500
0#
#511000
b111101011 5
1#
#511500
0#
#512000
b111101010 5
1#
#512500
0#
#513000
b111101001 5
1#
#513500
0#
#514000
b111101000 5
1#
#514500
0#
#515000
b111100111 5
1#
#515500
0#
#516000
b111100110 5
1#
#516500
0#
#517000
b111100101 5
1#
#517500
0#
#518000
b111100100 5
1#
#518500
0#
#519000
b111100011 5
1#
#519500
0#
#520000
b111100010 5
1#
#520500
0#
#521000
b111100001 5
1#
#521500
0#
#522000
b111100000 5
1#
#522500
0#
#523000
b111011111 5
1#
#523500
0#
#524000
b111011110 5
1#
#524500
0#
#525000
b111011101 5
1#
#525500
0#
#526000
b111011100 5
1#
#526500
0#
#527000
b111011011 5
1#
#527500
0#
#528000
b111011010 5
1#
#528500
0#
#529000
b111011001 5
1#
#529500
0#
#530000
b111011000 5
1#
#530500
0#
#531000
b111010111 5
1#
#531500
0#
#532000
b111010110 5
1#
#532500
0#
#533000
b111010101 5
1#
#533500
0#
#534000
b111010100 5
1#
#534500
0#
#535000
b111010011 5
1#
#535500
0#
#536000
b111010010 5
1#
#536500
0#
#537000
b111010001 5
1#
#537500
0#
#538000
b111010000 5
1#
#538500
0#
#539000
b111001111 5
1#
#539500
0#
#540000
b111001110 5
1#
#540500
0#
#541000
b111001101 5
1#
