4_Exercise/pwm.v

module pwm (clk, rst, period, dutyCycle, modeBurst, typeBurst, pwmOut, outRST);

    //Define the inputs here - remeber inputs don't need reg key word but outputs do
    input clk; 
    input rst;
    input [15:0] period;
    input [7:0] dutyCycle;
    input typeBurst; 
    input modeBurst;

    //define outputs here
    output reg pwmOut; 
    output reg outRST; 

    //define states here
    parameter sIdle = 0, sInit = 1, sOn = 2, sOff = 3, sOnBurst = 4, sOffBurst = 5;

    //States
    reg [2:0] state, stateNext; 

    //Extranous variables
    reg [32:0] onTime;
    reg [32:0] offTime; 

    //burst variables
    reg [32:0] burst_onTime, burst_offTime;  
    reg [32:0] burstDiv; 
    reg [32:0] burstCounter; 
    reg [32:0] tickTime;
    initial begin 
        $display(1000000000/period);
        if (typeBurst == 1) begin 
            burstDiv = 32; 
            burstCounter = 16; 
        end else begin 
            burstDiv = 16; 
            burstCounter = 8; 
        end
    end
    
         
    

    /* Moore Machines consist of 3 always blocks 
        - The first is to drive the states
        - The second is to drive the logic
        - The thrid is to drive the outputs
    */

    //always block to drive the states
    always @(posedge clk) begin
        state <= stateNext; 
    end


    //always block to drive the logic
    always @(posedge clk, rst) begin 
        if (rst == 1) begin 
            state = sIdle; 
        end else begin 
            state = stateNext; 
        end
        case (state)

            sIdle: begin 
                //Drive outputs: 
                outRST = rst; 
                pwmOut = 0; 

                //sIdle needs to only go to sInit, when rst = 0, else stay on sIdle
                if (rst == 0) begin 
                    stateNext = sInit;
                end else begin 
                    stateNext = sIdle; 
                end
            end

            sInit: begin 
                //Drive outputs: 
                outRST = rst; 
                pwmOut = 0; 

                //sInit should always move to sOn unless rst goes back on
                if (rst == 1) begin
                    //go back to sIdle
                    stateNext = sIdle; 
                end else begin 

                    if (modeBurst) begin 
                        stateNext = sOnBurst; 
                    end else begin 
                        stateNext = sOn; 
                    end; 

                    tickTime = 1000000000/period;
                    tickTime = 1000000000/tickTime;
                    //Lets also calcuate on and off times so we don't have to worry about that 
                    onTime = (tickTime * dutyCycle)/100; 
                    offTime = (tickTime*(100 - dutyCycle))/100; 

                    burst_onTime = onTime/burstDiv; 
                    burst_offTime = onTime/burstDiv; 
                    
                end
            end

            sOn: begin
                //Drive output
                pwmOut = 1;
                outRST = rst; 

                /* There are 3 options for movement within this stage
                    - sOn has not finished its duty cycle so it goes back to sOn
                    - sOn has finsihed its duty cycle so it moves to sOff
                    - rst is turned on and the system needs to go back to the idle state
                */

                if (rst == 1) begin 
                    //set idle back on 
                    stateNext = sIdle; 
                end else if (onTime != 0) begin 
                    onTime--; 
                    stateNext = sOn;   
                end else begin 
                    stateNext = sOff; 
                    onTime = (tickTime * dutyCycle)/100; 
                end
            end

            sOff: begin
                //Drive output
                pwmOut = 0;
                outRST = rst; 

                /* There are 3 options for movement within this stage
                    - sOff has not finished its duty cycle so it goes back to sOf
                    - sOff has finsihed its duty cycle so it moves to sOn or sOnBurst
                    - rst is turned on and the system needs to go back to the idle state
                */
                if (rst == 1) begin 
                    //set idle back on 
                    stateNext = sIdle; 
                end else if (offTime != 0) begin 
                    offTime--; 
                    stateNext = sOff; 
                end else begin 
                    if (modeBurst) begin 
                        stateNext = sOnBurst; 
                    end else begin
                        stateNext = sOn; 
                    end  
                    offTime = (tickTime * (100 - dutyCycle))/100; 
                end
            end

            sOnBurst: begin
                //Drive output
                pwmOut = 0;
                outRST = rst; 

                if (rst == 1) begin 
                    stateNext = sIdle;
                end else if (burstCounter > 0) begin //we need to decide wheater we need to go to sOff or sBurstOff or stay on burstOn
                    //Now we look at either sburston or sburstoff
                    if (burst_onTime > 0) begin 
                        burst_onTime--; 
                        stateNext = sOnBurst; 
                    end else begin 
                        //This means that it is time to go to burstOff 
                        burstCounter--; 
                        burst_onTime = ((tickTime * dutyCycle)/100)/burstDiv;
                        stateNext = sOffBurst;
                    end
                end else begin //this means that the burst counter is at 0
                    //Drive the state to sOff
                    stateNext = sOff; 

                    //Drive output
                    if (typeBurst == 1) begin 
                        burstCounter = 16; 
                    end else begin 
                        burstCounter = 8; 
                    end
                end
            end

            sOffBurst: begin
                //Drive output
                pwmOut = 1;


                /* There are 2 cases in which this state can move to
                    - It can go to offBurst while count is less than 8 or 16 depending on burst type
                    - or it can go to idle if reset is activated
                */

                if (rst == 1) begin 
                    stateNext = sIdle; 
                end else if (burst_offTime > 0) begin 
                    burst_offTime--;
                    stateNext = sOffBurst; 
                end else begin //This is when burstOff time is done
                    burst_offTime = ((tickTime * dutyCycle)/100)/burstDiv;
                    stateNext = sOnBurst;
                end
            end

            default: //NEVER FORGET THE DEFAULT CASE STATEMENT!!!
                stateNext = sInit; 
            


        endcase

    end



endmodule

4_Exercise/tb_pwm.v
`timescale 1ns/1ps
`include "pwm.v"

module tb_pwm;
    // Declare inputs as reg and outputs as wire
    reg clk;
    reg rst;
    reg [15:0] period;
    reg [7:0] dutyCycle;
    reg modeBurst;
    reg typeBurst;
    wire pwmOut;
    wire outRST;

    // Instantiate the PWM module
    pwm signal (
        .clk(clk),
        .rst(rst),
        .period(period),
        .dutyCycle(dutyCycle),
        .modeBurst(modeBurst),
        .typeBurst(typeBurst),
        .pwmOut(pwmOut),
        .outRST(outRST)
    );

    // This should generate a clock signal at 1 GHz
    always begin
        clk = 1;
        #0.5;
        clk = 0;
        #0.5;
    end

    // Test procedure
    initial begin
        $dumpvars(0, tb_pwm);

        typeBurst = 0; 
        modeBurst = 1; 
        // Set initial values
        rst = 0;
        period = 20;  // Set period
        dutyCycle = 50;    // Set duty cycle


        #5000;

        $finish;
    end

endmodule

4_Exercise/dump.vcd
$date
	Thu Feb 06 18:52:12 2025
$end
$version
	Icarus Verilog
$end
$timescale
	1ps
$end
$scope module tb_pwm $end
$var wire 1 ! pwmOut $end
$var wire 1 " outRST $end
$var reg 1 # clk $end
$var reg 8 $ dutyCycle [7:0] $end
$var reg 1 % modeBurst $end
$var reg 16 & period [15:0] $end
$var reg 1 ' rst $end
$var reg 1 ( typeBurst $end
$scope module signal $end
$var wire 1 # clk $end
$var wire 8 ) dutyCycle [7:0] $end
$var wire 1 % modeBurst $end
$var wire 16 * period [15:0] $end
$var wire 1 ' rst $end
$var wire 1 ( typeBurst $end
$var parameter 32 + sIdle $end
$var parameter 32 , sInit $end
$var parameter 32 - sOff $end
$var parameter 32 . sOffBurst $end
$var parameter 32 / sOn $end
$var parameter 32 0 sOnBurst $end
$var reg 33 1 burstCounter [32:0] $end
$var reg 33 2 burstDiv [32:0] $end
$var reg 33 3 burst_offTime [32:0] $end
$var reg 33 4 burst_onTime [32:0] $end
$var reg 33 5 offTime [32:0] $end
$var reg 33 6 onTime [32:0] $end
$var reg 1 " outRST $end
$var reg 1 ! pwmOut $end
$var reg 3 7 state [2:0] $end
$var reg 3 8 stateNext [2:0] $end
$var reg 33 9 tickTime [32:0] $end
$upscope $end
$upscope $end
$enddefinitions $end
$comment Show the parameter values. $end
$dumpall
b100 0
b10 /
b101 .
b11 -
b1 ,
b0 +
$end
#0
$dumpvars
bx 9
b1 8
bx 7
bx 6
bx 5
bx 4
bx 3
b10000 2
b1000 1
b10100 *
b110010 )
0(
0'
b10100 &
1%
b110010 $
1#
x"
x!
$end
#500
0#
#1000
b0 3
b0 4
b1010 5
b1010 6
b10100 9
b100 8
0!
0"
b1 7
1#
#1500
0#
#2000
b101 8
b111 1
b100 7
1#
#2500
0#
#3000
b100 8
1!
b101 7
1#
#3500
0#
#4000
b101 8
b110 1
0!
b100 7
1#
#4500
0#
#5000
b100 8
1!
b101 7
1#
#5500
0#
#6000
b101 8
b101 1
0!
b100 7
1#
#6500
0#
#7000
b100 8
1!
b101 7
1#
#7500
0#
#8000
b101 8
b100 1
0!
b100 7
1#
#8500
0#
#9000
b100 8
1!
b101 7
1#
#9500
0#
#10000
b101 8
b11 1
0!
b100 7
1#
#10500
0#
#11000
b100 8
1!
b101 7
1#
#11500
0#
#12000
b101 8
b10 1
0!
b100 7
1#
#12500
0#
#13000
b100 8
1!
b101 7
1#
#13500
0#
#14000
b101 8
b1 1
0!
b100 7
1#
#14500
0#
#15000
b100 8
1!
b101 7
1#
#15500
0#
#16000
b101 8
b0 1
0!
b100 7
1#
#16500
0#
#17000
b100 8
1!
b101 7
1#
#17500
0#
#18000
b1000 1
b11 8
0!
b100 7
1#
#18500
0#
#19000
b1001 5
b11 7
1#
#19500
0#
#20000
b1000 5
1#
#20500
0#
#21000
b111 5
1#
#21500
0#
#22000
b110 5
1#
#22500
0#
#23000
b101 5
1#
#23500
0#
#24000
b100 5
1#
#24500
0#
#25000
b11 5
1#
#25500
0#
#26000
b10 5
1#
#26500
0#
#27000
b1 5
1#
#27500
0#
#28000
b0 5
1#
#28500
0#
#29000
b1010 5
b100 8
1#
#29500
0#
#30000
b101 8
b111 1
b100 7
1#
#30500
0#
#31000
b100 8
1!
b101 7
1#
#31500
0#
#32000
b101 8
b110 1
0!
b100 7
1#
#32500
0#
#33000
b100 8
1!
b101 7
1#
#33500
0#
#34000
b101 8
b101 1
0!
b100 7
1#
#34500
0#
#35000
b100 8
1!
b101 7
1#
#35500
0#
#36000
b101 8
b100 1
0!
b100 7
1#
#36500
0#
#37000
b100 8
1!
b101 7
1#
#37500
0#
#38000
b101 8
b11 1
0!
b100 7
1#
#38500
0#
#39000
b100 8
1!
b101 7
1#
#39500
0#
#40000
b101 8
b10 1
0!
b100 7
1#
#40500
0#
#41000
b100 8
1!
b101 7
1#
#41500
0#
#42000
b101 8
b1 1
0!
b100 7
1#
#42500
0#
#43000
b100 8
1!
b101 7
1#
#43500
0#
#44000
b101 8
b0 1
0!
b100 7
1#
#44500
0#
#45000
b100 8
1!
b101 7
1#
#45500
0#
#46000
b1000 1
b11 8
0!
b100 7
1#
#46500
0#
#47000
b1001 5
b11 7
1#
#47500
0#
#48000
b1000 5
1#
#48500
0#
#49000
b111 5
1#
#49500
0#
#50000
b110 5
1#
#50500
0#
#51000
b101 5
1#
#51500
0#
#52000
b100 5
1#
#52500
0#
#53000
b11 5
1#
#53500
0#
#54000
b10 5
1#
#54500
0#
#55000
b1 5
1#
#55500
0#
#56000
b0 5
1#
#56500
0#
#57000
b1010 5
b100 8
1#
#57500
0#
#58000
b101 8
b111 1
b100 7
1#
#58500
0#
#59000
b100 8
1!
b101 7
1#
#59500
0#
#60000
b101 8
b110 1
0!
b100 7
1#
#60500
0#
#61000
b100 8
1!
b101 7
1#
#61500
0#
#62000
b101 8
b101 1
0!
b100 7
1#
#62500
0#
#63000
b100 8
1!
b101 7
1#
#63500
0#
#64000
b101 8
b100 1
0!
b100 7
1#
#64500
0#
#65000
b100 8
1!
b101 7
1#
#65500
0#
#66000
b101 8
b11 1
0!
b100 7
1#
#66500
0#
#67000
b100 8
1!
b101 7
1#
#67500
0#
#68000
b101 8
b10 1
0!
b100 7
1#
#68500
0#
#69000
b100 8
1!
b101 7
1#
#69500
0#
#70000
b101 8
b1 1
0!
b100 7
1#
#70500
0#
#71000
b100 8
1!
b101 7
1#
#71500
0#
#72000
b101 8
b0 1
0!
b100 7
1#
#72500
0#
#73000
b100 8
1!
b101 7
1#
#73500
0#
#74000
b1000 1
b11 8
0!
b100 7
1#
#74500
0#
#75000
b1001 5
b11 7
1#
#75500
0#
#76000
b1000 5
1#
#76500
0#
#77000
b111 5
1#
#77500
0#
#78000
b110 5
1#
#78500
0#
#79000
b101 5
1#
#79500
0#
#80000
b100 5
1#
#80500
0#
#81000
b11 5
1#
#81500
0#
#82000
b10 5
1#
#82500
0#
#83000
b1 5
1#
#83500
0#
#84000
b0 5
1#
#84500
0#
#85000
b1010 5
b100 8
1#
#85500
0#
#86000
b101 8
b111 1
b100 7
1#
#86500
0#
#87000
b100 8
1!
b101 7
1#
#87500
0#
#88000
b101 8
b110 1
0!
b100 7
1#
#88500
0#
#89000
b100 8
1!
b101 7
1#
#89500
0#
#90000
b101 8
b101 1
0!
b100 7
1#
#90500
0#
#91000
b100 8
1!
b101 7
1#
#91500
0#
#92000
b101 8
b100 1
0!
b100 7
1#
#92500
0#
#93000
b100 8
1!
b101 7
1#
#93500
0#
#94000
b101 8
b11 1
0!
b100 7
1#
#94500
0#
#95000
b100 8
1!
b101 7
1#
#95500
0#
#96000
b101 8
b10 1
0!
b100 7
1#
#96500
0#
#97000
b100 8
1!
b101 7
1#
#97500
0#
#98000
b101 8
b1 1
0!
b100 7
1#
#98500
0#
#99000
b100 8
1!
b101 7
1#
#99500
0#
#100000
b101 8
b0 1
0!
b100 7
1#
#100500
0#
#101000
b100 8
1!
b101 7
1#
#101500
0#
#102000
b1000 1
b11 8
0!
b100 7
1#
#102500
0#
#103000
b1001 5
b11 7
1#
#103500
0#
#104000
b1000 5
1#
#104500
0#
#105000
b111 5
1#
#105500
0#
#106000
b110 5
1#
#106500
0#
#107000
b101 5
1#
#107500
0#
#108000
b100 5
1#
#108500
0#
#109000
b11 5
1#
#109500
0#
#110000
b10 5
1#
#110500
0#
#111000
b1 5
1#
#111500
0#
#112000
b0 5
1#
#112500
0#
#113000
b1010 5
b100 8
1#
#113500
0#
#114000
b101 8
b111 1
b100 7
1#
#114500
0#
#115000
b100 8
1!
b101 7
1#
#115500
0#
#116000
b101 8
b110 1
0!
b100 7
1#
#116500
0#
#117000
b100 8
1!
b101 7
1#
#117500
0#
#118000
b101 8
b101 1
0!
b100 7
1#
#118500
0#
#119000
b100 8
1!
b101 7
1#
#119500
0#
#120000
b101 8
b100 1
0!
b100 7
1#
#120500
0#
#121000
b100 8
1!
b101 7
1#
#121500
0#
#122000
b101 8
b11 1
0!
b100 7
1#
#122500
0#
#123000
b100 8
1!
b101 7
1#
#123500
0#
#124000
b101 8
b10 1
0!
b100 7
1#
#124500
0#
#125000
b100 8
1!
b101 7
1#
#125500
0#
#126000
b101 8
b1 1
0!
b100 7
1#
#126500
0#
#127000
b100 8
1!
b101 7
1#
#127500
0#
#128000
b101 8
b0 1
0!
b100 7
1#
#128500
0#
#129000
b100 8
1!
b101 7
1#
#129500
0#
#130000
b1000 1
b11 8
0!
b100 7
1#
#130500
0#
#131000
b1001 5
b11 7
1#
#131500
0#
#132000
b1000 5
1#
#132500
0#
#133000
b111 5
1#
#133500
0#
#134000
b110 5
1#
#134500
0#
#135000
b101 5
1#
#135500
0#
#136000
b100 5
1#
#136500
0#
#137000
b11 5
1#
#137500
0#
#138000
b10 5
1#
#138500
0#
#139000
b1 5
1#
#139500
0#
#140000
b0 5
1#
#140500
0#
#141000
b1010 5
b100 8
1#
#141500
0#
#142000
b101 8
b111 1
b100 7
1#
#142500
0#
#143000
b100 8
1!
b101 7
1#
#143500
0#
#144000
b101 8
b110 1
0!
b100 7
1#
#144500
0#
#145000
b100 8
1!
b101 7
1#
#145500
0#
#146000
b101 8
b101 1
0!
b100 7
1#
#146500
0#
#147000
b100 8
1!
b101 7
1#
#147500
0#
#148000
b101 8
b100 1
0!
b100 7
1#
#148500
0#
#149000
b100 8
1!
b101 7
1#
#149500
0#
#150000
b101 8
b11 1
0!
b100 7
1#
#150500
0#
#151000
b100 8
1!
b101 7
1#
#151500
0#
#152000
b101 8
b10 1
0!
b100 7
1#
#152500
0#
#153000
b100 8
1!
b101 7
1#
#153500
0#
#154000
b101 8
b1 1
0!
b100 7
1#
#154500
0#
#155000
b100 8
1!
b101 7
1#
#155500
0#
#156000
b101 8
b0 1
0!
b100 7
1#
#156500
0#
#157000
b100 8
1!
b101 7
1#
#157500
0#
#158000
b1000 1
b11 8
0!
b100 7
1#
#158500
0#
#159000
b1001 5
b11 7
1#
#159500
0#
#160000
b1000 5
1#
#160500
0#
#161000
b111 5
1#
#161500
0#
#162000
b110 5
1#
#162500
0#
#163000
b101 5
1#
#163500
0#
#164000
b100 5
1#
#164500
0#
#165000
b11 5
1#
#165500
0#
#166000
b10 5
1#
#166500
0#
#167000
b1 5
1#
#167500
0#
#168000
b0 5
1#
#168500
0#
#169000
b1010 5
b100 8
1#
#169500
0#
#170000
b101 8
b111 1
b100 7
1#
#170500
0#
#171000
b100 8
1!
b101 7
1#
#171500
0#
#172000
b101 8
b110 1
0!
b100 7
1#
#172500
0#
#173000
b100 8
1!
b101 7
1#
#173500
0#
#174000
b101 8
b101 1
0!
b100 7
1#
#174500
0#
#175000
b100 8
1!
b101 7
1#
#175500
0#
#176000
b101 8
b100 1
0!
b100 7
1#
#176500
0#
#177000
b100 8
1!
b101 7
1#
#177500
0#
#178000
b101 8
b11 1
0!
b100 7
1#
#178500
0#
#179000
b100 8
1!
b101 7
1#
#179500
0#
#180000
b101 8
b10 1
0!
b100 7
1#
#180500
0#
#181000
b100 8
1!
b101 7
1#
#181500
0#
#182000
b101 8
b1 1
0!
b100 7
1#
#182500
0#
#183000
b100 8
1!
b101 7
1#
#183500
0#
#184000
b101 8
b0 1
0!
b100 7
1#
#184500
0#
#185000
b100 8
1!
b101 7
1#
#185500
0#
#186000
b1000 1
b11 8
0!
b100 7
1#
#186500
0#
#187000
b1001 5
b11 7
1#
#187500
0#
#188000
b1000 5
1#
#188500
0#
#189000
b111 5
1#
#189500
0#
#190000
b110 5
1#
#190500
0#
#191000
b101 5
1#
#191500
0#
#192000
b100 5
1#
#192500
0#
#193000
b11 5
1#
#193500
0#
#194000
b10 5
1#
#194500
0#
#195000
b1 5
1#
#195500
0#
#196000
b0 5
1#
#196500
0#
#197000
b1010 5
b100 8
1#
#197500
0#
#198000
b101 8
b111 1
b100 7
1#
#198500
0#
#199000
b100 8
1!
b101 7
1#
#199500
0#
#200000
b101 8
b110 1
0!
b100 7
1#
#200500
0#
#201000
b100 8
1!
b101 7
1#
#201500
0#
#202000
b101 8
b101 1
0!
b100 7
1#
#202500
0#
#203000
b100 8
1!
b101 7
1#
#203500
0#
#204000
b101 8
b100 1
0!
b100 7
1#
#204500
0#
#205000
b100 8
1!
b101 7
1#
#205500
0#
#206000
b101 8
b11 1
0!
b100 7
1#
#206500
0#
#207000
b100 8
1!
b101 7
1#
#207500
0#
#208000
b101 8
b10 1
0!
b100 7
1#
#208500
0#
#209000
b100 8
1!
b101 7
1#
#209500
0#
#210000
b101 8
b1 1
0!
b100 7
1#
#210500
0#
#211000
b100 8
1!
b101 7
1#
#211500
0#
#212000
b101 8
b0 1
0!
b100 7
1#
#212500
0#
#213000
b100 8
1!
b101 7
1#
#213500
0#
#214000
b1000 1
b11 8
0!
b100 7
1#
#214500
0#
#215000
b1001 5
b11 7
1#
#215500
0#
#216000
b1000 5
1#
#216500
0#
#217000
b111 5
1#
#217500
0#
#218000
b110 5
1#
#218500
0#
#219000
b101 5
1#
#219500
0#
#220000
b100 5
1#
#220500
0#
#221000
b11 5
1#
#221500
0#
#222000
b10 5
1#
#222500
0#
#223000
b1 5
1#
#223500
0#
#224000
b0 5
1#
#224500
0#
#225000
b1010 5
b100 8
1#
#225500
0#
#226000
b101 8
b111 1
b100 7
1#
#226500
0#
#227000
b100 8
1!
b101 7
1#
#227500
0#
#228000
b101 8
b110 1
0!
b100 7
1#
#228500
0#
#229000
b100 8
1!
b101 7
1#
#229500
0#
#230000
b101 8
b101 1
0!
b100 7
1#
#230500
0#
#231000
b100 8
1!
b101 7
1#
#231500
0#
#232000
b101 8
b100 1
0!
b100 7
1#
#232500
0#
#233000
b100 8
1!
b101 7
1#
#233500
0#
#234000
b101 8
b11 1
0!
b100 7
1#
#234500
0#
#235000
b100 8
1!
b101 7
1#
#235500
0#
#236000
b101 8
b10 1
0!
b100 7
1#
#236500
0#
#237000
b100 8
1!
b101 7
1#
#237500
0#
#238000
b101 8
b1 1
0!
b100 7
1#
#238500
0#
#239000
b100 8
1!
b101 7
1#
#239500
0#
#240000
b101 8
b0 1
0!
b100 7
1#
#240500
0#
#241000
b100 8
1!
b101 7
1#
#241500
0#
#242000
b1000 1
b11 8
0!
b100 7
1#
#242500
0#
#243000
b1001 5
b11 7
1#
#243500
0#
#244000
b1000 5
1#
#244500
0#
#245000
b111 5
1#
#245500
0#
#246000
b110 5
1#
#246500
0#
#247000
b101 5
1#
#247500
0#
#248000
b100 5
1#
#248500
0#
#249000
b11 5
1#
#249500
0#
#250000
b10 5
1#
#250500
0#
#251000
b1 5
1#
#251500
0#
#252000
b0 5
1#
#252500
0#
#253000
b1010 5
b100 8
1#
#253500
0#
#254000
b101 8
b111 1
b100 7
1#
#254500
0#
#255000
b100 8
1!
b101 7
1#
#255500
0#
#256000
b101 8
b110 1
0!
b100 7
1#
#256500
0#
#257000
b100 8
1!
b101 7
1#
#257500
0#
#258000
b101 8
b101 1
0!
b100 7
1#
#258500
0#
#259000
b100 8
1!
b101 7
1#
#259500
0#
#260000
b101 8
b100 1
0!
b100 7
1#
#260500
0#
#261000
b100 8
1!
b101 7
1#
#261500
0#
#262000
b101 8
b11 1
0!
b100 7
1#
#262500
0#
#263000
b100 8
1!
b101 7
1#
#263500
0#
#264000
b101 8
b10 1
0!
b100 7
1#
#264500
0#
#265000
b100 8
1!
b101 7
1#
#265500
0#
#266000
b101 8
b1 1
0!
b100 7
1#
#266500
0#
#267000
b100 8
1!
b101 7
1#
#267500
0#
#268000
b101 8
b0 1
0!
b100 7
1#
#268500
0#
#269000
b100 8
1!
b101 7
1#
#269500
0#
#270000
b1000 1
b11 8
0!
b100 7
1#
#270500
0#
#271000
b1001 5
b11 7
1#
#271500
0#
#272000
b1000 5
1#
#272500
0#
#273000
b111 5
1#
#273500
0#
#274000
b110 5
1#
#274500
0#
#275000
b101 5
1#
#275500
0#
#276000
b100 5
1#
#276500
0#
#277000
b11 5
1#
#277500
0#
#278000
b10 5
1#
#278500
0#
#279000
b1 5
1#
#279500
0#
#280000
b0 5
1#
#280500
0#
#281000
b1010 5
b100 8
1#
#281500
0#
#282000
b101 8
b111 1
b100 7
1#
#282500
0#
#283000
b100 8
1!
b101 7
1#
#283500
0#
#284000
b101 8
b110 1
0!
b100 7
1#
#284500
0#
#285000
b100 8
1!
b101 7
1#
#285500
0#
#286000
b101 8
b101 1
0!
b100 7
1#
#286500
0#
#287000
b100 8
1!
b101 7
1#
#287500
0#
#288000
b101 8
b100 1
0!
b100 7
1#
#288500
0#
#289000
b100 8
1!
b101 7
1#
#289500
0#
#290000
b101 8
b11 1
0!
b100 7
1#
#290500
0#
#291000
b100 8
1!
b101 7
1#
#291500
0#
#292000
b101 8
b10 1
0!
b100 7
1#
#292500
0#
#293000
b100 8
1!
b101 7
1#
#293500
0#
#294000
b101 8
b1 1
0!
b100 7
1#
#294500
0#
#295000
b100 8
1!
b101 7
1#
#295500
0#
#296000
b101 8
b0 1
0!
b100 7
1#
#296500
0#
#297000
b100 8
1!
b101 7
1#
#297500
0#
#298000
b1000 1
b11 8
0!
b100 7
1#
#298500
0#
#299000
b1001 5
b11 7
1#
#299500
0#
#300000
b1000 5
1#
#300500
0#
#301000
b111 5
1#
#301500
0#
#302000
b110 5
1#
#302500
0#
#303000
b101 5
1#
#303500
0#
#304000
b100 5
1#
#304500
0#
#305000
b11 5
1#
#305500
0#
#306000
b10 5
1#
#306500
0#
#307000
b1 5
1#
#307500
0#
#308000
b0 5
1#
#308500
0#
#309000
b1010 5
b100 8
1#
#309500
0#
#310000
b101 8
b111 1
b100 7
1#
#310500
0#
#311000
b100 8
1!
b101 7
1#
#311500
0#
#312000
b101 8
b110 1
0!
b100 7
1#
#312500
0#
#313000
b100 8
1!
b101 7
1#
#313500
0#
#314000
b101 8
b101 1
0!
b100 7
1#
#314500
0#
#315000
b100 8
1!
b101 7
1#
#315500
0#
#316000
b101 8
b100 1
0!
b100 7
1#
#316500
0#
#317000
b100 8
1!
b101 7
1#
#317500
0#
#318000
b101 8
b11 1
0!
b100 7
1#
#318500
0#
#319000
b100 8
1!
b101 7
1#
#319500
0#
#320000
b101 8
b10 1
0!
b100 7
1#
#320500
0#
#321000
b100 8
1!
b101 7
1#
#321500
0#
#322000
b101 8
b1 1
0!
b100 7
1#
#322500
0#
#323000
b100 8
1!
b101 7
1#
#323500
0#
#324000
b101 8
b0 1
0!
b100 7
1#
#324500
0#
#325000
b100 8
1!
b101 7
1#
#325500
0#
#326000
b1000 1
b11 8
0!
b100 7
1#
#326500
0#
#327000
b1001 5
b11 7
1#
#327500
0#
#328000
b1000 5
1#
#328500
0#
#329000
b111 5
1#
#329500
0#
#330000
b110 5
1#
#330500
0#
#331000
b101 5
1#
#331500
0#
#332000
b100 5
1#
#332500
0#
#333000
b11 5
1#
#333500
0#
#334000
b10 5
1#
#334500
0#
#335000
b1 5
1#
#335500
0#
#336000
b0 5
1#
#336500
0#
#337000
b1010 5
b100 8
1#
#337500
0#
#338000
b101 8
b111 1
b100 7
1#
#338500
0#
#339000
b100 8
1!
b101 7
1#
#339500
0#
#340000
b101 8
b110 1
0!
b100 7
1#
#340500
0#
#341000
b100 8
1!
b101 7
1#
#341500
0#
#342000
b101 8
b101 1
0!
b100 7
1#
#342500
0#
#343000
b100 8
1!
b101 7
1#
#343500
0#
#344000
b101 8
b100 1
0!
b100 7
1#
#344500
0#
#345000
b100 8
1!
b101 7
1#
#345500
0#
#346000
b101 8
b11 1
0!
b100 7
1#
#346500
0#
#347000
b100 8
1!
b101 7
1#
#347500
0#
#348000
b101 8
b10 1
0!
b100 7
1#
#348500
0#
#349000
b100 8
1!
b101 7
1#
#349500
0#
#350000
b101 8
b1 1
0!
b100 7
1#
#350500
0#
#351000
b100 8
1!
b101 7
1#
#351500
0#
#352000
b101 8
b0 1
0!
b100 7
1#
#352500
0#
#353000
b100 8
1!
b101 7
1#
#353500
0#
#354000
b1000 1
b11 8
0!
b100 7
1#
#354500
0#
#355000
b1001 5
b11 7
1#
#355500
0#
#356000
b1000 5
1#
#356500
0#
#357000
b111 5
1#
#357500
0#
#358000
b110 5
1#
#358500
0#
#359000
b101 5
1#
#359500
0#
#360000
b100 5
1#
#360500
0#
#361000
b11 5
1#
#361500
0#
#362000
b10 5
1#
#362500
0#
#363000
b1 5
1#
#363500
0#
#364000
b0 5
1#
#364500
0#
#365000
b1010 5
b100 8
1#
#365500
0#
#366000
b101 8
b111 1
b100 7
1#
#366500
0#
#367000
b100 8
1!
b101 7
1#
#367500
0#
#368000
b101 8
b110 1
0!
b100 7
1#
#368500
0#
#369000
b100 8
1!
b101 7
1#
#369500
0#
#370000
b101 8
b101 1
0!
b100 7
1#
#370500
0#
#371000
b100 8
1!
b101 7
1#
#371500
0#
#372000
b101 8
b100 1
0!
b100 7
1#
#372500
0#
#373000
b100 8
1!
b101 7
1#
#373500
0#
#374000
b101 8
b11 1
0!
b100 7
1#
#374500
0#
#375000
b100 8
1!
b101 7
1#
#375500
0#
#376000
b101 8
b10 1
0!
b100 7
1#
#376500
0#
#377000
b100 8
1!
b101 7
1#
#377500
0#
#378000
b101 8
b1 1
0!
b100 7
1#
#378500
0#
#379000
b100 8
1!
b101 7
1#
#379500
0#
#380000
b101 8
b0 1
0!
b100 7
1#
#380500
0#
#381000
b100 8
1!
b101 7
1#
#381500
0#
#382000
b1000 1
b11 8
0!
b100 7
1#
#382500
0#
#383000
b1001 5
b11 7
1#
#383500
0#
#384000
b1000 5
1#
#384500
0#
#385000
b111 5
1#
#385500
0#
#386000
b110 5
1#
#386500
0#
#387000
b101 5
1#
#387500
0#
#388000
b100 5
1#
#388500
0#
#389000
b11 5
1#
#389500
0#
#390000
b10 5
1#
#390500
0#
#391000
b1 5
1#
#391500
0#
#392000
b0 5
1#
#392500
0#
#393000
b1010 5
b100 8
1#
#393500
0#
#394000
b101 8
b111 1
b100 7
1#
#394500
0#
#395000
b100 8
1!
b101 7
1#
#395500
0#
#396000
b101 8
b110 1
0!
b100 7
1#
#396500
0#
#397000
b100 8
1!
b101 7
1#
#397500
0#
#398000
b101 8
b101 1
0!
b100 7
1#
#398500
0#
#399000
b100 8
1!
b101 7
1#
#399500
0#
#400000
b101 8
b100 1
0!
b100 7
1#
#400500
0#
#401000
b100 8
1!
b101 7
1#
#401500
0#
#402000
b101 8
b11 1
0!
b100 7
1#
#402500
0#
#403000
b100 8
1!
b101 7
1#
#403500
0#
#404000
b101 8
b10 1
0!
b100 7
1#
#404500
0#
#405000
b100 8
1!
b101 7
1#
#405500
0#
#406000
b101 8
b1 1
0!
b100 7
1#
#406500
0#
#407000
b100 8
1!
b101 7
1#
#407500
0#
#408000
b101 8
b0 1
0!
b100 7
1#
#408500
0#
#409000
b100 8
1!
b101 7
1#
#409500
0#
#410000
b1000 1
b11 8
0!
b100 7
1#
#410500
0#
#411000
b1001 5
b11 7
1#
#411500
0#
#412000
b1000 5
1#
#412500
0#
#413000
b111 5
1#
#413500
0#
#414000
b110 5
1#
#414500
0#
#415000
b101 5
1#
#415500
0#
#416000
b100 5
1#
#416500
0#
#417000
b11 5
1#
#417500
0#
#418000
b10 5
1#
#418500
0#
#419000
b1 5
1#
#419500
0#
#420000
b0 5
1#
#420500
0#
#421000
b1010 5
b100 8
1#
#421500
0#
#422000
b101 8
b111 1
b100 7
1#
#422500
0#
#423000
b100 8
1!
b101 7
1#
#423500
0#
#424000
b101 8
b110 1
0!
b100 7
1#
#424500
0#
#425000
b100 8
1!
b101 7
1#
#425500
0#
#426000
b101 8
b101 1
0!
b100 7
1#
#426500
0#
#427000
b100 8
1!
b101 7
1#
#427500
0#
#428000
b101 8
b100 1
0!
b100 7
1#
#428500
0#
#429000
b100 8
1!
b101 7
1#
#429500
0#
#430000
b101 8
b11 1
0!
b100 7
1#
#430500
0#
#431000
b100 8
1!
b101 7
1#
#431500
0#
#432000
b101 8
b10 1
0!
b100 7
1#
#432500
0#
#433000
b100 8
1!
b101 7
1#
#433500
0#
#434000
b101 8
b1 1
0!
b100 7
1#
#434500
0#
#435000
b100 8
1!
b101 7
1#
#435500
0#
#436000
b101 8
b0 1
0!
b100 7
1#
#436500
0#
