1_Excercise/SampleFSM.v
// example FSM for CSEE 4290
// From Pg 44-46 Verilog text

`timescale 1ns/1ns

module SampleFSM(B, X, Clk, Rst);

input B;
output reg X;
input Clk, Rst;

parameter S_Off = 0, S_On1 = 1, S_On2 = 2, S_On3 = 3;

reg [1:0] State, StateNext;

// CombLogic

always @(State, B) begin

  case (State)
	S_Off: begin
		X <= 0;
		if (B == 0)
			StateNext <= S_Off;
		else
			StateNext <= S_On1;
		end
	S_On1: begin
		X <= 1;
		StateNext <= S_On2;
		end
	S_On2: begin
		X <= 1;
		StateNext <= S_On3;
		end
	S_On3: begin
		X <= 1;
		StateNext <= S_Off;
		end
  endcase
end

//StateReg

always @(posedge Clk) begin
 
  if (Rst == 1)
	State <= S_Off;
  else
	State <= StateNext;
end

endmodule

1_Excercise/SampleFSM_Test.v
// Testbench for Sample FSM

`timescale 1ns/1ns
`include "SampleFSM.v"

module SampleFSM_Test();

reg Clk_s, Rst_s, B_s;
wire X_s;

SampleFSM  CompToTest(B_s, X_s, Clk_s, Rst_s);

//Clock

always begin
	Clk_s <= 0;
	#10;
	Clk_s <= 1;
	#10;
end

// Test inputs

initial begin
$dumpvars(0,SampleFSM_Test);
	Rst_s <= 1;
	B_s <= 0;
	@(posedge Clk_s);
	#5 Rst_s <= 0;
	@(posedge Clk_s);
	#5 B_s <= 1;
	@(posedge Clk_s);
	#5 B_s <= 0;
	@(posedge Clk_s);
	@(posedge Clk_s);
	@(posedge Clk_s);
	@(posedge Clk_s);
#10 $finish;
end
endmodule

1_Excercise/dump.vcd
$date
	Wed Jan 08 16:42:55 2025
$end
$version
	Icarus Verilog
$end
$timescale
	1ns
$end
$scope module SampleFSM_Test $end
$var wire 1 ! X_s $end
$var reg 1 " B_s $end
$var reg 1 # Clk_s $end
$var reg 1 $ Rst_s $end
$scope module CompToTest $end
$var wire 1 " B $end
$var wire 1 # Clk $end
$var wire 1 $ Rst $end
$var parameter 32 % S_Off $end
$var parameter 32 & S_On1 $end
$var parameter 32 ' S_On2 $end
$var parameter 32 ( S_On3 $end
$var reg 2 ) State [1:0] $end
$var reg 2 * StateNext [1:0] $end
$var reg 1 ! X $end
$upscope $end
$upscope $end
$enddefinitions $end
$comment Show the parameter values. $end
$dumpall
b11 (
b10 '
b1 &
b0 %
$end
#0
$dumpvars
bx *
bx )
1$
0#
0"
x!
$end
#10
b0 *
0!
b0 )
1#
#15
0$
#20
0#
#30
1#
#35
b1 *
1"
#40
0#
#50
b10 *
1!
b1 )
1#
#55
0"
#60
0#
#70
b11 *
b10 )
1#
#80
0#
#90
b0 *
b11 )
1#
#100
0#
#110
0!
b0 )
1#
