3_Exercise/primeNumber.v

module primeNumber(numMax, clk, rst, prime, numberChecked, numberOfPrimes);
    //Delcare all the inputs here
    input [10:0] numMax; //You only need 10 bits, but we'll use 11 just in case
    input clk; 
    input rst;

    //Declare all outputs here
    output reg [10:0] prime; //Again we only need 10 bits but we'll use 11 just in case
    output reg [10:0] numberChecked; 
    output reg [10:0] numberOfPrimes; //There is no need for this many bits to be used, if we were to optimize this project, than maybe this number would be smaller

    //Declare Wire for prime lookups
    wire primeBool; //This is the value we can input into the module

    integer i;
    integer loopMax;
    integer count;  
    always @(posedge clk) begin
        count = 0; 
        if (rst == 0) begin

            //Setting up the for loop
            loopMax = numMax; 
            
            for (i = 2; i <= loopMax; i++) begin
                numberChecked = i; 
                //CASE STATEMENT WAS CHAT-GPT GENERATED
                //We double checked the AI with resource: https://www.vedantu.com/maths/prime-numbers-from-1-to-1000
                case (i)
                    // List of prime numbers
                    10'd2, 10'd3, 10'd5, 10'd7, 10'd11, 10'd13, 10'd17, 10'd19, 10'd23, 10'd29,
                    10'd31, 10'd37, 10'd41, 10'd43, 10'd47, 10'd53, 10'd59, 10'd61, 10'd67, 10'd71,
                    10'd73, 10'd79, 10'd83, 10'd89, 10'd97, 10'd101, 10'd103, 10'd107, 10'd109, 10'd113,
                    10'd127, 10'd131, 10'd137, 10'd139, 10'd149, 10'd151, 10'd157, 10'd163, 10'd167, 10'd173,
                    10'd179, 10'd181, 10'd191, 10'd193, 10'd197, 10'd199, 10'd211, 10'd223, 10'd227, 10'd229,
                    10'd233, 10'd239, 10'd241, 10'd251, 10'd257, 10'd263, 10'd269, 10'd271, 10'd277, 10'd281,
                    10'd283, 10'd293, 10'd307, 10'd311, 10'd313, 10'd317, 10'd331, 10'd337, 10'd347, 10'd349,
                    10'd353, 10'd359, 10'd367, 10'd373, 10'd379, 10'd383, 10'd389, 10'd397, 10'd401, 10'd409,
                    10'd419, 10'd421, 10'd431, 10'd433, 10'd439, 10'd443, 10'd449, 10'd457, 10'd461, 10'd463,
                    10'd467, 10'd479, 10'd487, 10'd491, 10'd499, 10'd503, 10'd509, 10'd521, 10'd523, 10'd541,
                    10'd547, 10'd557, 10'd563, 10'd569, 10'd571, 10'd577, 10'd587, 10'd593, 10'd599, 10'd601,
                    10'd607, 10'd613, 10'd617, 10'd619, 10'd631, 10'd641, 10'd643, 10'd647, 10'd653, 10'd659,
                    10'd661, 10'd673, 10'd677, 10'd683, 10'd691, 10'd701, 10'd709, 10'd719, 10'd727, 10'd733,
                    10'd739, 10'd743, 10'd751, 10'd757, 10'd761, 10'd769, 10'd773, 10'd787, 10'd797, 10'd809,
                    10'd811, 10'd821, 10'd823, 10'd827, 10'd829, 10'd839, 10'd853, 10'd857, 10'd859, 10'd863,
                    10'd877, 10'd881, 10'd883, 10'd887, 10'd907, 10'd911, 10'd919, 10'd929, 10'd937, 10'd941,
                    10'd947, 10'd953, 10'd967, 10'd971, 10'd977, 10'd983, 10'd991, 10'd997:
                        prime = 1;
                    //Make sure to always have a default case with case statements
                    default: prime = 0;
                endcase
                if (prime == 1) begin 
                    count++; 
                end
            end

            //Finally update the number of primes
            numberOfPrimes = count; 

        end

    end


endmodule

3_Exercise/tb_primeNumber.v
`include "primeNumber.v"

module tb_primeNumber(); 

    //Define the inputs as reg
    reg [10:0] numMax;
    reg clk; 
    reg rst;


    //Define the outputs as wires
    wire [10:0] prime; //Again we only need 10 bits but we'll use 11 just in case
    wire [10:0] numberChecked; 
    wire [10:0] numberOfPrimes; //There is no need for this many bits to be used, if we were to optimize this project, than maybe this number would be smaller


    //Initialize primeNumber module
    primeNumber pn(
        .numMax(numMax), 
        .clk(clk), 
        .rst(rst), 

        .prime(prime), 
        .numberChecked(numberChecked), 
        .numberOfPrimes(numberOfPrimes)
    );


    //Start the clock
    always begin
        clk = 1; 
        #10;
        clk = 0;
        #10;
    end

    integer i, j; 
    //Start the test cases
    initial begin
        $dumpvars(0, tb_primeNumber);
        for (i = 0; i < 1000; i++) begin //This will be the input for numMax
            numMax = i; 
            rst = 0; 

            //Now we need to run the clock cycles since this is a flop based design
            for (j = 0; j < i + 1; j++) begin 
                @(posedge clk);
            end
        end

        $finish;
    end




endmodule

3_Exercise/dump.vcd
$date
	Wed Jan 29 11:56:32 2025
$end
$version
	Icarus Verilog
$end
$timescale
	1s
$end
$scope module tb_primeNumber $end
$var wire 11 ! prime [10:0] $end
$var wire 11 " numberOfPrimes [10:0] $end
$var wire 11 # numberChecked [10:0] $end
$var reg 1 $ clk $end
$var reg 11 % numMax [10:0] $end
$var reg 1 & rst $end
$var integer 32 ' i [31:0] $end
$var integer 32 ( j [31:0] $end
$scope module pn $end
$var wire 1 $ clk $end
$var wire 11 ) numMax [10:0] $end
$var wire 1 & rst $end
$var reg 11 * numberChecked [10:0] $end
$var reg 11 + numberOfPrimes [10:0] $end
$var reg 11 , prime [10:0] $end
$var integer 32 - count [31:0] $end
$var integer 32 . i [31:0] $end
$var integer 32 / loopMax [31:0] $end
$upscope $end
$upscope $end
$enddefinitions $end
$comment Show the parameter values. $end
$dumpall
$end
#0
$dumpvars
b0 /
b10 .
b0 -
bx ,
b0 +
bx *
b0 )
b0 (
b0 '
0&
b0 %
1$
bx #
b0 "
bx !
$end
#10
0$
#20
b1 %
b1 )
b1 '
b0 (
1$
#30
0$
#40
b1 /
b1 (
1$
#50
0$
#60
b10 %
b10 )
b10 '
b0 (
1$
#70
0$
#80
b1 "
b1 +
b11 .
b1 -
b1 !
b1 ,
b10 #
b10 *
b10 /
b1 (
1$
#90
0$
#100
b10 (
b11 .
b1 -
1$
#110
0$
#120
b10 "
b10 +
b11 #
b11 *
b100 .
b11 /
b10 -
b11 %
b11 )
b11 '
b0 (
1$
#130
0$
#140
b1 (
b11 #
b11 *
b100 .
b10 -
1$
#150
0$
#160
b11 #
b11 *
b100 .
b10 -
b10 (
1$
#170
0$
#180
b11 (
b11 #
b11 *
b100 .
b10 -
1$
#190
0$
#200
b0 !
b0 ,
b100 #
b100 *
b101 .
b100 /
b10 -
b100 %
b100 )
b100 '
b0 (
1$
#210
0$
#220
b1 (
b0 !
b0 ,
b100 #
b100 *
b101 .
b10 -
1$
#230
0$
#240
b0 !
b0 ,
b100 #
b100 *
b101 .
b10 -
b10 (
1$
#250
0$
#260
b11 (
b0 !
b0 ,
b100 #
b100 *
b101 .
b10 -
1$
#270
0$
#280
b0 !
b0 ,
b100 #
b100 *
b101 .
b10 -
b100 (
1$
#290
0$
#300
b101 %
b101 )
b101 '
b0 (
b0 !
b0 ,
b100 #
b100 *
b101 .
b10 -
1$
#310
0$
#320
b11 "
b11 +
b1 !
b1 ,
b101 #
b101 *
b110 .
b101 /
b11 -
b1 (
1$
#330
0$
#340
b10 (
b1 !
b1 ,
b101 #
b101 *
b110 .
b11 -
1$
#350
0$
#360
b1 !
b1 ,
b101 #
b101 *
b110 .
b11 -
b11 (
1$
#370
0$
#380
b100 (
b1 !
b1 ,
b101 #
b101 *
b110 .
b11 -
1$
#390
0$
#400
b1 !
b1 ,
b101 #
b101 *
b110 .
b11 -
b101 (
1$
#410
0$
#420
b110 %
b110 )
b110 '
b0 (
b1 !
b1 ,
b101 #
b101 *
b110 .
b11 -
1$
#430
0$
#440
b0 !
b0 ,
b110 #
b110 *
b111 .
b110 /
b11 -
b1 (
1$
#450
0$
#460
b10 (
b0 !
b0 ,
b110 #
b110 *
b111 .
b11 -
1$
#470
0$
#480
b0 !
b0 ,
b110 #
b110 *
b111 .
b11 -
b11 (
1$
#490
0$
#500
b100 (
b0 !
b0 ,
b110 #
b110 *
b111 .
b11 -
1$
#510
0$
#520
b0 !
b0 ,
b110 #
b110 *
b111 .
b11 -
b101 (
1$
#530
0$
#540
b110 (
b0 !
b0 ,
b110 #
b110 *
b111 .
b11 -
1$
#550
0$
#560
b100 "
b100 +
b1 !
b1 ,
b111 #
b111 *
b1000 .
b111 /
b100 -
b111 %
b111 )
b111 '
b0 (
1$
#570
0$
#580
b1 (
b1 !
b1 ,
b111 #
b111 *
b1000 .
b100 -
1$
#590
0$
#600
b1 !
b1 ,
b111 #
b111 *
b1000 .
b100 -
b10 (
1$
#610
0$
#620
b11 (
b1 !
b1 ,
b111 #
b111 *
b1000 .
b100 -
1$
#630
0$
#640
b1 !
b1 ,
b111 #
b111 *
b1000 .
b100 -
b100 (
1$
#650
0$
#660
b101 (
b1 !
b1 ,
b111 #
b111 *
b1000 .
b100 -
1$
#670
0$
#680
b1 !
b1 ,
b111 #
b111 *
b1000 .
b100 -
b110 (
1$
#690
0$
#700
b111 (
b1 !
b1 ,
b111 #
b111 *
b1000 .
b100 -
1$
#710
0$
#720
b0 !
b0 ,
b1000 #
b1000 *
b1001 .
b1000 /
b100 -
b1000 %
b1000 )
b1000 '
b0 (
1$
#730
0$
#740
b1 (
b0 !
b0 ,
b1000 #
b1000 *
b1001 .
b100 -
1$
#750
0$
#760
b0 !
b0 ,
b1000 #
b1000 *
b1001 .
b100 -
b10 (
1$
#770
0$
#780
b11 (
b0 !
b0 ,
b1000 #
b1000 *
b1001 .
b100 -
1$
#790
0$
#800
b0 !
b0 ,
b1000 #
b1000 *
b1001 .
b100 -
b100 (
1$
#810
0$
#820
b101 (
b0 !
b0 ,
b1000 #
b1000 *
b1001 .
b100 -
1$
#830
0$
#840
b0 !
b0 ,
b1000 #
b1000 *
b1001 .
b100 -
b110 (
1$
#850
0$
#860
b111 (
b0 !
b0 ,
b1000 #
b1000 *
b1001 .
b100 -
1$
#870
0$
#880
b0 !
b0 ,
b1000 #
b1000 *
b1001 .
b100 -
b1000 (
1$
#890
0$
#900
b1001 %
b1001 )
b1001 '
b0 (
b0 !
b0 ,
b1000 #
b1000 *
b1001 .
b100 -
1$
#910
0$
#920
b0 !
b0 ,
b1001 #
b1001 *
b1010 .
b1001 /
b100 -
b1 (
1$
#930
0$
#940
b10 (
b0 !
b0 ,
b1001 #
b1001 *
b1010 .
b100 -
1$
#950
0$
#960
b0 !
b0 ,
b1001 #
b1001 *
b1010 .
b100 -
b11 (
1$
#970
0$
#980
b100 (
b0 !
b0 ,
b1001 #
b1001 *
b1010 .
b100 -
1$
#990
0$
#1000
b0 !
b0 ,
b1001 #
b1001 *
b1010 .
b100 -
b101 (
1$
#1010
0$
#1020
b110 (
b0 !
b0 ,
b1001 #
b1001 *
b1010 .
b100 -
1$
#1030
0$
#1040
b0 !
b0 ,
b1001 #
b1001 *
b1010 .
b100 -
b111 (
1$
#1050
0$
#1060
b1000 (
b0 !
b0 ,
b1001 #
b1001 *
b1010 .
b100 -
1$
#1070
0$
#1080
b0 !
b0 ,
b1001 #
b1001 *
b1010 .
b100 -
b1001 (
1$
#1090
0$
#1100
b1010 %
b1010 )
b1010 '
b0 (
b0 !
b0 ,
b1001 #
b1001 *
b1010 .
b100 -
1$
#1110
0$
#1120
b0 !
b0 ,
b1010 #
b1010 *
b1011 .
b1010 /
b100 -
b1 (
1$
#1130
0$
#1140
b10 (
b0 !
b0 ,
b1010 #
b1010 *
b1011 .
b100 -
1$
#1150
0$
#1160
b0 !
b0 ,
b1010 #
b1010 *
b1011 .
b100 -
b11 (
1$
#1170
0$
#1180
b100 (
b0 !
b0 ,
b1010 #
b1010 *
b1011 .
b100 -
1$
#1190
0$
#1200
b0 !
b0 ,
b1010 #
b1010 *
b1011 .
b100 -
b101 (
1$
#1210
0$
#1220
b110 (
b0 !
b0 ,
b1010 #
b1010 *
b1011 .
b100 -
1$
#1230
0$
#1240
b0 !
b0 ,
b1010 #
b1010 *
b1011 .
b100 -
b111 (
1$
#1250
0$
#1260
b1000 (
b0 !
b0 ,
b1010 #
b1010 *
b1011 .
b100 -
1$
#1270
0$
#1280
b0 !
b0 ,
b1010 #
b1010 *
b1011 .
b100 -
b1001 (
1$
#1290
0$
#1300
b1010 (
b0 !
b0 ,
b1010 #
b1010 *
b1011 .
b100 -
1$
#1310
0$
#1320
b101 "
b101 +
b1 !
b1 ,
b1011 #
b1011 *
b1100 .
b1011 /
b101 -
b1011 %
b1011 )
b1011 '
b0 (
1$
#1330
0$
#1340
b1 (
b1 !
b1 ,
b1011 #
b1011 *
b1100 .
b101 -
1$
#1350
0$
#1360
b1 !
b1 ,
b1011 #
b1011 *
b1100 .
b101 -
b10 (
1$
#1370
0$
#1380
b11 (
b1 !
b1 ,
b1011 #
b1011 *
b1100 .
b101 -
1$
#1390
0$
#1400
b1 !
b1 ,
b1011 #
b1011 *
b1100 .
b101 -
b100 (
1$
#1410
0$
#1420
b101 (
b1 !
b1 ,
b1011 #
b1011 *
b1100 .
b101 -
1$
#1430
0$
#1440
b1 !
b1 ,
b1011 #
b1011 *
b1100 .
b101 -
b110 (
1$
#1450
0$
#1460
b111 (
b1 !
b1 ,
b1011 #
b1011 *
b1100 .
b101 -
1$
#1470
0$
#1480
b1 !
b1 ,
b1011 #
b1011 *
b1100 .
b101 -
b1000 (
1$
#1490
0$
#1500
b1001 (
b1 !
b1 ,
b1011 #
b1011 *
b1100 .
b101 -
1$
#1510
0$
#1520
b1 !
b1 ,
b1011 #
b1011 *
b1100 .
b101 -
b1010 (
1$
#1530
0$
#1540
b1011 (
b1 !
b1 ,
b1011 #
b1011 *
b1100 .
b101 -
1$
#1550
0$
#1560
b0 !
b0 ,
b1100 #
b1100 *
b1101 .
b1100 /
b101 -
b1100 %
b1100 )
b1100 '
b0 (
1$
#1570
0$
#1580
b1 (
b0 !
b0 ,
b1100 #
b1100 *
b1101 .
b101 -
1$
#1590
0$
#1600
b0 !
b0 ,
b1100 #
b1100 *
b1101 .
b101 -
b10 (
1$
#1610
0$
#1620
b11 (
b0 !
b0 ,
b1100 #
b1100 *
b1101 .
b101 -
1$
#1630
0$
#1640
b0 !
b0 ,
b1100 #
b1100 *
b1101 .
b101 -
b100 (
1$
#1650
0$
#1660
b101 (
b0 !
b0 ,
b1100 #
b1100 *
b1101 .
b101 -
1$
#1670
0$
#1680
b0 !
b0 ,
b1100 #
b1100 *
b1101 .
b101 -
b110 (
1$
#1690
0$
#1700
b111 (
b0 !
b0 ,
b1100 #
b1100 *
b1101 .
b101 -
1$
#1710
0$
#1720
b0 !
b0 ,
b1100 #
b1100 *
b1101 .
b101 -
b1000 (
1$
#1730
0$
#1740
b1001 (
b0 !
b0 ,
b1100 #
b1100 *
b1101 .
b101 -
1$
#1750
0$
#1760
b0 !
b0 ,
b1100 #
b1100 *
b1101 .
b101 -
b1010 (
1$
#1770
0$
#1780
b1011 (
b0 !
b0 ,
b1100 #
b1100 *
b1101 .
b101 -
1$
#1790
0$
#1800
b0 !
b0 ,
b1100 #
b1100 *
b1101 .
b101 -
b1100 (
1$
#1810
0$
#1820
b1101 %
b1101 )
b1101 '
b0 (
b0 !
b0 ,
b1100 #
b1100 *
b1101 .
b101 -
1$
#1830
0$
#1840
b110 "
b110 +
b1 !
b1 ,
b1101 #
b1101 *
b1110 .
b1101 /
b110 -
b1 (
1$
#1850
0$
#1860
b10 (
b1 !
b1 ,
b1101 #
b1101 *
b1110 .
b110 -
1$
#1870
0$
#1880
b1 !
b1 ,
b1101 #
b1101 *
b1110 .
b110 -
b11 (
1$
#1890
0$
#1900
b100 (
b1 !
b1 ,
b1101 #
b1101 *
b1110 .
b110 -
1$
#1910
0$
#1920
b1 !
b1 ,
b1101 #
b1101 *
b1110 .
b110 -
b101 (
1$
#1930
0$
#1940
b110 (
b1 !
b1 ,
b1101 #
b1101 *
b1110 .
b110 -
1$
#1950
0$
#1960
b1 !
b1 ,
b1101 #
b1101 *
b1110 .
b110 -
b111 (
1$
#1970
0$
#1980
b1000 (
b1 !
b1 ,
b1101 #
b1101 *
b1110 .
b110 -
1$
#1990
0$
#2000
b1 !
b1 ,
b1101 #
b1101 *
b1110 .
b110 -
b1001 (
1$
#2010
0$
#2020
b1010 (
b1 !
b1 ,
b1101 #
b1101 *
b1110 .
b110 -
1$
#2030
0$
#2040
b1 !
b1 ,
b1101 #
b1101 *
b1110 .
b110 -
b1011 (
1$
#2050
0$
#2060
b1100 (
b1 !
b1 ,
b1101 #
b1101 *
b1110 .
b110 -
1$
#2070
0$
#2080
b1 !
b1 ,
b1101 #
b1101 *
b1110 .
b110 -
b1101 (
1$
#2090
0$
#2100
b1110 %
b1110 )
b1110 '
b0 (
b1 !
b1 ,
b1101 #
b1101 *
b1110 .
b110 -
1$
#2110
0$
#2120
b0 !
b0 ,
b1110 #
b1110 *
b1111 .
b1110 /
b110 -
b1 (
1$
#2130
0$
#2140
b10 (
b0 !
b0 ,
b1110 #
b1110 *
b1111 .
b110 -
1$
#2150
0$
#2160
b0 !
b0 ,
b1110 #
b1110 *
b1111 .
b110 -
b11 (
1$
#2170
0$
#2180
b100 (
b0 !
b0 ,
b1110 #
b1110 *
b1111 .
b110 -
1$
#2190
0$
#2200
b0 !
b0 ,
b1110 #
b1110 *
b1111 .
b110 -
b101 (
1$
#2210
0$
#2220
b110 (
b0 !
b0 ,
b1110 #
b1110 *
b1111 .
b110 -
1$
#2230
0$
#2240
b0 !
b0 ,
b1110 #
b1110 *
b1111 .
b110 -
b111 (
1$
#2250
0$
#2260
b1000 (
b0 !
b0 ,
b1110 #
b1110 *
b1111 .
b110 -
1$
#2270
0$
#2280
b0 !
b0 ,
b1110 #
b1110 *
b1111 .
b110 -
b1001 (
1$
#2290
0$
#2300
b1010 (
b0 !
b0 ,
b1110 #
b1110 *
b1111 .
b110 -
1$
#2310
0$
#2320
b0 !
b0 ,
b1110 #
b1110 *
b1111 .
b110 -
b1011 (
1$
#2330
0$
#2340
b1100 (
b0 !
b0 ,
b1110 #
b1110 *
b1111 .
b110 -
1$
#2350
0$
#2360
b0 !
b0 ,
b1110 #
b1110 *
b1111 .
b110 -
b1101 (
1$
#2370
0$
#2380
b1110 (
b0 !
b0 ,
b1110 #
b1110 *
b1111 .
b110 -
1$
#2390
0$
#2400
b0 !
b0 ,
b1111 #
b1111 *
b10000 .
b1111 /
b110 -
b1111 %
b1111 )
b1111 '
b0 (
1$
#2410
0$
#2420
b1 (
b0 !
b0 ,
b1111 #
b1111 *
b10000 .
b110 -
1$
#2430
0$
#2440
b0 !
b0 ,
b1111 #
b1111 *
b10000 .
b110 -
b10 (
1$
#2450
0$
#2460
b11 (
b0 !
b0 ,
b1111 #
b1111 *
b10000 .
b110 -
1$
#2470
0$
#2480
b0 !
b0 ,
b1111 #
b1111 *
b10000 .
b110 -
b100 (
1$
#2490
0$
#2500
b101 (
b0 !
b0 ,
b1111 #
b1111 *
b10000 .
b110 -
1$
#2510
0$
#2520
b0 !
b0 ,
b1111 #
b1111 *
b10000 .
b110 -
b110 (
1$
#2530
0$
#2540
b111 (
b0 !
b0 ,
b1111 #
b1111 *
b10000 .
b110 -
1$
#2550
0$
#2560
b0 !
b0 ,
b1111 #
b1111 *
b10000 .
b110 -
b1000 (
1$
#2570
0$
#2580
b1001 (
b0 !
b0 ,
b1111 #
b1111 *
b10000 .
b110 -
1$
#2590
0$
#2600
b0 !
b0 ,
b1111 #
b1111 *
b10000 .
b110 -
b1010 (
1$
#2610
0$
#2620
b1011 (
b0 !
b0 ,
b1111 #
b1111 *
b10000 .
b110 -
1$
#2630
0$
#2640
b0 !
b0 ,
b1111 #
b1111 *
b10000 .
b110 -
b1100 (
1$
#2650
0$
#2660
b1101 (
b0 !
b0 ,
b1111 #
b1111 *
b10000 .
b110 -
1$
#2670
0$
#2680
b0 !
b0 ,
b1111 #
b1111 *
b10000 .
b110 -
b1110 (
1$
#2690
0$
#2700
b1111 (
b0 !
b0 ,
b1111 #
b1111 *
b10000 .
b110 -
1$
#2710
0$
#2720
b0 !
b0 ,
b10000 #
b10000 *
b10001 .
b10000 /
b110 -
b10000 %
b10000 )
b10000 '
b0 (
1$
#2730
0$
#2740
b1 (
b0 !
b0 ,
b10000 #
b10000 *
b10001 .
b110 -
1$
#2750
0$
#2760
b0 !
b0 ,
b10000 #
b10000 *
b10001 .
b110 -
b10 (
1$
#2770
0$
#2780
b11 (
b0 !
b0 ,
b10000 #
b10000 *
b10001 .
b110 -
1$
#2790
0$
#2800
b0 !
b0 ,
b10000 #
b10000 *
b10001 .
b110 -
b100 (
1$
#2810
0$
#2820
b101 (
b0 !
b0 ,
b10000 #
b10000 *
b10001 .
b110 -
1$
#2830
0$
#2840
b0 !
b0 ,
b10000 #
b10000 *
b10001 .
b110 -
b110 (
1$
#2850
0$
#2860
b111 (
b0 !
b0 ,
b10000 #
b10000 *
b10001 .
b110 -
1$
#2870
0$
#2880
b0 !
b0 ,
b10000 #
b10000 *
b10001 .
b110 -
b1000 (
1$
#2890
0$
#2900
b1001 (
b0 !
b0 ,
b10000 #
b10000 *
b10001 .
b110 -
1$
#2910
0$
#2920
b0 !
b0 ,
b10000 #
b10000 *
b10001 .
b110 -
b1010 (
1$
#2930
0$
#2940
b1011 (
b0 !
b0 ,
b10000 #
b10000 *
b10001 .
b110 -
1$
#2950
0$
#2960
b0 !
b0 ,
b10000 #
b10000 *
b10001 .
b110 -
b1100 (
1$
#2970
0$
#2980
b1101 (
b0 !
b0 ,
b10000 #
b10000 *
b10001 .
b110 -
1$
#2990
0$
#3000
b0 !
b0 ,
b10000 #
b10000 *
b10001 .
b110 -
b1110 (
1$
#3010
0$
#3020
b1111 (
b0 !
b0 ,
b10000 #
b10000 *
b10001 .
b110 -
1$
#3030
0$
#3040
b0 !
b0 ,
b10000 #
b10000 *
b10001 .
b110 -
b10000 (
1$
#3050
0$
#3060
b10001 %
b10001 )
b10001 '
b0 (
b0 !
b0 ,
b10000 #
b10000 *
b10001 .
b110 -
1$
#3070
0$
#3080
b111 "
b111 +
b1 !
b1 ,
b10001 #
b10001 *
b10010 .
b10001 /
b111 -
b1 (
1$
#3090
0$
#3100
b10 (
b1 !
b1 ,
b10001 #
b10001 *
b10010 .
b111 -
1$
#3110
0$
#3120
b1 !
b1 ,
b10001 #
b10001 *
b10010 .
b111 -
b11 (
1$
#3130
0$
#3140
b100 (
b1 !
b1 ,
b10001 #
b10001 *
b10010 .
b111 -
1$
#3150
0$
#3160
b1 !
b1 ,
b10001 #
b10001 *
b10010 .
b111 -
b101 (
1$
#3170
0$
#3180
b110 (
b1 !
b1 ,
b10001 #
b10001 *
b10010 .
b111 -
1$
#3190
0$
#3200
b1 !
b1 ,
b10001 #
b10001 *
b10010 .
b111 -
b111 (
1$
#3210
0$
#3220
b1000 (
b1 !
b1 ,
b10001 #
b10001 *
b10010 .
b111 -
1$
#3230
0$
#3240
b1 !
b1 ,
b10001 #
b10001 *
b10010 .
b111 -
b1001 (
1$
#3250
0$
#3260
b1010 (
b1 !
b1 ,
b10001 #
b10001 *
b10010 .
b111 -
1$
#3270
0$
#3280
b1 !
b1 ,
b10001 #
b10001 *
b10010 .
b111 -
b1011 (
1$
#3290
0$
#3300
b1100 (
b1 !
b1 ,
b10001 #
b10001 *
b10010 .
b111 -
1$
#3310
0$
#3320
b1 !
b1 ,
b10001 #
b10001 *
b10010 .
b111 -
b1101 (
1$
#3330
0$
#3340
b1110 (
b1 !
b1 ,
b10001 #
b10001 *
b10010 .
b111 -
1$
#3350
0$
#3360
b1 !
b1 ,
b10001 #
b10001 *
b10010 .
b111 -
b1111 (
1$
#3370
0$
#3380
b10000 (
b1 !
b1 ,
b10001 #
b10001 *
b10010 .
b111 -
1$
#3390
0$
#3400
b1 !
b1 ,
b10001 #
b10001 *
b10010 .
b111 -
b10001 (
1$
#3410
0$
#3420
b10010 %
b10010 )
b10010 '
b0 (
b1 !
b1 ,
b10001 #
b10001 *
b10010 .
b111 -
1$
#3430
0$
#3440
b0 !
b0 ,
b10010 #
b10010 *
b10011 .
b10010 /
b111 -
b1 (
1$
#3450
0$
#3460
b10 (
b0 !
b0 ,
b10010 #
b10010 *
b10011 .
b111 -
1$
#3470
0$
#3480
b0 !
b0 ,
b10010 #
b10010 *
b10011 .
b111 -
b11 (
1$
#3490
0$
#3500
b100 (
b0 !
b0 ,
b10010 #
b10010 *
b10011 .
b111 -
1$
#3510
0$
#3520
b0 !
b0 ,
b10010 #
b10010 *
b10011 .
b111 -
b101 (
1$
#3530
0$
#3540
b110 (
b0 !
b0 ,
b10010 #
b10010 *
b10011 .
b111 -
1$
#3550
0$
#3560
b0 !
b0 ,
b10010 #
b10010 *
b10011 .
b111 -
b111 (
1$
#3570
0$
#3580
b1000 (
b0 !
b0 ,
b10010 #
b10010 *
b10011 .
b111 -
1$
#3590
0$
#3600
b0 !
b0 ,
b10010 #
b10010 *
b10011 .
b111 -
b1001 (
1$
#3610
0$
#3620
b1010 (
b0 !
b0 ,
b10010 #
b10010 *
b10011 .
b111 -
1$
#3630
0$
#3640
b0 !
b0 ,
b10010 #
b10010 *
b10011 .
b111 -
b1011 (
1$
#3650
0$
#3660
b1100 (
b0 !
b0 ,
b10010 #
b10010 *
b10011 .
b111 -
1$
#3670
0$
#3680
b0 !
b0 ,
b10010 #
b10010 *
b10011 .
b111 -
b1101 (
1$
#3690
0$
#3700
b1110 (
b0 !
b0 ,
b10010 #
b10010 *
b10011 .
b111 -
1$
#3710
0$
#3720
b0 !
b0 ,
b10010 #
b10010 *
b10011 .
b111 -
b1111 (
1$
#3730
0$
#3740
b10000 (
b0 !
b0 ,
b10010 #
b10010 *
b10011 .
b111 -
1$
#3750
0$
#3760
b0 !
b0 ,
b10010 #
b10010 *
b10011 .
b111 -
b10001 (
1$
#3770
0$
#3780
b10010 (
b0 !
b0 ,
b10010 #
b10010 *
b10011 .
b111 -
1$
#3790
0$
#3800
b1000 "
b1000 +
b1 !
b1 ,
b10011 #
b10011 *
b10100 .
b10011 /
b1000 -
b10011 %
b10011 )
b10011 '
b0 (
1$
#3810
0$
#3820
b1 (
b1 !
b1 ,
b10011 #
b10011 *
b10100 .
b1000 -
1$
#3830
0$
#3840
b1 !
b1 ,
b10011 #
b10011 *
b10100 .
b1000 -
b10 (
1$
#3850
0$
#3860
b11 (
b1 !
b1 ,
b10011 #
b10011 *
b10100 .
b1000 -
1$
#3870
0$
#3880
b1 !
b1 ,
b10011 #
b10011 *
b10100 .
b1000 -
b100 (
1$
#3890
0$
#3900
b101 (
b1 !
b1 ,
b10011 #
b10011 *
b10100 .
b1000 -
1$
#3910
0$
#3920
b1 !
b1 ,
b10011 #
b10011 *
b10100 .
b1000 -
b110 (
1$
#3930
0$
#3940
b111 (
b1 !
b1 ,
b10011 #
b10011 *
b10100 .
b1000 -
1$
#3950
0$
#3960
b1 !
b1 ,
b10011 #
b10011 *
b10100 .
b1000 -
b1000 (
1$
#3970
0$
#3980
b1001 (
b1 !
b1 ,
b10011 #
b10011 *
b10100 .
b1000 -
1$
#3990
0$
#4000
b1 !
b1 ,
b10011 #
b10011 *
b10100 .
b1000 -
b1010 (
1$
#4010
0$
#4020
b1011 (
b1 !
b1 ,
b10011 #
b10011 *
b10100 .
b1000 -
1$
#4030
0$
#4040
b1 !
b1 ,
b10011 #
b10011 *
b10100 .
b1000 -
b1100 (
1$
#4050
0$
#4060
b1101 (
b1 !
b1 ,
b10011 #
b10011 *
b10100 .
b1000 -
1$
#4070
0$
#4080
b1 !
b1 ,
b10011 #
b10011 *
b10100 .
b1000 -
b1110 (
1$
#4090
0$
#4100
b1111 (
b1 !
b1 ,
b10011 #
b10011 *
b10100 .
b1000 -
1$
#4110
0$
#4120
b1 !
b1 ,
b10011 #
b10011 *
b10100 .
b1000 -
b10000 (
1$
#4130
0$
#4140
b10001 (
b1 !
b1 ,
b10011 #
b10011 *
b10100 .
b1000 -
1$
#4150
0$
#4160
b1 !
b1 ,
b10011 #
b10011 *
b10100 .
b1000 -
b10010 (
1$
#4170
0$
#4180
b10011 (
b1 !
b1 ,
b10011 #
b10011 *
b10100 .
b1000 -
1$
#4190
0$
#4200
b0 !
b0 ,
b10100 #
b10100 *
b10101 .
b10100 /
b1000 -
b10100 %
b10100 )
b10100 '
b0 (
1$
#4210
0$
#4220
b1 (
b0 !
b0 ,
b10100 #
b10100 *
b10101 .
b1000 -
1$
#4230
0$
#4240
b0 !
b0 ,
b10100 #
b10100 *
b10101 .
b1000 -
b10 (
1$
#4250
0$
#4260
b11 (
b0 !
b0 ,
b10100 #
b10100 *
b10101 .
b1000 -
1$
#4270
0$
#4280
b0 !
b0 ,
b10100 #
b10100 *
b10101 .
b1000 -
b100 (
1$
#4290
0$
#4300
b101 (
b0 !
b0 ,
b10100 #
b10100 *
b10101 .
b1000 -
1$
#4310
0$
#4320
b0 !
b0 ,
b10100 #
b10100 *
b10101 .
b1000 -
b110 (
1$
#4330
0$
#4340
b111 (
b0 !
b0 ,
b10100 #
b10100 *
b10101 .
b1000 -
1$
#4350
0$
#4360
b0 !
b0 ,
b10100 #
b10100 *
b10101 .
b1000 -
b1000 (
1$
#4370
0$
#4380
b1001 (
b0 !
b0 ,
b10100 #
b10100 *
b10101 .
b1000 -
1$
#4390
0$
#4400
b0 !
b0 ,
b10100 #
b10100 *
b10101 .
b1000 -
b1010 (
1$
#4410
0$
#4420
b1011 (
b0 !
b0 ,
b10100 #
b10100 *
b10101 .
b1000 -
1$
#4430
0$
#4440
b0 !
b0 ,
b10100 #
b10100 *
b10101 .
b1000 -
b1100 (
1$
#4450
0$
#4460
b1101 (
b0 !
b0 ,
b10100 #
b10100 *
b10101 .
b1000 -
1$
#4470
0$
#4480
b0 !
b0 ,
b10100 #
b10100 *
b10101 .
b1000 -
b1110 (
1$
#4490
0$
#4500
b1111 (
b0 !
b0 ,
b10100 #
b10100 *
b10101 .
b1000 -
1$
#4510
0$
#4520
b0 !
b0 ,
b10100 #
b10100 *
b10101 .
b1000 -
b10000 (
1$
#4530
0$
#4540
b10001 (
b0 !
b0 ,
b10100 #
b10100 *
b10101 .
b1000 -
1$
#4550
0$
