3_Exercise/primeNumber.v

module primeNumber(numMax, clk, rst, prime, numberChecked, numberOfPrimes);
    //Delcare all the inputs here
    input [10:0] numMax; //You only need 10 bits, but we'll use 11 just in case
    input clk; 
    input rst;

    //Declare all outputs here
    output reg prime;
    output reg [10:0] numberChecked; 
    output reg [10:0] numberOfPrimes; //There is no need for this many bits to be used, if we were to optimize this project, than maybe this number would be smaller

    //Declare Wire for prime lookups

    integer i;
    integer loopMax;
    integer count;  
    integer primeTemp; 

    //Parameters for states
    parameter sOff = 0, sInit = 1, sCalc = 2, sSet = 3, sDone = 4; 

    reg [2:0] state, stateNext;

    //Memory State
    always @(posedge clk) begin 
        state <= stateNext; 
    end


    //Next State Logic
    always @(posedge clk, rst) begin  
        if (rst == 1) begin 
            state = sOff;
        end 
        else begin
            state = stateNext;
        end


        case(state)

            sOff: begin 
                if (rst == 0) begin 
                    stateNext = sInit; 
                end else begin 
                    stateNext = sOff; 
                end
            end

            sInit: begin 
                //Initialize all our variables
                count = 0; 
                i = 2;

                //Move states
                stateNext = sCalc; 
            end

            sCalc: begin 
                 
                //CASE STATEMENT WAS CHAT-GPT GENERATED
                //We double checked the AI with resource: https://www.vedantu.com/maths/prime-numbers-from-1-to-1000
                case (i)
                    // List of prime numbers
                    10'd2, 10'd3, 10'd5, 10'd7, 10'd11, 10'd13, 10'd17, 10'd19, 10'd23, 10'd29,
                    10'd31, 10'd37, 10'd41, 10'd43, 10'd47, 10'd53, 10'd59, 10'd61, 10'd67, 10'd71,
                    10'd73, 10'd79, 10'd83, 10'd89, 10'd97, 10'd101, 10'd103, 10'd107, 10'd109, 10'd113,
                    10'd127, 10'd131, 10'd137, 10'd139, 10'd149, 10'd151, 10'd157, 10'd163, 10'd167, 10'd173,
                    10'd179, 10'd181, 10'd191, 10'd193, 10'd197, 10'd199, 10'd211, 10'd223, 10'd227, 10'd229,
                    10'd233, 10'd239, 10'd241, 10'd251, 10'd257, 10'd263, 10'd269, 10'd271, 10'd277, 10'd281,
                    10'd283, 10'd293, 10'd307, 10'd311, 10'd313, 10'd317, 10'd331, 10'd337, 10'd347, 10'd349,
                    10'd353, 10'd359, 10'd367, 10'd373, 10'd379, 10'd383, 10'd389, 10'd397, 10'd401, 10'd409,
                    10'd419, 10'd421, 10'd431, 10'd433, 10'd439, 10'd443, 10'd449, 10'd457, 10'd461, 10'd463,
                    10'd467, 10'd479, 10'd487, 10'd491, 10'd499, 10'd503, 10'd509, 10'd521, 10'd523, 10'd541,
                    10'd547, 10'd557, 10'd563, 10'd569, 10'd571, 10'd577, 10'd587, 10'd593, 10'd599, 10'd601,
                    10'd607, 10'd613, 10'd617, 10'd619, 10'd631, 10'd641, 10'd643, 10'd647, 10'd653, 10'd659,
                    10'd661, 10'd673, 10'd677, 10'd683, 10'd691, 10'd701, 10'd709, 10'd719, 10'd727, 10'd733,
                    10'd739, 10'd743, 10'd751, 10'd757, 10'd761, 10'd769, 10'd773, 10'd787, 10'd797, 10'd809,
                    10'd811, 10'd821, 10'd823, 10'd827, 10'd829, 10'd839, 10'd853, 10'd857, 10'd859, 10'd863,
                    10'd877, 10'd881, 10'd883, 10'd887, 10'd907, 10'd911, 10'd919, 10'd929, 10'd937, 10'd941,
                    10'd947, 10'd953, 10'd967, 10'd971, 10'd977, 10'd983, 10'd991, 10'd997:
                        primeTemp = 1;
                    //Make sure to always have a default case with case statements
                    default: primeTemp = 0;
                endcase
               
                stateNext = sSet; 
                

            end

            sSet: begin 
                if (prime == 1) begin 
                    count++; 
                end

                 if (i == 2) begin 
                    i++; 
                end 
                else begin 
                    i = i + 2; 
                end

                //Now we do the logic for moving the states
                if (i <= numMax) begin //Its important to make sure that we do equal to so we also check if the number inputted is a prime
                    //Update State
                    stateNext = sCalc;  

                end else begin 
                    stateNext = sDone; 
                end
            end

            sDone: begin 
                stateNext = sOff; 
            end

            default: 
                stateNext = sInit;

        endcase

    end

    //Here we decide the outputs
    always @(state) begin 
        //outputs to determine
        if (state == sCalc || stateNext == sCalc) begin 
            numberChecked = i;
            prime = primeTemp; 
            numberOfPrimes = count; 
        end     

        if (state == sDone) begin 
            //Now we just need to update our last things 
            prime = 0; 
        end



    end
    


endmodule

3_Exercise/tb_primeNumber.v
`include "primeNumber.v"
`timescale 1ns/1ns

module tb_primeNumber(); 

    //Define the inputs as reg
    reg [10:0] numMax;
    reg clk; 
    reg rst;


    //Define the outputs as wires
    wire prime; //Again we only need 10 bits but we'll use 11 just in case
    wire [10:0] numberChecked; 
    wire [10:0] numberOfPrimes; //There is no need for this many bits to be used, if we were to optimize this project, than maybe this number would be smaller

    //Create a reg to prove that it is correct or not. 

    //Initialize primeNumber module
    primeNumber pn(
        .numMax(numMax), 
        .clk(clk), 
        .rst(rst), 

        .prime(prime), 
        .numberChecked(numberChecked), 
        .numberOfPrimes(numberOfPrimes)
    );


    //Start the clock
    always begin
        clk = 1; 
        #10;
        clk = 0;
        #10;
    end

    integer k, primeOrNah;

    always @(numberChecked) begin
        if (numberChecked <= 1) begin
            primeOrNah = 0;  // Not prime
        end 
        else if (numberChecked <= 3) begin
            primeOrNah = 1;  // 2 and 3 are prime
        end 
        else if (numberChecked % 2 == 0) begin
            primeOrNah = 0;  // Even numbers (except 2) are not prime
        end 
        else begin
            primeOrNah = 1;  // Assume prime
            for (k = 3; k * k <= numberChecked; k = k + 2) begin
                if (numberChecked % k == 0) begin
                    primeOrNah = 0;  // Found a divisor, not prime
                end
            end
        end
    end

    integer i, j; 
    //Start the test cases
    initial begin
        $dumpvars(0, tb_primeNumber);


        //Singular Test Cases
        numMax = 100; 
        rst = 0; 

        //Now we need to run the clock cycles since this is a flop based design
        for (j = 0; j < numMax+1; j++) begin 
            @(posedge clk);
        end

        

        $finish;
    end




endmodule

3_Exercise/dump.vcd
$date
	Thu Jan 30 19:08:00 2025
$end
$version
	Icarus Verilog
$end
$timescale
	1ns
$end
$scope module tb_primeNumber $end
$var wire 1 ! prime $end
$var wire 11 " numberOfPrimes [10:0] $end
$var wire 11 # numberChecked [10:0] $end
$var reg 1 $ clk $end
$var reg 11 % numMax [10:0] $end
$var reg 1 & rst $end
$var integer 32 ' j [31:0] $end
$var integer 32 ( k [31:0] $end
$var integer 32 ) primeOrNah [31:0] $end
$scope module pn $end
$var wire 1 $ clk $end
$var wire 11 * numMax [10:0] $end
$var wire 1 & rst $end
$var parameter 32 + sCalc $end
$var parameter 32 , sDone $end
$var parameter 32 - sInit $end
$var parameter 32 . sOff $end
$var parameter 32 / sSet $end
$var reg 11 0 numberChecked [10:0] $end
$var reg 11 1 numberOfPrimes [10:0] $end
$var reg 1 ! prime $end
$var reg 3 2 state [2:0] $end
$var reg 3 3 stateNext [2:0] $end
$var integer 32 4 count [31:0] $end
$var integer 32 5 i [31:0] $end
$var integer 32 6 primeTemp [31:0] $end
$upscope $end
$upscope $end
$enddefinitions $end
$comment Show the parameter values. $end
$dumpall
b11 /
b0 .
b1 -
b100 ,
b10 +
$end
#0
$dumpvars
bx 6
bx 5
bx 4
b1 3
bx 2
bx 1
bx 0
b1100100 *
bx )
bx (
b0 '
0&
b1100100 %
1$
bx #
bx "
x!
$end
#10
0$
#20
b1 )
b0 "
b0 1
b10 #
b10 0
b10 3
b10 5
b0 4
b1 2
b1 '
1$
#30
0$
#40
1!
b11 3
b1 6
b10 2
b10 '
1$
#50
0$
#60
b1 "
b1 1
b11 #
b11 0
b10 3
b11 5
b1 4
b11 2
b11 '
1$
#70
0$
#80
b11 3
b10 2
b100 '
1$
#90
0$
#100
b11 (
b10 "
b10 1
b101 #
b101 0
b10 3
b101 5
b10 4
b11 2
b101 '
1$
#110
0$
#120
b11 3
b10 2
b110 '
1$
#130
0$
#140
b11 "
b11 1
b111 #
b111 0
b10 3
b111 5
b11 4
b11 2
b111 '
1$
#150
0$
#160
b11 3
b10 2
b1000 '
1$
#170
0$
#180
b101 (
b0 )
b100 "
b100 1
b1001 #
b1001 0
b10 3
b1001 5
b100 4
b11 2
b1001 '
1$
#190
0$
#200
0!
b11 3
b0 6
b10 2
b1010 '
1$
#210
0$
#220
b101 (
b1 )
b1011 #
b1011 0
b10 3
b1011 5
b11 2
b1011 '
1$
#230
0$
#240
1!
b11 3
b1 6
b10 2
b1100 '
1$
#250
0$
#260
b101 (
b101 "
b101 1
b1101 #
b1101 0
b10 3
b1101 5
b101 4
b11 2
b1101 '
1$
#270
0$
#280
b11 3
b10 2
b1110 '
1$
#290
0$
#300
b0 )
b101 (
b110 "
b110 1
b1111 #
b1111 0
b10 3
b1111 5
b110 4
b11 2
b1111 '
1$
#310
0$
#320
0!
b11 3
b0 6
b10 2
b10000 '
1$
#330
0$
#340
b101 (
b1 )
b10001 #
b10001 0
b10 3
b10001 5
b11 2
b10001 '
1$
#350
0$
#360
1!
b11 3
b1 6
b10 2
b10010 '
1$
#370
0$
#380
b101 (
b111 "
b111 1
b10011 #
b10011 0
b10 3
b10011 5
b111 4
b11 2
b10011 '
1$
#390
0$
#400
b11 3
b10 2
b10100 '
1$
#410
0$
#420
b0 )
b101 (
b1000 "
b1000 1
b10101 #
b10101 0
b10 3
b10101 5
b1000 4
b11 2
b10101 '
1$
#430
0$
#440
0!
b11 3
b0 6
b10 2
b10110 '
1$
#450
0$
#460
b101 (
b1 )
b10111 #
b10111 0
b10 3
b10111 5
b11 2
b10111 '
1$
#470
0$
#480
1!
b11 3
b1 6
b10 2
b11000 '
1$
#490
0$
#500
b0 )
b111 (
b1001 "
b1001 1
b11001 #
b11001 0
b10 3
b11001 5
b1001 4
b11 2
b11001 '
1$
#510
0$
#520
0!
b11 3
b0 6
b10 2
b11010 '
1$
#530
0$
#540
b111 (
b0 )
b11011 #
b11011 0
b10 3
b11011 5
b11 2
b11011 '
1$
#550
0$
#560
b11 3
b10 2
b11100 '
1$
#570
0$
#580
b111 (
b1 )
b11101 #
b11101 0
b10 3
b11101 5
b11 2
b11101 '
1$
#590
0$
#600
1!
b11 3
b1 6
b10 2
b11110 '
1$
#610
0$
#620
b111 (
b1010 "
b1010 1
b11111 #
b11111 0
b10 3
b11111 5
b1010 4
b11 2
b11111 '
1$
#630
0$
#640
b11 3
b10 2
b100000 '
1$
#650
0$
#660
b0 )
b111 (
b1011 "
b1011 1
b100001 #
b100001 0
b10 3
b100001 5
b1011 4
b11 2
b100001 '
1$
#670
0$
#680
0!
b11 3
b0 6
b10 2
b100010 '
1$
#690
0$
#700
b111 (
b0 )
b100011 #
b100011 0
b10 3
b100011 5
b11 2
b100011 '
1$
#710
0$
#720
b11 3
b10 2
b100100 '
1$
#730
0$
#740
b111 (
b1 )
b100101 #
b100101 0
b10 3
b100101 5
b11 2
b100101 '
1$
#750
0$
#760
1!
b11 3
b1 6
b10 2
b100110 '
1$
#770
0$
#780
b0 )
b111 (
b1100 "
b1100 1
b100111 #
b100111 0
b10 3
b100111 5
b1100 4
b11 2
b100111 '
1$
#790
0$
#800
0!
b11 3
b0 6
b10 2
b101000 '
1$
#810
0$
#820
b111 (
b1 )
b101001 #
b101001 0
b10 3
b101001 5
b11 2
b101001 '
1$
#830
0$
#840
1!
b11 3
b1 6
b10 2
b101010 '
1$
#850
0$
#860
b111 (
b1101 "
b1101 1
b101011 #
b101011 0
b10 3
b101011 5
b1101 4
b11 2
b101011 '
1$
#870
0$
#880
b11 3
b10 2
b101100 '
1$
#890
0$
#900
b0 )
b111 (
b1110 "
b1110 1
b101101 #
b101101 0
b10 3
b101101 5
b1110 4
b11 2
b101101 '
1$
#910
0$
#920
0!
b11 3
b0 6
b10 2
b101110 '
1$
#930
0$
#940
b111 (
b1 )
b101111 #
b101111 0
b10 3
b101111 5
b11 2
b101111 '
1$
#950
0$
#960
1!
b11 3
b1 6
b10 2
b110000 '
1$
#970
0$
#980
b0 )
b1001 (
b1111 "
b1111 1
b110001 #
b110001 0
b10 3
b110001 5
b1111 4
b11 2
b110001 '
1$
#990
0$
#1000
0!
b11 3
b0 6
b10 2
b110010 '
1$
#1010
0$
#1020
b1001 (
b0 )
b110011 #
b110011 0
b10 3
b110011 5
b11 2
b110011 '
1$
#1030
0$
#1040
b11 3
b10 2
b110100 '
1$
#1050
0$
#1060
b1001 (
b1 )
b110101 #
b110101 0
b10 3
b110101 5
b11 2
b110101 '
1$
#1070
0$
#1080
1!
b11 3
b1 6
b10 2
b110110 '
1$
#1090
0$
#1100
b0 )
b1001 (
b10000 "
b10000 1
b110111 #
b110111 0
b10 3
b110111 5
b10000 4
b11 2
b110111 '
1$
#1110
0$
#1120
0!
b11 3
b0 6
b10 2
b111000 '
1$
#1130
0$
#1140
b1001 (
b0 )
b111001 #
b111001 0
b10 3
b111001 5
b11 2
b111001 '
1$
#1150
0$
#1160
b11 3
b10 2
b111010 '
1$
#1170
0$
#1180
b1001 (
b1 )
b111011 #
b111011 0
b10 3
b111011 5
b11 2
b111011 '
1$
#1190
0$
#1200
1!
b11 3
b1 6
b10 2
b111100 '
1$
#1210
0$
#1220
b1001 (
b10001 "
b10001 1
b111101 #
b111101 0
b10 3
b111101 5
b10001 4
b11 2
b111101 '
1$
#1230
0$
#1240
b11 3
b10 2
b111110 '
1$
#1250
0$
#1260
b0 )
b1001 (
b10010 "
b10010 1
b111111 #
b111111 0
b10 3
b111111 5
b10010 4
b11 2
b111111 '
1$
#1270
0$
#1280
0!
b11 3
b0 6
b10 2
b1000000 '
1$
#1290
0$
#1300
b1001 (
b0 )
b1000001 #
b1000001 0
b10 3
b1000001 5
b11 2
b1000001 '
1$
#1310
0$
#1320
b11 3
b10 2
b1000010 '
1$
#1330
0$
#1340
b1001 (
b1 )
b1000011 #
b1000011 0
b10 3
b1000011 5
b11 2
b1000011 '
1$
#1350
0$
#1360
1!
b11 3
b1 6
b10 2
b1000100 '
1$
#1370
0$
#1380
b0 )
b1001 (
b10011 "
b10011 1
b1000101 #
b1000101 0
b10 3
b1000101 5
b10011 4
b11 2
b1000101 '
1$
#1390
0$
#1400
0!
b11 3
b0 6
b10 2
b1000110 '
1$
#1410
0$
#1420
b1001 (
b1 )
b1000111 #
b1000111 0
b10 3
b1000111 5
b11 2
b1000111 '
1$
#1430
0$
#1440
1!
b11 3
b1 6
b10 2
b1001000 '
1$
#1450
0$
#1460
b1001 (
b10100 "
b10100 1
b1001001 #
b1001001 0
b10 3
b1001001 5
b10100 4
b11 2
b1001001 '
1$
#1470
0$
#1480
b11 3
b10 2
b1001010 '
1$
#1490
0$
#1500
b0 )
b1001 (
b10101 "
b10101 1
b1001011 #
b1001011 0
b10 3
b1001011 5
b10101 4
b11 2
b1001011 '
1$
#1510
0$
#1520
0!
b11 3
b0 6
b10 2
b1001100 '
1$
#1530
0$
#1540
b1001 (
b0 )
b1001101 #
b1001101 0
b10 3
b1001101 5
b11 2
b1001101 '
1$
#1550
0$
#1560
b11 3
b10 2
b1001110 '
1$
#1570
0$
#1580
b1001 (
b1 )
b1001111 #
b1001111 0
b10 3
b1001111 5
b11 2
b1001111 '
1$
#1590
0$
#1600
1!
b11 3
b1 6
b10 2
b1010000 '
1$
#1610
0$
#1620
b0 )
b1011 (
b10110 "
b10110 1
b1010001 #
b1010001 0
b10 3
b1010001 5
b10110 4
b11 2
b1010001 '
1$
#1630
0$
#1640
0!
b11 3
b0 6
b10 2
b1010010 '
1$
#1650
0$
#1660
b1011 (
b1 )
b1010011 #
b1010011 0
b10 3
b1010011 5
b11 2
b1010011 '
1$
#1670
0$
#1680
1!
b11 3
b1 6
b10 2
b1010100 '
1$
#1690
0$
#1700
b0 )
b1011 (
b10111 "
b10111 1
b1010101 #
b1010101 0
b10 3
b1010101 5
b10111 4
b11 2
b1010101 '
1$
#1710
0$
#1720
0!
b11 3
b0 6
b10 2
b1010110 '
1$
#1730
0$
#1740
b1011 (
b0 )
b1010111 #
b1010111 0
b10 3
b1010111 5
b11 2
b1010111 '
1$
#1750
0$
#1760
b11 3
b10 2
b1011000 '
1$
#1770
0$
#1780
b1011 (
b1 )
b1011001 #
b1011001 0
b10 3
b1011001 5
b11 2
b1011001 '
1$
#1790
0$
#1800
1!
b11 3
b1 6
b10 2
b1011010 '
1$
#1810
0$
#1820
b0 )
b1011 (
b11000 "
b11000 1
b1011011 #
b1011011 0
b10 3
b1011011 5
b11000 4
b11 2
b1011011 '
1$
#1830
0$
#1840
0!
b11 3
b0 6
b10 2
b1011100 '
1$
#1850
0$
#1860
b1011 (
b0 )
b1011101 #
b1011101 0
b10 3
b1011101 5
b11 2
b1011101 '
1$
#1870
0$
#1880
b11 3
b10 2
b1011110 '
1$
#1890
0$
#1900
b1011 (
b0 )
b1011111 #
b1011111 0
b10 3
b1011111 5
b11 2
b1011111 '
1$
#1910
0$
#1920
b11 3
b10 2
b1100000 '
1$
#1930
0$
#1940
b1011 (
b1 )
b1100001 #
b1100001 0
b10 3
b1100001 5
b11 2
b1100001 '
1$
#1950
0$
#1960
1!
b11 3
b1 6
b10 2
b1100010 '
1$
#1970
0$
#1980
b0 )
b1011 (
b11001 "
b11001 1
b1100011 #
b1100011 0
b10 3
b1100011 5
b11001 4
b11 2
b1100011 '
1$
#1990
0$
#2000
0!
b11 3
b0 6
b10 2
b1100100 '
1$
#2010
0$
#2020
b100 3
b1100101 5
b11 2
b1100101 '
1$
