3_Exercise/primeNumber.v

module primeNumber(numMax, clk, rst, prime, numberChecked, numberOfPrimes);
    //Delcare all the inputs here
    input [10:0] numMax; //You only need 10 bits, but we'll use 11 just in case
    input clk; 
    input rst;

    //Declare all outputs here
    output reg prime;
    output reg [10:0] numberChecked; 
    output reg [10:0] numberOfPrimes; //There is no need for this many bits to be used, if we were to optimize this project, than maybe this number would be smaller

    //Declare Wire for prime lookups

    integer i;
    integer loopMax;
    integer count;  
    integer primeTemp = 0; 

    //Parameters for states
    parameter sOff = 0, sInit = 1, sCalc = 2, sSet = 3, sDone = 4; 

    reg [2:0] state, stateNext;

    //Memory State
    always @(posedge clk) begin 
        state <= stateNext; 
        
    end


    //Next State Logic
    always @(posedge clk, rst) begin  
        if (rst == 1) begin 
            state = sOff;
        end 
        else begin
            state = stateNext;
        end

        prime <= primeTemp;

        case(state)

            sOff: begin 
                if (rst == 0) begin 
                    stateNext = sInit; 
                end else begin 
                    stateNext = sOff; 
                end
            end

            sInit: begin 
                //Initialize all our variables
                count = 0; 
                i = 1;
                primeTemp = 0; 

                //Move states
                stateNext = sCalc; 
            end

            sCalc: begin 
                 
                //CASE STATEMENT WAS CHAT-GPT GENERATED
                //We double checked the AI with resource: https://www.vedantu.com/maths/prime-numbers-from-1-to-1000
                case (i)
                    // List of prime numbers
                    10'd2, 10'd3, 10'd5, 10'd7, 10'd11, 10'd13, 10'd17, 10'd19, 10'd23, 10'd29,
                    10'd31, 10'd37, 10'd41, 10'd43, 10'd47, 10'd53, 10'd59, 10'd61, 10'd67, 10'd71,
                    10'd73, 10'd79, 10'd83, 10'd89, 10'd97, 10'd101, 10'd103, 10'd107, 10'd109, 10'd113,
                    10'd127, 10'd131, 10'd137, 10'd139, 10'd149, 10'd151, 10'd157, 10'd163, 10'd167, 10'd173,
                    10'd179, 10'd181, 10'd191, 10'd193, 10'd197, 10'd199, 10'd211, 10'd223, 10'd227, 10'd229,
                    10'd233, 10'd239, 10'd241, 10'd251, 10'd257, 10'd263, 10'd269, 10'd271, 10'd277, 10'd281,
                    10'd283, 10'd293, 10'd307, 10'd311, 10'd313, 10'd317, 10'd331, 10'd337, 10'd347, 10'd349,
                    10'd353, 10'd359, 10'd367, 10'd373, 10'd379, 10'd383, 10'd389, 10'd397, 10'd401, 10'd409,
                    10'd419, 10'd421, 10'd431, 10'd433, 10'd439, 10'd443, 10'd449, 10'd457, 10'd461, 10'd463,
                    10'd467, 10'd479, 10'd487, 10'd491, 10'd499, 10'd503, 10'd509, 10'd521, 10'd523, 10'd541,
                    10'd547, 10'd557, 10'd563, 10'd569, 10'd571, 10'd577, 10'd587, 10'd593, 10'd599, 10'd601,
                    10'd607, 10'd613, 10'd617, 10'd619, 10'd631, 10'd641, 10'd643, 10'd647, 10'd653, 10'd659,
                    10'd661, 10'd673, 10'd677, 10'd683, 10'd691, 10'd701, 10'd709, 10'd719, 10'd727, 10'd733,
                    10'd739, 10'd743, 10'd751, 10'd757, 10'd761, 10'd769, 10'd773, 10'd787, 10'd797, 10'd809,
                    10'd811, 10'd821, 10'd823, 10'd827, 10'd829, 10'd839, 10'd853, 10'd857, 10'd859, 10'd863,
                    10'd877, 10'd881, 10'd883, 10'd887, 10'd907, 10'd911, 10'd919, 10'd929, 10'd937, 10'd941,
                    10'd947, 10'd953, 10'd967, 10'd971, 10'd977, 10'd983, 10'd991, 10'd997:
                        primeTemp = 1; 
                    //Make sure to always have a default case with case statements
                    default: primeTemp = 0; 
                endcase
               
                stateNext = sSet; 
                

            end

            sSet: begin 
                if (prime == 1) begin 
                    count++; 
                end

                if (i == 1 || i == 2) begin   
                    i++;  
                end 
                else begin 
                    i = i + 2; 
                end

                //Now we do the logic for moving the states
                if (i <= numMax + 1) begin //Its important to make sure that we do equal to so we also check if the number inputted is a prime
                    //Update State
                    stateNext = sCalc;  

                end else begin 
                    stateNext = sDone; 
                end
            end

            sDone: begin 
                stateNext = sOff; 
            end

            default: 
                stateNext = sInit;

        endcase

    end

    //Here we decide the outputs
    always @(state) begin 
        //outputs to determine
        if (state == sSet || stateNext == sSet || state == sCalc || stateNext == sCalc) begin 
            numberChecked = i; 
            numberOfPrimes = count;
            if (i == 2) begin 
                prime = 1; 
            end
            else begin 
                prime = primeTemp;
            end
        end     

        if (state == sDone) begin 
            //Now we just need to update our last things 
            $display("done");
        end



    end
    


endmodule

3_Exercise/tb_primeNumber.v
`include "primeNumber.v"
`timescale 1ns/1ns

module tb_primeNumber(); 

    //Define the inputs as reg
    reg [10:0] numMax;
    reg clk; 
    reg rst;


    //Define the outputs as wires
    wire prime; //Again we only need 10 bits but we'll use 11 just in case
    wire [10:0] numberChecked; 
    wire [10:0] numberOfPrimes; //There is no need for this many bits to be used, if we were to optimize this project, than maybe this number would be smaller

    //Create a reg to prove that it is correct or not. 

    //Initialize primeNumber module
    primeNumber pn(
        .numMax(numMax), 
        .clk(clk), 
        .rst(rst), 

        .prime(prime), 
        .numberChecked(numberChecked), 
        .numberOfPrimes(numberOfPrimes)
    );


    //Start the clock
    always begin
        clk = 1; 
        #10;
        clk = 0;
        #10;
    end

    integer k, primeOrNah;

    always @(numberChecked) begin
        if (numberChecked <= 1) begin
            primeOrNah = 0;  // Not prime
        end 
        else if (numberChecked <= 3) begin
            primeOrNah = 1;  // 2 and 3 are prime
        end 
        else if (numberChecked % 2 == 0) begin
            primeOrNah = 0;  // Even numbers (except 2) are not prime
        end 
        else begin
            primeOrNah = 1;  // Assume prime
            for (k = 3; k * k <= numberChecked; k = k + 2) begin
                if (numberChecked % k == 0) begin
                    primeOrNah = 0;  // Found a divisor, not prime
                end
            end
        end
    end

    integer i, j; 
    //Start the test cases
    initial begin
        $dumpvars(0, tb_primeNumber);

        @(posedge clk)
        rst = 1; 
        @(posedge clk)
        //Singular Test Cases
        numMax = 10; 
        rst = 0; 

        //Now we need to run the clock cycles since this is a flop based design
        for (j = 0; j < numMax + 5; j++) begin 
            @(posedge clk);
        end

        

        $finish;
    end




endmodule

3_Exercise/dump.vcd
$date
	Fri Jan 31 19:54:23 2025
$end
$version
	Icarus Verilog
$end
$timescale
	1ns
$end
$scope module tb_primeNumber $end
$var wire 1 ! prime $end
$var wire 11 " numberOfPrimes [10:0] $end
$var wire 11 # numberChecked [10:0] $end
$var reg 1 $ clk $end
$var reg 11 % numMax [10:0] $end
$var reg 1 & rst $end
$var integer 32 ' j [31:0] $end
$var integer 32 ( k [31:0] $end
$var integer 32 ) primeOrNah [31:0] $end
$scope module pn $end
$var wire 1 $ clk $end
$var wire 11 * numMax [10:0] $end
$var wire 1 & rst $end
$var parameter 32 + sCalc $end
$var parameter 32 , sDone $end
$var parameter 32 - sInit $end
$var parameter 32 . sOff $end
$var parameter 32 / sSet $end
$var reg 11 0 numberChecked [10:0] $end
$var reg 11 1 numberOfPrimes [10:0] $end
$var reg 1 ! prime $end
$var reg 3 2 state [2:0] $end
$var reg 3 3 stateNext [2:0] $end
$var integer 32 4 count [31:0] $end
$var integer 32 5 i [31:0] $end
$var integer 32 6 primeTemp [31:0] $end
$upscope $end
$upscope $end
$enddefinitions $end
$comment Show the parameter values. $end
$dumpall
b11 /
b0 .
b1 -
b100 ,
b10 +
$end
#0
$dumpvars
b0 6
bx 5
bx 4
b1 3
bx 2
bx 1
bx 0
bx *
bx )
bx (
bx '
x&
bx %
1$
bx #
bx "
0!
$end
#10
0$
#20
b0 3
b1 2
1&
1$
#30
0$
#40
b1 3
b0 2
b0 '
0&
b1010 %
b1010 *
1$
#50
0$
#60
b0 )
b0 "
b0 1
b1 #
b1 0
b10 3
b1 5
b0 4
b1 2
b1 '
1$
#70
0$
#80
b11 3
b10 2
b10 '
1$
#90
0$
#100
b1 )
0!
b10 #
b10 0
b10 3
b10 5
b11 2
b11 '
1$
#110
0$
#120
0!
b11 3
b1 6
b10 2
b100 '
1$
#130
0$
#140
1!
b11 #
b11 0
b10 3
b11 5
b11 2
b101 '
1$
#150
0$
#160
b11 3
b10 2
b110 '
1$
#170
0$
#180
b11 (
b1 "
b1 1
b101 #
b101 0
b10 3
b101 5
b1 4
b11 2
b111 '
1$
#190
0$
#200
b11 3
b10 2
b1000 '
1$
#210
0$
#220
b10 "
b10 1
b111 #
b111 0
b10 3
b111 5
b10 4
b11 2
b1001 '
1$
#230
0$
#240
b11 3
b10 2
b1010 '
1$
#250
0$
#260
b101 (
b0 )
b11 "
b11 1
b1001 #
b1001 0
b10 3
b1001 5
b11 4
b11 2
b1011 '
1$
#270
0$
#280
1!
b11 3
b0 6
b10 2
b1100 '
1$
#290
0$
#300
b101 (
b1 )
0!
b100 "
b100 1
b1011 #
b1011 0
b10 3
b1011 5
b100 4
b11 2
b1101 '
1$
#310
0$
#320
0!
b11 3
b1 6
b10 2
b1110 '
1$
#330
0$
#340
b101 (
1!
b1101 #
b1101 0
b100 3
b1101 5
b11 2
b1111 '
1$
