3_Exercise/primeNumber.v

module primeNumber(numMax, clk, rst, prime, numberChecked, numberOfPrimes);
    //Delcare all the inputs here
    input [10:0] numMax; //You only need 10 bits, but we'll use 11 just in case
    input clk; 
    input rst;

    //Declare all outputs here
    output reg [10:0] prime; //Again we only need 10 bits but we'll use 11 just in case
    output reg [10:0] numberChecked; 
    output reg [10:0] numberOfPrimes; //There is no need for this many bits to be used, if we were to optimize this project, than maybe this number would be smaller

    //Declare Wire for prime lookups
    wire primeBool; //This is the value we can input into the module

    integer i;
    integer loopMax;
    integer count;  
    always @(rst != 1) begin
        count = 0; 
        i = 2; 
    end


    //Now we want to create a sort of loop that will loop along with the 
    always @(posedge clk) begin
        if (i < numMax) begin 
             numberChecked = i; 
            //CASE STATEMENT WAS CHAT-GPT GENERATED
            //We double checked the AI with resource: https://www.vedantu.com/maths/prime-numbers-from-1-to-1000
            case (i)
                // List of prime numbers
                10'd2, 10'd3, 10'd5, 10'd7, 10'd11, 10'd13, 10'd17, 10'd19, 10'd23, 10'd29,
                10'd31, 10'd37, 10'd41, 10'd43, 10'd47, 10'd53, 10'd59, 10'd61, 10'd67, 10'd71,
                10'd73, 10'd79, 10'd83, 10'd89, 10'd97, 10'd101, 10'd103, 10'd107, 10'd109, 10'd113,
                10'd127, 10'd131, 10'd137, 10'd139, 10'd149, 10'd151, 10'd157, 10'd163, 10'd167, 10'd173,
                10'd179, 10'd181, 10'd191, 10'd193, 10'd197, 10'd199, 10'd211, 10'd223, 10'd227, 10'd229,
                10'd233, 10'd239, 10'd241, 10'd251, 10'd257, 10'd263, 10'd269, 10'd271, 10'd277, 10'd281,
                10'd283, 10'd293, 10'd307, 10'd311, 10'd313, 10'd317, 10'd331, 10'd337, 10'd347, 10'd349,
                10'd353, 10'd359, 10'd367, 10'd373, 10'd379, 10'd383, 10'd389, 10'd397, 10'd401, 10'd409,
                10'd419, 10'd421, 10'd431, 10'd433, 10'd439, 10'd443, 10'd449, 10'd457, 10'd461, 10'd463,
                10'd467, 10'd479, 10'd487, 10'd491, 10'd499, 10'd503, 10'd509, 10'd521, 10'd523, 10'd541,
                10'd547, 10'd557, 10'd563, 10'd569, 10'd571, 10'd577, 10'd587, 10'd593, 10'd599, 10'd601,
                10'd607, 10'd613, 10'd617, 10'd619, 10'd631, 10'd641, 10'd643, 10'd647, 10'd653, 10'd659,
                10'd661, 10'd673, 10'd677, 10'd683, 10'd691, 10'd701, 10'd709, 10'd719, 10'd727, 10'd733,
                10'd739, 10'd743, 10'd751, 10'd757, 10'd761, 10'd769, 10'd773, 10'd787, 10'd797, 10'd809,
                10'd811, 10'd821, 10'd823, 10'd827, 10'd829, 10'd839, 10'd853, 10'd857, 10'd859, 10'd863,
                10'd877, 10'd881, 10'd883, 10'd887, 10'd907, 10'd911, 10'd919, 10'd929, 10'd937, 10'd941,
                10'd947, 10'd953, 10'd967, 10'd971, 10'd977, 10'd983, 10'd991, 10'd997:
                    prime = 1;
                //Make sure to always have a default case with case statements
                default: prime = 0;
            endcase
            if (prime == 1) begin 
                count++; 
            end

            
        end


        //Finally update the number of primes
        numberOfPrimes = count; 

        //update count
        if (i == 2) begin 
            i ++; 
        end
        else begin 
            i = i + 2; 
        end
    end 


endmodule

3_Exercise/tb_primeNumber.v
`include "primeNumber.v"
`timescale 1ns/1ns

module tb_primeNumber(); 

    //Define the inputs as reg
    reg [10:0] numMax;
    reg clk; 
    reg rst;


    //Define the outputs as wires
    wire [10:0] prime; //Again we only need 10 bits but we'll use 11 just in case
    wire [10:0] numberChecked; 
    wire [10:0] numberOfPrimes; //There is no need for this many bits to be used, if we were to optimize this project, than maybe this number would be smaller


    //Initialize primeNumber module
    primeNumber pn(
        .numMax(numMax), 
        .clk(clk), 
        .rst(rst), 

        .prime(prime), 
        .numberChecked(numberChecked), 
        .numberOfPrimes(numberOfPrimes)
    );


    //Start the clock
    always begin
        clk = 1; 
        #10;
        clk = 0;
        #10;
    end

    integer i, j; 
    //Start the test cases
    initial begin
        $dumpvars(0, tb_primeNumber);
        /*
        for (i = 0; i < 2; i++) begin //This will be the input for numMax
            numMax = i; 
            rst = 0; 

            //Now we need to run the clock cycles since this is a flop based design
            for (j = 0; j < i + 1; j++) begin 
                @(posedge clk);
            end
        end
        */



        //Singular Test Cases
        numMax = 100; 
        rst = 0; 

        //Now we need to run the clock cycles since this is a flop based design
        for (j = 0; j <  numMax+ 1; j++) begin 
            @(posedge clk);
        end

        $finish;
    end




endmodule

3_Exercise/dump.vcd
$date
	Wed Jan 29 15:56:03 2025
$end
$version
	Icarus Verilog
$end
$timescale
	1ns
$end
$scope module tb_primeNumber $end
$var wire 11 ! prime [10:0] $end
$var wire 11 " numberOfPrimes [10:0] $end
$var wire 11 # numberChecked [10:0] $end
$var reg 1 $ clk $end
$var reg 11 % numMax [10:0] $end
$var reg 1 & rst $end
$var integer 32 ' j [31:0] $end
$scope module pn $end
$var wire 1 $ clk $end
$var wire 11 ( numMax [10:0] $end
$var wire 1 & rst $end
$var reg 11 ) numberChecked [10:0] $end
$var reg 11 * numberOfPrimes [10:0] $end
$var reg 11 + prime [10:0] $end
$var integer 32 , count [31:0] $end
$var integer 32 - i [31:0] $end
$upscope $end
$upscope $end
$enddefinitions $end
$comment Show the parameter values. $end
$dumpall
$end
#0
$dumpvars
b10 -
b0 ,
bx +
bx *
bx )
b1100100 (
b0 '
0&
b1100100 %
1$
bx #
bx "
bx !
$end
#10
0$
#20
b1 '
b11 -
b1 "
b1 *
b1 ,
b1 !
b1 +
b10 #
b10 )
1$
#30
0$
#40
b101 -
b10 "
b10 *
b10 ,
b11 #
b11 )
b10 '
1$
#50
0$
#60
b11 '
b111 -
b11 "
b11 *
b11 ,
b101 #
b101 )
1$
#70
0$
#80
b1001 -
b100 "
b100 *
b100 ,
b111 #
b111 )
b100 '
1$
#90
0$
#100
b101 '
b1011 -
b0 !
b0 +
b1001 #
b1001 )
1$
#110
0$
#120
b1101 -
b101 "
b101 *
b101 ,
b1 !
b1 +
b1011 #
b1011 )
b110 '
1$
#130
0$
#140
b111 '
b1111 -
b110 "
b110 *
b110 ,
b1101 #
b1101 )
1$
#150
0$
#160
b10001 -
b0 !
b0 +
b1111 #
b1111 )
b1000 '
1$
#170
0$
#180
b1001 '
b10011 -
b111 "
b111 *
b111 ,
b1 !
b1 +
b10001 #
b10001 )
1$
#190
0$
#200
b10101 -
b1000 "
b1000 *
b1000 ,
b10011 #
b10011 )
b1010 '
1$
#210
0$
#220
b1011 '
b10111 -
b0 !
b0 +
b10101 #
b10101 )
1$
#230
0$
#240
b11001 -
b1001 "
b1001 *
b1001 ,
b1 !
b1 +
b10111 #
b10111 )
b1100 '
1$
#250
0$
#260
b1101 '
b11011 -
b0 !
b0 +
b11001 #
b11001 )
1$
#270
0$
#280
b11101 -
b11011 #
b11011 )
b1110 '
1$
#290
0$
#300
b1111 '
b11111 -
b1010 "
b1010 *
b1010 ,
b1 !
b1 +
b11101 #
b11101 )
1$
#310
0$
#320
b100001 -
b1011 "
b1011 *
b1011 ,
b11111 #
b11111 )
b10000 '
1$
#330
0$
#340
b10001 '
b100011 -
b0 !
b0 +
b100001 #
b100001 )
1$
#350
0$
#360
b100101 -
b100011 #
b100011 )
b10010 '
1$
#370
0$
#380
b10011 '
b100111 -
b1100 "
b1100 *
b1100 ,
b1 !
b1 +
b100101 #
b100101 )
1$
#390
0$
#400
b101001 -
b0 !
b0 +
b100111 #
b100111 )
b10100 '
1$
#410
0$
#420
b10101 '
b101011 -
b1101 "
b1101 *
b1101 ,
b1 !
b1 +
b101001 #
b101001 )
1$
#430
0$
#440
b101101 -
b1110 "
b1110 *
b1110 ,
b101011 #
b101011 )
b10110 '
1$
#450
0$
#460
b10111 '
b101111 -
b0 !
b0 +
b101101 #
b101101 )
1$
#470
0$
#480
b110001 -
b1111 "
b1111 *
b1111 ,
b1 !
b1 +
b101111 #
b101111 )
b11000 '
1$
#490
0$
#500
b11001 '
b110011 -
b0 !
b0 +
b110001 #
b110001 )
1$
#510
0$
#520
b110101 -
b110011 #
b110011 )
b11010 '
1$
#530
0$
#540
b11011 '
b110111 -
b10000 "
b10000 *
b10000 ,
b1 !
b1 +
b110101 #
b110101 )
1$
#550
0$
#560
b111001 -
b0 !
b0 +
b110111 #
b110111 )
b11100 '
1$
#570
0$
#580
b11101 '
b111011 -
b111001 #
b111001 )
1$
#590
0$
#600
b111101 -
b10001 "
b10001 *
b10001 ,
b1 !
b1 +
b111011 #
b111011 )
b11110 '
1$
#610
0$
#620
b11111 '
b111111 -
b10010 "
b10010 *
b10010 ,
b111101 #
b111101 )
1$
#630
0$
#640
b1000001 -
b0 !
b0 +
b111111 #
b111111 )
b100000 '
1$
#650
0$
#660
b100001 '
b1000011 -
b1000001 #
b1000001 )
1$
#670
0$
#680
b1000101 -
b10011 "
b10011 *
b10011 ,
b1 !
b1 +
b1000011 #
b1000011 )
b100010 '
1$
#690
0$
#700
b100011 '
b1000111 -
b0 !
b0 +
b1000101 #
b1000101 )
1$
#710
0$
#720
b1001001 -
b10100 "
b10100 *
b10100 ,
b1 !
b1 +
b1000111 #
b1000111 )
b100100 '
1$
#730
0$
#740
b100101 '
b1001011 -
b10101 "
b10101 *
b10101 ,
b1001001 #
b1001001 )
1$
#750
0$
#760
b1001101 -
b0 !
b0 +
b1001011 #
b1001011 )
b100110 '
1$
#770
0$
#780
b100111 '
b1001111 -
b1001101 #
b1001101 )
1$
#790
0$
#800
b1010001 -
b10110 "
b10110 *
b10110 ,
b1 !
b1 +
b1001111 #
b1001111 )
b101000 '
1$
#810
0$
#820
b101001 '
b1010011 -
b0 !
b0 +
b1010001 #
b1010001 )
1$
#830
0$
#840
b1010101 -
b10111 "
b10111 *
b10111 ,
b1 !
b1 +
b1010011 #
b1010011 )
b101010 '
1$
#850
0$
#860
b101011 '
b1010111 -
b0 !
b0 +
b1010101 #
b1010101 )
1$
#870
0$
#880
b1011001 -
b1010111 #
b1010111 )
b101100 '
1$
#890
0$
#900
b101101 '
b1011011 -
b11000 "
b11000 *
b11000 ,
b1 !
b1 +
b1011001 #
b1011001 )
1$
#910
0$
#920
b1011101 -
b0 !
b0 +
b1011011 #
b1011011 )
b101110 '
1$
#930
0$
#940
b101111 '
b1011111 -
b1011101 #
b1011101 )
1$
#950
0$
#960
b1100001 -
b1011111 #
b1011111 )
b110000 '
1$
#970
0$
#980
b110001 '
b1100011 -
b11001 "
b11001 *
b11001 ,
b1 !
b1 +
b1100001 #
b1100001 )
1$
#990
0$
#1000
b1100101 -
b0 !
b0 +
b1100011 #
b1100011 )
b110010 '
1$
#1010
0$
#1020
b110011 '
b1100111 -
1$
#1030
0$
#1040
b1101001 -
b110100 '
1$
#1050
0$
#1060
b110101 '
b1101011 -
1$
#1070
0$
#1080
b1101101 -
b110110 '
1$
#1090
0$
#1100
b110111 '
b1101111 -
1$
#1110
0$
#1120
b1110001 -
b111000 '
1$
#1130
0$
#1140
b111001 '
b1110011 -
1$
#1150
0$
#1160
b1110101 -
b111010 '
1$
#1170
0$
#1180
b111011 '
b1110111 -
1$
#1190
0$
#1200
b1111001 -
b111100 '
1$
#1210
0$
#1220
b111101 '
b1111011 -
1$
#1230
0$
#1240
b1111101 -
b111110 '
1$
#1250
0$
#1260
b111111 '
b1111111 -
1$
#1270
0$
#1280
b10000001 -
b1000000 '
1$
#1290
0$
#1300
b1000001 '
b10000011 -
1$
#1310
0$
#1320
b10000101 -
b1000010 '
1$
#1330
0$
#1340
b1000011 '
b10000111 -
1$
#1350
0$
#1360
b10001001 -
b1000100 '
1$
#1370
0$
#1380
b1000101 '
b10001011 -
1$
#1390
0$
#1400
b10001101 -
b1000110 '
1$
#1410
0$
#1420
b1000111 '
b10001111 -
1$
#1430
0$
#1440
b10010001 -
b1001000 '
1$
#1450
0$
#1460
b1001001 '
b10010011 -
1$
#1470
0$
#1480
b10010101 -
b1001010 '
1$
#1490
0$
#1500
b1001011 '
b10010111 -
1$
#1510
0$
#1520
b10011001 -
b1001100 '
1$
#1530
0$
#1540
b1001101 '
b10011011 -
1$
#1550
0$
#1560
b10011101 -
b1001110 '
1$
#1570
0$
#1580
b1001111 '
b10011111 -
1$
#1590
0$
#1600
b10100001 -
b1010000 '
1$
#1610
0$
#1620
b1010001 '
b10100011 -
1$
#1630
0$
#1640
b10100101 -
b1010010 '
1$
#1650
0$
#1660
b1010011 '
b10100111 -
1$
#1670
0$
#1680
b10101001 -
b1010100 '
1$
#1690
0$
#1700
b1010101 '
b10101011 -
1$
#1710
0$
#1720
b10101101 -
b1010110 '
1$
#1730
0$
#1740
b1010111 '
b10101111 -
1$
#1750
0$
#1760
b10110001 -
b1011000 '
1$
#1770
0$
#1780
b1011001 '
b10110011 -
1$
#1790
0$
#1800
b10110101 -
b1011010 '
1$
#1810
0$
#1820
b1011011 '
b10110111 -
1$
#1830
0$
#1840
b10111001 -
b1011100 '
1$
#1850
0$
#1860
b1011101 '
b10111011 -
1$
#1870
0$
#1880
b10111101 -
b1011110 '
1$
#1890
0$
#1900
b1011111 '
b10111111 -
1$
#1910
0$
#1920
b11000001 -
b1100000 '
1$
#1930
0$
#1940
b1100001 '
b11000011 -
1$
#1950
0$
#1960
b11000101 -
b1100010 '
1$
#1970
0$
#1980
b1100011 '
b11000111 -
1$
#1990
0$
#2000
b11001001 -
b1100100 '
1$
#2010
0$
#2020
b1100101 '
b11001011 -
1$
