5_Exercise/pwm.v

module pwm (clk, rst, period, dutyCycle, modeBurst, typeBurst, pwmOut, outRST);

    //Define the inputs here - remeber inputs don't need reg key word but outputs do
    input clk; 
    input rst;
    input [15:0] period;
    input [7:0] dutyCycle;
    input typeBurst; 
    input modeBurst;

    //define outputs here
    output reg pwmOut; 
    output reg outRST; 

    //define states here
    parameter sIdle = 0, sInit = 1, sOn = 2, sOff = 3, sOnBurst = 4, sOffBurst = 5;

    //States
    reg [2:0] state, stateNext; 

    //Extranous variables
    reg [32:0] onTime;
    reg [32:0] offTime; 

    //burst variables
    reg [32:0] burst_onTime, burst_offTime;  
    reg [32:0] burstDiv; 
    reg [32:0] burstCounter; 
    reg [32:0] tickTime;
    
         
    

    /* Moore Machines consist of 3 always blocks 
        - The first is to drive the states
        - The second is to drive the logic
        - The thrid is to drive the outputs
    */

    //always block to drive the states
    always @(posedge clk) begin
        state <= stateNext; 
    end


    //always block to drive the logic
    always @(posedge clk) begin 
        if (rst == 1) begin 
            state = sIdle; 
        end else begin 
            state = stateNext; 
        end
        case (state)

            sIdle: begin 
                //Drive outputs: 
                outRST = rst; 
                pwmOut = 0; 

                //sIdle needs to only go to sInit, when rst = 0, else stay on sIdle
                if (rst == 0) begin 
                    stateNext = sInit;
                end else begin 
                    stateNext = sIdle; 
                end
            end

            sInit: begin 
                //Drive outputs: 
                outRST = rst; 
                pwmOut = 0; 

                //sInit should always move to sOn unless rst goes back on
                if (rst == 1) begin
                    //go back to sIdle
                    stateNext = sIdle; 
                end else begin 
                    if (typeBurst == 1) begin 
                        burstDiv = 32; 
                        burstCounter = 16; 
                    end else begin 
                        burstDiv = 16; 
                        burstCounter = 8; 
                    end

                    if (modeBurst) begin 
                        stateNext = sOnBurst; 
                    end else begin 
                        stateNext = sOn; 
                    end

                    tickTime = 1000000000/period;
                    tickTime = 1000000000/tickTime;
                    //Lets also calcuate on and off times so we don't have to worry about that 
                    onTime = (tickTime * dutyCycle)/100; 
                    offTime = (tickTime*(100 - dutyCycle))/100; 

                    burst_onTime = onTime/burstDiv; 
                    burst_offTime = onTime/burstDiv; 
                    
                end
            end

            sOn: begin

                if (dutyCycle == 0) begin
                    pwmOut = 0;
                end else begin 
                    //Drive output
                    pwmOut = 1;
                    outRST = rst; 
                end



                /* There are 3 options for movement within this stage
                    - sOn has not finished its duty cycle so it goes back to sOn
                    - sOn has finsihed its duty cycle so it moves to sOff
                    - rst is turned on and the system needs to go back to the idle state
                */

                if (rst == 1) begin 
                    //set idle back on 
                    stateNext = sIdle; 
                end else if (onTime != 0) begin 
                    onTime = onTime - 1; 
                    stateNext = sOn;   
                end else begin 
                    stateNext = sOff; 
                    onTime = (tickTime * dutyCycle)/100; 
                end
            end

            sOff: begin
                //Drive output
                pwmOut = 0;
                outRST = rst; 

                /* There are 3 options for movement within this stage
                    - sOff has not finished its duty cycle so it goes back to sOf
                    - sOff has finsihed its duty cycle so it moves to sOn or sOnBurst
                    - rst is turned on and the system needs to go back to the idle state
                */
                if (rst == 1) begin 
                    //set idle back on 
                    stateNext = sIdle; 
                end else if (offTime != 0) begin 
                    offTime = offTime - 1; 
                    stateNext = sOff; 
                end else begin 
                    if (modeBurst) begin 
                        stateNext = sOnBurst; 
                    end else begin
                        stateNext = sOn; 
                    end  
                    offTime = (tickTime * (100 - dutyCycle))/100; 
                end
            end

            sOnBurst: begin
                //Drive output
                pwmOut = 0;
                outRST = rst; 

                if (rst == 1) begin 
                    stateNext = sIdle;
                end else if (burstCounter > 0) begin //we need to decide wheater we need to go to sOff or sBurstOff or stay on burstOn
                    //Now we look at either sburston or sburstoff
                    if (burst_onTime > 0) begin 
                        burst_onTime =burst_onTime - 1; 
                        stateNext = sOnBurst; 
                    end else begin 
                        //This means that it is time to go to burstOff 
                        burstCounter = burstCounter - 1; 
                        burst_onTime = ((tickTime * dutyCycle)/100)/burstDiv;
                        stateNext = sOffBurst;
                    end
                end else begin //this means that the burst counter is at 0
                    //Drive the state to sOff
                    stateNext = sOff; 

                    //Drive output
                    if (typeBurst == 1) begin 
                        burstCounter = 16; 
                    end else begin 
                        burstCounter = 8; 
                    end
                end
            end

            sOffBurst: begin
                //Drive output
                pwmOut = 1;


                /* There are 2 cases in which this state can move to
                    - It can go to offBurst while count is less than 8 or 16 depending on burst type
                    - or it can go to idle if reset is activated
                */

                if (rst == 1) begin 
                    stateNext = sIdle; 
                end else if (burst_offTime > 0) begin 
                    burst_offTime = burst_offTime - 1;
                    stateNext = sOffBurst; 
                end else begin //This is when burstOff time is done
                    burst_offTime = ((tickTime * dutyCycle)/100)/burstDiv;
                    stateNext = sOnBurst;
                end
            end

            default: //NEVER FORGET THE DEFAULT CASE STATEMENT!!!
                stateNext = sInit; 
            


        endcase

    end



endmodule

5_Exercise/led.v
`include "pwm.v"
module led(switchPanel, rLED, gLED, bLED, clk, rst);

    //define the inputs here
    input [15:0] switchPanel; 
    input clk;
    input rst; 

    //Assign outputs here
    output reg rLED, gLED, bLED;

    //Assign input wires here
    wire [4:0] rIn;
    assign rIn = switchPanel[15:11];
    reg [7:0] rDutyCycle;

    wire [5:0] bIn; 
    assign bIn = switchPanel[10:5];
    reg [7:0] bDutyCycle;

    wire [4:0] gIn; 
    assign gIn = switchPanel[4:0];
    reg [7:0] gDutyCycle;


    //Define case statements
    parameter sIdle = 0, sOn = 1; 
    reg state, stateNext; 
    
    wire rpwm, gpwm, bpwm; 



    //Now create pwm modules and assign the numbers to them

    pwm rLight(
        .clk(clk), 
        .rst(rst), 
        .period(10), 
        .dutyCycle(rDutyCycle),
        .typeBurst(0), 
        .modeBurst(0), 
        .pwmOut(rpwm)
    );

    pwm gLight(
        .clk(clk), 
        .rst(rst), 
        .period(10), 
        .dutyCycle(gDutyCycle),
        .typeBurst(0), 
        .modeBurst(0),
        .pwmOut(gpwm)
    );

    pwm bLight(
        .clk(clk), 
        .rst(rst), 
        .period(10), 
        .dutyCycle(bDutyCycle),
        .typeBurst(0), 
        .modeBurst(0),
        .pwmOut(bpwm)
    );

    //Drive the state
    always @(posedge clk) begin 
        state <= stateNext; 
    end

    always @(posedge clk) begin 

        if (rst == 1) begin 
            stateNext = sIdle;
        end

        case(state)

            sIdle: begin 
                //Drive outputs
                rDutyCycle = 0; 
                gDutyCycle = 0; 
                bDutyCycle = 0;

                bLED = 0;
                gLED = 0;
                rLED = 0;
                //We have 2 options when considering this state
                //Either stay in sIdle or go to sOn

                if (rst == 1) begin 
                    stateNext = sIdle; 
                end else begin 
                    stateNext = sOn;
                end
            end

            sOn: begin 
                //We need to check if we need to go back to sIdle
                if (rst == 1) begin 
                    stateNext = sIdle; 
                end else begin 
                    stateNext = sOn;
                end


            
                //Drive the outputs
                bLED = bpwm;
                gLED = gpwm;
                rLED = rpwm;

                rDutyCycle = (rIn*100) >> 5; 
                gDutyCycle = (gIn*100) >> 5;
                bDutyCycle = (bIn*100) >> 6;

            end
            
            default: 
                stateNext = sIdle; 
            
        endcase

    end
endmodule

5_Exercise/tb_led.v
`timescale 1ns / 1ns
`include "led.v"
module tb_led();
    // Testbench signals
    reg [15:0] switchPanel;
    reg clk;
    reg rst;
    wire rLED, gLED, bLED;

    // Instantiate the LED module
    led uut (
        .switchPanel(switchPanel),
        .rLED(rLED),
        .gLED(gLED),
        .bLED(bLED),
        .clk(clk),
        .rst(rst)
    );

    // Clock generation
    always #5 clk = ~clk; // 10ns period (100MHz clock)

    // Test procedure
    initial begin
        $dumpvars(0, tb_led);
        // Initialize signals
        clk = 0;
        rst = 0;
        switchPanel = 16'b1111100000000000;

        
        #2000
        /*
        rst = 0;
        
        // Test different switchPanel values
        #20 switchPanel = 16'b1111100000000000; // High red intensity
        #40 switchPanel = 16'b0000011111100000; // High green intensity
        #40 switchPanel = 16'b0000000000011111; // High blue intensity
        #40 switchPanel = 16'b0111101111011110; // Mixed colors
        
        // Apply reset again
        #20 rst = 1;
        #20 rst = 0;

        // End simulation
        #100 */
        $finish;
    end

endmodule

5_Exercise/dump.vcd
$date
	Thu Feb 13 12:31:01 2025
$end
$version
	Icarus Verilog
$end
$timescale
	1ns
$end
$scope module tb_led $end
$var wire 1 ! rLED $end
$var wire 1 " gLED $end
$var wire 1 # bLED $end
$var reg 1 $ clk $end
$var reg 1 % rst $end
$var reg 16 & switchPanel [15:0] $end
$scope module uut $end
$var wire 1 $ clk $end
$var wire 1 % rst $end
$var wire 16 ' switchPanel [15:0] $end
$var wire 1 ( rpwm $end
$var wire 5 ) rIn [4:0] $end
$var wire 1 * gpwm $end
$var wire 5 + gIn [4:0] $end
$var wire 1 , bpwm $end
$var wire 6 - bIn [5:0] $end
$var parameter 32 . sIdle $end
$var parameter 32 / sOn $end
$var reg 8 0 bDutyCycle [7:0] $end
$var reg 1 # bLED $end
$var reg 8 1 gDutyCycle [7:0] $end
$var reg 1 " gLED $end
$var reg 8 2 rDutyCycle [7:0] $end
$var reg 1 ! rLED $end
$var reg 1 3 state $end
$var reg 1 4 stateNext $end
$scope module bLight $end
$var wire 1 $ clk $end
$var wire 8 5 dutyCycle [7:0] $end
$var wire 1 6 modeBurst $end
$var wire 16 7 period [15:0] $end
$var wire 1 % rst $end
$var wire 1 8 typeBurst $end
$var parameter 32 9 sIdle $end
$var parameter 32 : sInit $end
$var parameter 32 ; sOff $end
$var parameter 32 < sOffBurst $end
$var parameter 32 = sOn $end
$var parameter 32 > sOnBurst $end
$var reg 33 ? burstCounter [32:0] $end
$var reg 33 @ burstDiv [32:0] $end
$var reg 33 A burst_offTime [32:0] $end
$var reg 33 B burst_onTime [32:0] $end
$var reg 33 C offTime [32:0] $end
$var reg 33 D onTime [32:0] $end
$var reg 1 E outRST $end
$var reg 1 , pwmOut $end
$var reg 3 F state [2:0] $end
$var reg 3 G stateNext [2:0] $end
$var reg 33 H tickTime [32:0] $end
$upscope $end
$scope module gLight $end
$var wire 1 $ clk $end
$var wire 8 I dutyCycle [7:0] $end
$var wire 1 J modeBurst $end
$var wire 16 K period [15:0] $end
$var wire 1 % rst $end
$var wire 1 L typeBurst $end
$var parameter 32 M sIdle $end
$var parameter 32 N sInit $end
$var parameter 32 O sOff $end
$var parameter 32 P sOffBurst $end
$var parameter 32 Q sOn $end
$var parameter 32 R sOnBurst $end
$var reg 33 S burstCounter [32:0] $end
$var reg 33 T burstDiv [32:0] $end
$var reg 33 U burst_offTime [32:0] $end
$var reg 33 V burst_onTime [32:0] $end
$var reg 33 W offTime [32:0] $end
$var reg 33 X onTime [32:0] $end
$var reg 1 Y outRST $end
$var reg 1 * pwmOut $end
$var reg 3 Z state [2:0] $end
$var reg 3 [ stateNext [2:0] $end
$var reg 33 \ tickTime [32:0] $end
$upscope $end
$scope module rLight $end
$var wire 1 $ clk $end
$var wire 8 ] dutyCycle [7:0] $end
$var wire 1 ^ modeBurst $end
$var wire 16 _ period [15:0] $end
$var wire 1 % rst $end
$var wire 1 ` typeBurst $end
$var parameter 32 a sIdle $end
$var parameter 32 b sInit $end
$var parameter 32 c sOff $end
$var parameter 32 d sOffBurst $end
$var parameter 32 e sOn $end
$var parameter 32 f sOnBurst $end
$var reg 33 g burstCounter [32:0] $end
$var reg 33 h burstDiv [32:0] $end
$var reg 33 i burst_offTime [32:0] $end
$var reg 33 j burst_onTime [32:0] $end
$var reg 33 k offTime [32:0] $end
$var reg 33 l onTime [32:0] $end
$var reg 1 m outRST $end
$var reg 1 ( pwmOut $end
$var reg 3 n state [2:0] $end
$var reg 3 o stateNext [2:0] $end
$var reg 33 p tickTime [32:0] $end
$upscope $end
$upscope $end
$upscope $end
$enddefinitions $end
$comment Show the parameter values. $end
$dumpall
b100 f
b10 e
b101 d
b11 c
b1 b
b0 a
b100 R
b10 Q
b101 P
b11 O
b1 N
b0 M
b100 >
b10 =
b101 <
b11 ;
b1 :
b0 9
b1 /
b0 .
$end
#0
$dumpvars
bx p
bx o
bx n
xm
bx l
bx k
bx j
bx i
bx h
bx g
0`
b1010 _
0^
bx ]
bx \
bx [
bx Z
xY
bx X
bx W
bx V
bx U
bx T
bx S
0L
b1010 K
0J
bx I
bx H
bx G
bx F
xE
bx D
bx C
bx B
bx A
bx @
bx ?
08
b1010 7
06
bx 5
x4
x3
bx 2
bx 1
bx 0
b0 -
x,
b0 +
x*
b11111 )
x(
b1111100000000000 '
b1111100000000000 &
0%
0$
x#
x"
x!
$end
#5
b1 n
b1 Z
b1 F
03
b1 o
b1 [
b1 G
04
1$
#10
0$
#15
14
0!
0"
0#
b0 0
b0 5
b0 1
b0 I
b0 2
b0 ]
b1010 H
b10 G
b1000 ?
b10000 @
0,
0E
b1010 \
b10 [
b1000 S
b10000 T
0*
0Y
b1010 p
b10 o
b1000 g
b10000 h
0(
0m
1$
#20
0$
#25
13
b0 l
b11 o
b11 n
b0 X
b11 [
b11 Z
b0 D
b11 G
b11 F
1$
#30
0$
#35
b1100000 2
b1100000 ]
b1010 C
b10 G
b1010 W
b10 [
b1010 k
b10 o
1$
#40
0$
#45
b1001 l
b11 o
1(
b11 n
b11 [
b11 Z
b11 G
b11 F
1$
#50
0$
#55
b1001 C
b1001 W
b1001 k
0(
1$
#60
0$
#65
b1000 k
b1000 W
b1000 C
1$
#70
0$
#75
b111 C
b111 W
b111 k
1$
#80
0$
#85
b110 k
b110 W
b110 C
1$
#90
0$
#95
b101 C
b101 W
b101 k
1$
#100
0$
#105
b100 k
b100 W
b100 C
1$
#110
0$
#115
b11 C
b11 W
b11 k
1$
#120
0$
#125
b10 k
b10 W
b10 C
1$
#130
0$
#135
b1 C
b1 W
b1 k
1$
#140
0$
#145
b0 k
b0 W
b0 C
1$
#150
0$
#155
b1010 C
b10 G
b1010 W
b10 [
b10 o
1$
#160
0$
#165
b1000 l
1(
b10 n
b11 [
b11 Z
b11 G
b11 F
1$
#170
0$
#175
1!
b1001 C
b1001 W
b111 l
1$
#180
0$
#185
b110 l
b1000 W
b1000 C
1$
#190
0$
#195
b111 C
b111 W
b101 l
1$
#200
0$
#205
b100 l
b110 W
b110 C
1$
#210
0$
#215
b101 C
b101 W
b11 l
1$
#220
0$
#225
b10 l
b100 W
b100 C
1$
#230
0$
#235
b11 C
b11 W
b1 l
1$
#240
0$
#245
b0 l
b10 W
b10 C
1$
#250
0$
#255
b1 C
b1 W
b1001 l
b11 o
1$
#260
0$
#265
b10 o
0(
b10 n
b0 W
b0 C
1$
#270
0$
#275
b1010 C
b10 G
b1010 W
b10 [
b1000 l
1(
1$
#280
0$
#285
b111 l
b11 [
b11 Z
b11 G
b11 F
1$
#290
0$
#295
b1001 C
b1001 W
b110 l
1$
#300
0$
#305
b101 l
b1000 W
b1000 C
1$
#310
0$
#315
b111 C
b111 W
b100 l
1$
#320
0$
#325
b11 l
b110 W
b110 C
1$
#330
0$
#335
b101 C
b101 W
b10 l
1$
#340
0$
#345
b1 l
b100 W
b100 C
1$
#350
0$
#355
b11 C
b11 W
b0 l
1$
#360
0$
#365
b11 n
b1001 l
b11 o
b10 W
b10 C
1$
#370
0$
#375
0!
b1 C
b1 W
b10 o
0(
1$
#380
0$
#385
b1000 l
1(
b10 n
b0 W
b0 C
1$
#390
0$
#395
1!
b1010 C
b10 G
b1010 W
b10 [
b111 l
1$
#400
0$
#405
b110 l
b11 [
b11 Z
b11 G
b11 F
1$
#410
0$
#415
b1001 C
b1001 W
b101 l
1$
#420
0$
#425
b100 l
b1000 W
b1000 C
1$
#430
0$
#435
b111 C
b111 W
b11 l
1$
#440
0$
#445
b10 l
b110 W
b110 C
1$
#450
0$
#455
b101 C
b101 W
b1 l
1$
#460
0$
#465
b0 l
b100 W
b100 C
1$
#470
0$
#475
b11 C
b11 W
b1001 l
b11 o
1$
#480
0$
#485
b10 o
0(
b10 n
b10 W
b10 C
1$
#490
0$
#495
b1 C
b1 W
b1000 l
1(
1$
#500
0$
#505
b111 l
b0 W
b0 C
1$
#510
0$
#515
b1010 C
b10 G
b1010 W
b10 [
b110 l
1$
#520
0$
#525
b101 l
b11 [
b11 Z
b11 G
b11 F
1$
#530
0$
#535
b1001 C
b1001 W
b100 l
1$
#540
0$
#545
b11 l
b1000 W
b1000 C
1$
#550
0$
#555
b111 C
b111 W
b10 l
1$
#560
0$
#565
b1 l
b110 W
b110 C
1$
#570
0$
#575
b101 C
b101 W
b0 l
1$
#580
0$
#585
b11 n
b1001 l
b11 o
b100 W
b100 C
1$
#590
0$
#595
0!
b11 C
b11 W
b10 o
0(
1$
#600
0$
#605
b1000 l
1(
b10 n
b10 W
b10 C
1$
#610
0$
#615
1!
b1 C
b1 W
b111 l
1$
#620
0$
#625
b110 l
b0 W
b0 C
1$
#630
0$
#635
b1010 C
b10 G
b1010 W
b10 [
b101 l
1$
#640
0$
#645
b100 l
b11 [
b11 Z
b11 G
b11 F
1$
#650
0$
#655
b1001 C
b1001 W
b11 l
1$
#660
0$
#665
b10 l
b1000 W
b1000 C
1$
#670
0$
#675
b111 C
b111 W
b1 l
1$
#680
0$
#685
b0 l
b110 W
b110 C
1$
#690
0$
#695
b101 C
b101 W
b1001 l
b11 o
1$
#700
0$
#705
b10 o
0(
b10 n
b100 W
b100 C
1$
#710
0$
#715
b11 C
b11 W
b1000 l
1(
1$
#720
0$
#725
b111 l
b10 W
b10 C
1$
#730
0$
#735
b1 C
b1 W
b110 l
1$
#740
0$
#745
b101 l
b0 W
b0 C
1$
#750
0$
#755
b1010 C
b10 G
b1010 W
b10 [
b100 l
1$
#760
0$
#765
b11 l
b11 [
b11 Z
b11 G
b11 F
1$
#770
0$
#775
b1001 C
b1001 W
b10 l
1$
#780
0$
#785
b1 l
b1000 W
b1000 C
1$
#790
0$
#795
b111 C
b111 W
b0 l
1$
#800
0$
#805
b11 n
b1001 l
b11 o
b110 W
b110 C
1$
#810
0$
#815
0!
b101 C
b101 W
b10 o
0(
1$
#820
0$
#825
b1000 l
1(
b10 n
b100 W
b100 C
1$
#830
0$
#835
1!
b11 C
b11 W
b111 l
1$
#840
0$
#845
b110 l
b10 W
b10 C
1$
#850
0$
#855
b1 C
b1 W
b101 l
1$
#860
0$
#865
b100 l
b0 W
b0 C
1$
#870
0$
#875
b1010 C
b10 G
b1010 W
b10 [
b11 l
1$
#880
0$
#885
b10 l
b11 [
b11 Z
b11 G
b11 F
1$
#890
0$
#895
b1001 C
b1001 W
b1 l
1$
#900
0$
#905
b0 l
b1000 W
b1000 C
1$
#910
0$
#915
b111 C
b111 W
b1001 l
b11 o
1$
#920
0$
#925
b10 o
0(
b10 n
b110 W
b110 C
1$
#930
0$
#935
b101 C
b101 W
b1000 l
1(
1$
#940
0$
#945
b111 l
b100 W
b100 C
1$
#950
0$
#955
b11 C
b11 W
b110 l
1$
#960
0$
#965
b101 l
b10 W
b10 C
1$
#970
0$
#975
b1 C
b1 W
b100 l
1$
#980
0$
#985
b11 l
b0 W
b0 C
1$
#990
0$
#995
b1010 C
b10 G
b1010 W
b10 [
b10 l
1$
#1000
0$
#1005
b1 l
b11 [
b11 Z
b11 G
b11 F
1$
#1010
0$
#1015
b1001 C
b1001 W
b0 l
1$
#1020
0$
#1025
b11 n
b1001 l
b11 o
b1000 W
b1000 C
1$
#1030
0$
#1035
0!
b111 C
b111 W
b10 o
0(
1$
#1040
0$
#1045
b1000 l
1(
b10 n
b110 W
b110 C
1$
#1050
0$
#1055
1!
b101 C
b101 W
b111 l
1$
#1060
0$
#1065
b110 l
b100 W
b100 C
1$
#1070
0$
#1075
b11 C
b11 W
b101 l
1$
#1080
0$
#1085
b100 l
b10 W
b10 C
1$
#1090
0$
#1095
b1 C
b1 W
b11 l
1$
#1100
0$
#1105
b10 l
b0 W
b0 C
1$
#1110
0$
#1115
b1010 C
b10 G
b1010 W
b10 [
b1 l
1$
#1120
0$
#1125
b0 l
b11 [
b11 Z
b11 G
b11 F
1$
#1130
0$
#1135
b1001 C
b1001 W
b1001 l
b11 o
1$
#1140
0$
#1145
b10 o
0(
b10 n
b1000 W
b1000 C
1$
#1150
0$
#1155
b111 C
b111 W
b1000 l
1(
1$
#1160
0$
#1165
b111 l
b110 W
b110 C
1$
#1170
0$
#1175
b101 C
b101 W
b110 l
1$
#1180
0$
#1185
b101 l
b100 W
b100 C
1$
#1190
0$
#1195
b11 C
b11 W
b100 l
1$
#1200
0$
#1205
b11 l
b10 W
b10 C
1$
#1210
0$
#1215
b1 C
b1 W
b10 l
1$
#1220
0$
#1225
b1 l
b0 W
b0 C
1$
#1230
0$
#1235
b1010 C
b10 G
b1010 W
b10 [
b0 l
1$
#1240
0$
#1245
b11 n
b1001 l
b11 o
b11 [
b11 Z
b11 G
b11 F
1$
#1250
0$
#1255
0!
b1001 C
b1001 W
b10 o
0(
1$
#1260
0$
#1265
b1000 l
1(
b10 n
b1000 W
b1000 C
1$
#1270
0$
#1275
1!
b111 C
b111 W
b111 l
1$
#1280
0$
#1285
b110 l
b110 W
b110 C
1$
#1290
0$
#1295
b101 C
b101 W
b101 l
1$
#1300
0$
#1305
b100 l
b100 W
b100 C
1$
#1310
0$
#1315
b11 C
b11 W
b11 l
1$
#1320
0$
#1325
b10 l
b10 W
b10 C
1$
#1330
0$
#1335
b1 C
b1 W
b1 l
1$
#1340
0$
#1345
b0 l
b0 W
b0 C
1$
#1350
0$
#1355
b1010 C
b10 G
b1010 W
b10 [
b1001 l
b11 o
1$
#1360
0$
#1365
b10 o
0(
b10 n
b11 [
b11 Z
b11 G
b11 F
1$
#1370
0$
#1375
b1001 C
b1001 W
b1000 l
1(
1$
#1380
0$
#1385
b111 l
b1000 W
b1000 C
1$
#1390
0$
#1395
b111 C
b111 W
b110 l
1$
#1400
0$
#1405
b101 l
b110 W
b110 C
1$
#1410
0$
#1415
b101 C
b101 W
b100 l
1$
#1420
0$
#1425
b11 l
b100 W
b100 C
1$
#1430
0$
#1435
b11 C
b11 W
b10 l
1$
#1440
0$
#1445
b1 l
b10 W
b10 C
1$
#1450
0$
#1455
b1 C
b1 W
b0 l
1$
#1460
0$
#1465
b11 n
b1001 l
b11 o
b0 W
b0 C
1$
#1470
0$
#1475
0!
b1010 C
b10 G
b1010 W
b10 [
b10 o
0(
1$
#1480
0$
#1485
b1000 l
1(
b10 n
b11 [
b11 Z
b11 G
b11 F
1$
#1490
0$
#1495
1!
b1001 C
b1001 W
b111 l
1$
#1500
0$
#1505
b110 l
b1000 W
b1000 C
1$
#1510
0$
#1515
b111 C
b111 W
b101 l
1$
#1520
0$
#1525
b100 l
b110 W
b110 C
1$
#1530
0$
#1535
b101 C
b101 W
b11 l
1$
#1540
0$
#1545
b10 l
b100 W
b100 C
1$
#1550
0$
#1555
b11 C
b11 W
b1 l
1$
#1560
0$
#1565
b0 l
b10 W
b10 C
1$
#1570
0$
#1575
b1 C
b1 W
b1001 l
b11 o
1$
#1580
0$
#1585
b10 o
0(
b10 n
b0 W
b0 C
1$
#1590
0$
#1595
b1010 C
b10 G
b1010 W
b10 [
b1000 l
1(
1$
#1600
0$
#1605
b111 l
b11 [
b11 Z
b11 G
b11 F
1$
#1610
0$
#1615
b1001 C
b1001 W
b110 l
1$
#1620
0$
#1625
b101 l
b1000 W
b1000 C
1$
#1630
0$
#1635
b111 C
b111 W
b100 l
1$
#1640
0$
#1645
b11 l
b110 W
b110 C
1$
#1650
0$
#1655
b101 C
b101 W
b10 l
1$
#1660
0$
#1665
b1 l
b100 W
b100 C
1$
#1670
0$
#1675
b11 C
b11 W
b0 l
1$
#1680
0$
#1685
b11 n
b1001 l
b11 o
b10 W
b10 C
1$
#1690
0$
#1695
0!
b1 C
b1 W
b10 o
0(
1$
#1700
0$
#1705
b1000 l
1(
b10 n
b0 W
b0 C
1$
#1710
0$
#1715
1!
b1010 C
b10 G
b1010 W
b10 [
b111 l
1$
#1720
0$
#1725
b110 l
b11 [
b11 Z
b11 G
b11 F
1$
#1730
0$
#1735
b1001 C
b1001 W
b101 l
1$
#1740
0$
#1745
b100 l
b1000 W
b1000 C
1$
#1750
0$
#1755
b111 C
b111 W
b11 l
1$
#1760
0$
#1765
b10 l
b110 W
b110 C
1$
#1770
0$
#1775
b101 C
b101 W
b1 l
1$
#1780
0$
#1785
b0 l
b100 W
b100 C
1$
#1790
0$
#1795
b11 C
b11 W
b1001 l
b11 o
1$
#1800
0$
#1805
b10 o
0(
b10 n
b10 W
b10 C
1$
#1810
0$
#1815
b1 C
b1 W
b1000 l
1(
1$
#1820
0$
#1825
b111 l
b0 W
b0 C
1$
#1830
0$
#1835
b1010 C
b10 G
b1010 W
b10 [
b110 l
1$
#1840
0$
#1845
b101 l
b11 [
b11 Z
b11 G
b11 F
1$
#1850
0$
#1855
b1001 C
b1001 W
b100 l
1$
#1860
0$
#1865
b11 l
b1000 W
b1000 C
1$
#1870
0$
#1875
b111 C
b111 W
b10 l
1$
#1880
0$
#1885
b1 l
b110 W
b110 C
1$
#1890
0$
#1895
b101 C
b101 W
b0 l
1$
#1900
0$
#1905
b11 n
b1001 l
b11 o
b100 W
b100 C
1$
#1910
0$
#1915
0!
b11 C
b11 W
b10 o
0(
1$
#1920
0$
#1925
b1000 l
1(
b10 n
b10 W
b10 C
1$
#1930
0$
#1935
1!
b1 C
b1 W
b111 l
1$
#1940
0$
#1945
b110 l
b0 W
b0 C
1$
#1950
0$
#1955
b1010 C
b10 G
b1010 W
b10 [
b101 l
1$
#1960
0$
#1965
b100 l
b11 [
b11 Z
b11 G
b11 F
1$
#1970
0$
#1975
b1001 C
b1001 W
b11 l
1$
#1980
0$
#1985
b10 l
b1000 W
b1000 C
1$
#1990
0$
#1995
b111 C
b111 W
b1 l
1$
